Workbook
Name Cía: '[1]Gráfico Diario x Marca'!$A$30:$A$32
Name Marca: '[1]Gráfico R Vs C'!$A$18:$A$38
Name Marca2: '[1]Gráfico Diario x Marca'!$A$1:$A$21
Name SKU: '[1]Gráfico R Vs C'!$A$40:$A$116
Name UB: '[1]Gráfico Diario x Marca'!$A$27:$A$28

Sheet Clientes
A1: Número de cliente | B1: Nombre de cliente de maestro de cliente | C1: Nombre corto | D1: SUB-CATEGORIA | E1: Estado o provincia | F1: RUT | G1: CódigoDirección | H1: AÑO COD | I1: CANAL DE DISTRIBUCIÓN | J1: REGIÓN | K1: SUCRUSAL
A2: J317255208 | B2: ADMINISTRADORA SD 1980, C.A | C2: ADMINT SD 1980 | D2: =+VLOOKUP(A2,Tabla3[],18,0) -> CADENAS - SUPERMERCADOS | E2: =+VLOOKUP(A2,Tabla3[],7,0) -> ARAGUA | F2: 20 | G2: 20001 | I2: POR ASIGNAR | J2: CENTRAL | L2: =+A2 -> J317255208
A3: V170806634 | B3: ALARCON DIAZ ERICK | C3: ALARCON ERICK | D3: =+VLOOKUP(A3,Tabla3[],18,0) -> #N/A | E3: =+VLOOKUP(A3,Tabla3[],7,0) -> #N/A | I3: POR ASIGNAR | J3: 0 | L3: =+A3 -> V170806634
A4: V235652923 | B4: ALEXIS RIVAS | C4: ALEXIS RIVAS | D4: =+VLOOKUP(A4,Tabla3[],18,0) -> #N/A | E4: =+VLOOKUP(A4,Tabla3[],7,0) -> #N/A | I4: POR ASIGNAR | J4: 0 | L4: =+A4 -> V235652923
A5: J402835604 | B5: ALIADOS COMERCIALES, C.A. | C5: ALIADOS COMERC | D5: =+VLOOKUP(A5,Tabla3[],18,0) -> DISTRIBUIDOR | E5: =+VLOOKUP(A5,Tabla3[],7,0) -> FALCON | F5: 65 | G5: 65001 | I5: POR ASIGNAR | J5: FALCON | L5: =+A5 -> J402835604
A6: J402802218 | B6: ALIANZA DISTRIBUIDORA C.A | C6: 30 SAN JUAN | D6: =+VLOOKUP(A6,Tabla3[],18,0) -> DISTRIBUIDOR | E6: =+VLOOKUP(A6,Tabla3[],7,0) -> ZULIA | F6: 64 | G6: 64001 | I6: DISTRIBUIDOR | J6: 0 | L6: =+A6 -> J402802218
A7: J312492031 | B7: AMIFARMACIA, C.A. | C7: 65 LOCATEL | D7: =+VLOOKUP(A7,Tabla3[],18,0) -> CADENAS - FARMACIAS | E7: =+VLOOKUP(A7,Tabla3[],7,0) -> CARABOBO | F7: 11 | G7: 11001 | I7: FARMACIA | J7: CENTRAL | L7: =+A7 -> J312492031
A8: V195648545 | B8: ANDERSON SOLAR | C8: ANDERSON SOLAR | D8: =+VLOOKUP(A8,Tabla3[],18,0) -> #N/A | E8: =+VLOOKUP(A8,Tabla3[],7,0) -> #N/A | I8: EMPLEADOS | J8: 0 | L8: =+A8 -> V195648545
A9: V206532960 | B9: ANGI AZZOLLINI | C9: ANGI AZZOLLINI | D9: =+VLOOKUP(A9,Tabla3[],18,0) -> #N/A | E9: =+VLOOKUP(A9,Tabla3[],7,0) -> #N/A | I9: EMPLEADOS | J9: 0 | L9: =+A9 -> V206532960
A10: J298008040 | B10: ARCO SUMINISTROS, C.A. | C10: ARCO SUMINISTRO | D10: =+VLOOKUP(A10,Tabla3[],18,0) -> DISTRIBUIDOR | E10: =+VLOOKUP(A10,Tabla3[],7,0) -> MERIDA | F10: 63 | G10: 63037 | I10: POR ASIGNAR | J10: 0 | L10: =+A10 -> J298008040
A11: J303032338 | B11: ARS PUBLICIDAD VENEZUELA, S.A. | C11: ARS PUBLICIDAD | D11: =+VLOOKUP(A11,Tabla3[],18,0) -> #N/A | E11: =+VLOOKUP(A11,Tabla3[],7,0) -> #N/A | F11: 51 | G11: 51021 | I11: POR ASIGNAR | J11: 0 | L11: =+A11 -> J303032338
A12: J308597724 | B12: ASMEDICAL, C.A. | C12: ASMEDICAL | D12: =+VLOOKUP(A12,Tabla3[],18,0) -> #N/A | E12: =+VLOOKUP(A12,Tabla3[],7,0) -> #N/A | I12: POR ASIGNAR | J12: 0 | L12: =+A12 -> J308597724
A13: J294462847 | B13: ASOC CIVIL CAJA DE AHORRO DEL EJERC BOLIVARIANO | C13: EJERC BOLIVARIA | D13: =+VLOOKUP(A13,Tabla3[],18,0) -> INSTITUCIONAL | E13: =+VLOOKUP(A13,Tabla3[],7,0) -> DISTRITO CAPITAL | F13: 10 | I13: POR ASIGNAR | J13: 0 | L13: =+A13 -> J294462847
A14: J302517079 | B14: ASOCIACION CIVIL HOGAR BAMBI VENEZUELA | C14: HOGAR BAMBI | D14: =+VLOOKUP(A14,Tabla3[],18,0) -> #N/A | E14: =+VLOOKUP(A14,Tabla3[],7,0) -> #N/A | I14: POR ASIGNAR | J14: 0 | L14: =+A14 -> J302517079
A15: J404498923 | B15: ASOCOMPRA ASOCIACIÓN DE COMPRADORES, A.C. | C15: ASOCOMPRA | D15: =+VLOOKUP(A15,Tabla3[],18,0) -> INSTITUCIONAL | E15: =+VLOOKUP(A15,Tabla3[],7,0) -> MIRANDA | F15: 95 | G15: 95001 | I15: POR ASIGNAR | J15: CAPITAL | L15: =+A15 -> J404498923
A16: J075245113 | B16: AUTO MERCADO SAN DIEGO, C.A. | C16: 37 SAN DIEGO | D16: =+VLOOKUP(A16,Tabla3[],18,0) -> CADENAS - SUPERMERCADOS | E16: =+VLOOKUP(A16,Tabla3[],7,0) -> ARAGUA | F16: 12 | G16: 12025 | I16: AUTOMERCADO | J16: CENTRAL | L16: =+A16 -> J075245113
A17: J413118440 | B17: AUTOMERCADO CHINATOWN SAN JUAN 2020, C.A | C17: CHINAT SAN JUAN | D17: =+VLOOKUP(A17,Tabla3[],18,0) -> MAYORISTAS | E17: =+VLOOKUP(A17,Tabla3[],7,0) -> DISTRITO CAPITAL | F17: 58 | G17: 54018 | I17: AUTOMERCADO | J17: CAPITAL | L17: =+A17 -> J413118440
A18: J304983905 | B18: AUTOMERCADO COSMO FRONTERA, C.A | C18: AUT COSMO FRONT | D18: =+VLOOKUP(A18,Tabla3[],18,0) -> SUPERMERCADOS INDEPENDIENTES | E18: =+VLOOKUP(A18,Tabla3[],7,0) -> TACHIRA | F18: 63 | G18: 63029 | I18: AUTOMERCADO | J18: 0 | L18: =+A18 -> J304983905
A19: J000859400 | B19: AUTOMERCADO EL PATIO LOS PALOS GRANDES | C19: 70 EL PATIO | D19: =+VLOOKUP(A19,Tabla3[],18,0) -> CADENAS - SUPERMERCADOS | E19: =+VLOOKUP(A19,Tabla3[],7,0) -> MIRANDA | F19: 57 | G19: 50001 | I19: AUTOMERCADO | J19: CAPITAL | L19: =+A19 -> J000859400
A20: J003720224 | B20: AUTOMERCADO LA MURALLA C.A. | C20: AUT LA MURALLA | D20: =+VLOOKUP(A20,Tabla3[],18,0) -> SUPERMERCADOS INDEPENDIENTES | E20: =+VLOOKUP(A20,Tabla3[],7,0) -> MIRANDA | F20: 57 | G20: 50026 | H20: 2019 | I20: AUTOMERCADO | J20: CAPITAL | L20: =+A20 -> J003720224
A21: J000811601 | B21: AUTOMERCADO LUZ C.A. | C21: AUTOMERCADO LUZ | D21: =+VLOOKUP(A21,Tabla3[],18,0) -> CADENAS - SUPERMERCADOS | E21: =+VLOOKUP(A21,Tabla3[],7,0) -> MIRANDA | F21: 50 | G21: 50002 | I21: AUTOMERCADO | J21: CAPITAL | L21: =+A21 -> J000811601
A22: J000537585 | B22: AUTOMERCADO SAN LORENZO C.A. | C22: AUT SAN LORENZO | D22: =+VLOOKUP(A22,Tabla3[],18,0) -> SUPERMERCADOS INDEPENDIENTES | E22: =+VLOOKUP(A22,Tabla3[],7,0) -> MIRANDA | F22: 57 | G22: 50003 | I22: AUTOMERCADO | J22: CAPITAL | L22: =+A22 -> J000537585
A23: J002099712 | B23: AUTOMERCADO SANTA ROSA DE LIMA C.A | C23: STA ROSA LIMA | D23: =+VLOOKUP(A23,Tabla3[],18,0) -> SUPERMERCADOS INDEPENDIENTES | E23: =+VLOOKUP(A23,Tabla3[],7,0) -> MIRANDA | F23: 57 | G23: 50004 | I23: AUTOMERCADO | J23: CAPITAL | L23: =+A23 -> J002099712
A24: J314301870 | B24: AUTOMERCADO SUPER EXITO COMPAÑIA ANONIMA | C24: AUT SUPER EXITO | D24: =+VLOOKUP(A24,Tabla3[],18,0) -> #N/A | E24: =+VLOOKUP(A24,Tabla3[],7,0) -> #N/A | I24: AUTOMERCADO | J24: 0 | L24: =+A24 -> J314301870
A25: J298782366 | B25: AUTOMERCADOS FRESCO MARKET AFN C.A. | C25: 66 FRESC.MARKET | D25: =+VLOOKUP(A25,Tabla3[],18,0) -> SUPERMERCADOS INDEPENDIENTES | E25: =+VLOOKUP(A25,Tabla3[],7,0) -> MIRANDA | F25: 10 | G25: 51001 | I25: AUTOMERCADO | J25: 0 | L25: =+A25 -> J298782366
A26: J305113530 | B26: AUTOMERCADOS KLASSE, C.A. | C26: AUT KLASSE | D26: =+VLOOKUP(A26,Tabla3[],18,0) -> SUPERMERCADOS INDEPENDIENTES | E26: =+VLOOKUP(A26,Tabla3[],7,0) -> MIRANDA | F26: 50 | G26: 50005 | I26: AUTOMERCADO | J26: 0 | L26: =+A26 -> J305113530
A27: J306725024 | B27: AUTOMERCADOS PLAZA'S, C.A. | C27: 42 PLAZA | D27: =+VLOOKUP(A27,Tabla3[],18,0) -> CADENAS - SUPERMERCADOS | E27: =+VLOOKUP(A27,Tabla3[],7,0) -> MIRANDA | F27: 10 | G27: 10040 | I27: AUTOMERCADO | J27: CAPITAL | L27: =+A27 -> J306725024
A28: J407238035 | B28: AUTOMERCADOS SUPER REY VALENCIA C,A | C28: AUTOM SUPER REY | D28: =+VLOOKUP(A28,Tabla3[],18,0) -> SUPERMERCADOS INDEPENDIENTES | E28: =+VLOOKUP(A28,Tabla3[],7,0) -> CARABOBO | F28: 20 | G28: 20053 | I28: AUTOMERCADO | J28: CENTRAL | L28: =+A28 -> J407238035
A29: J316324311 | B29: AUTOMERCADOS SUPER REY, C.A | C29: AUTOM SUPER REY | D29: =+VLOOKUP(A29,Tabla3[],18,0) -> SUPERMERCADOS INDEPENDIENTES | E29: =+VLOOKUP(A29,Tabla3[],7,0) -> ARAGUA | F29: 20 | G29: 20022 | I29: AUTOMERCADO | J29: CENTRAL | L29: =+A29 -> J316324311
A30: J310186839 | B30: AUTOSALUD FARMACIA, C.A. | C30: 65 LOCATEL | D30: =+VLOOKUP(A30,Tabla3[],18,0) -> CADENAS - FARMACIAS | E30: =+VLOOKUP(A30,Tabla3[],7,0) -> CARABOBO | F30: 11 | G30: 11002 | I30: AUTOMERCADO | J30: 0 | L30: =+A30 -> J310186839
A31: J316786110 | B31: AVILA PINTURAS, C.A. | C31: AVILA PINTURA | D31: =+VLOOKUP(A31,Tabla3[],18,0) -> INSTITUCIONAL | E31: =+VLOOKUP(A31,Tabla3[],7,0) -> MIRANDA | F31: 95 | G31: 95012 | I31: POR ASIGNAR | J31: 0 | L31: =+A31 -> J316786110
A32: V069096979 | B32: BAENA FERRER ELIZABETH | C32: BAENA ELIZABETH | D32: =+VLOOKUP(A32,Tabla3[],18,0) -> #N/A | E32: =+VLOOKUP(A32,Tabla3[],7,0) -> #N/A | I32: EMPLEADOS | J32: 0 | L32: =+A32 -> V069096979
A33: G200001100 | B33: BANCO CENTRAL DE VENEZUELA | C33: BCO CTRAL VZLA | D33: =+VLOOKUP(A33,Tabla3[],18,0) -> INSTITUCIONAL | E33: =+VLOOKUP(A33,Tabla3[],7,0) -> DISTRITO CAPITAL | F33: 63 | G33: 63032 | I33: POR ASIGNAR | J33: 0 | L33: =+A33 -> G200001100
A34: G200051876 | B34: BANCO DEL TESORO, C.A BANCO UNIVERSAL | C34: BCO TESORO | D34: =+VLOOKUP(A34,Tabla3[],18,0) -> #N/A | E34: =+VLOOKUP(A34,Tabla3[],7,0) -> #N/A | F34: 11 | G34: 11051 | I34: POR ASIGNAR | J34: 0 | L34: =+A34 -> G200051876
A35: J314850890 | B35: BARINTEL FARMACIA, C.A. | C35: 65 LOCATEL | D35: =+VLOOKUP(A35,Tabla3[],18,0) -> CADENAS - FARMACIAS | E35: =+VLOOKUP(A35,Tabla3[],7,0) -> BARINAS | F35: 23 | G35: 23018 | I35: FARMACIA | J35: LLANOS | L35: =+A35 -> J314850890
A36: V134733000 | B36: BARRIOS O VANESSA MILAGROS | C36: BARRIOS VANESSA | D36: =+VLOOKUP(A36,Tabla3[],18,0) -> #N/A | E36: =+VLOOKUP(A36,Tabla3[],7,0) -> #N/A | I36: EMPLEADOS | J36: 0 | L36: =+A36 -> V134733000
A37: J314527363 | B37: BAZAR AVANZA, C.A. | C37: BAZAR AVANZA | D37: =+VLOOKUP(A37,Tabla3[],18,0) -> MAYORISTAS | E37: =+VLOOKUP(A37,Tabla3[],7,0) -> ARAGUA | F37: 60 | G37: 60001 | I37: POR ASIGNAR | J37: CENTRAL | L37: =+A37 -> J314527363
A38: J000723060 | B38: BFC BANCO FONDO COMUN C.A., BANCO UNIVERSAL | C38: BCO BFC | D38: =+VLOOKUP(A38,Tabla3[],18,0) -> #N/A | E38: =+VLOOKUP(A38,Tabla3[],7,0) -> #N/A | F38: 10 | G38: 10033 | I38: POR ASIGNAR | J38: 0 | L38: =+A38 -> J000723060
A39: V193356156 | B39: BIDROGO MACHUCA JORGE LUIS | C39: BIDROGO JORGE | D39: =+VLOOKUP(A39,Tabla3[],18,0) -> #N/A | E39: =+VLOOKUP(A39,Tabla3[],7,0) -> #N/A | I39: EMPLEADOS | J39: 0 | L39: =+A39 -> V193356156
A40: J410939648 | B40: BIG DISTRIBUCIONES, CA | C40: BIG DISTRIB | D40: =+VLOOKUP(A40,Tabla3[],18,0) -> DISTRIBUIDOR | E40: =+VLOOKUP(A40,Tabla3[],7,0) -> ZULIA | F40: 62 | H40: 2019 | I40: DISTRIBUIDOR | J40: 0 | L40: =+A40 -> J410939648
A41: J311205268 | B41: BLITZ 2010 C.A. | C41: BLITZ 2010 | D41: =+VLOOKUP(A41,Tabla3[],18,0) -> DISTRIBUIDOR | E41: =+VLOOKUP(A41,Tabla3[],7,0) -> GUARICO | F41: 61 | G41: 61002 | I41: POR ASIGNAR | J41: CENTRO | L41: =+A41 -> J311205268
A42: J411076112 | B42: BOGA COSMETICS C.A | C42: 30 SAN JUAN | D42: =+VLOOKUP(A42,Tabla3[],18,0) -> DISTRIBUIDOR | E42: =+VLOOKUP(A42,Tabla3[],7,0) -> ZULIA | F42: 65 | G42: 65020 | H42: 2019 | I42: POR ASIGNAR | J42: ZULIA | L42: =+A42 -> J411076112
A43: V105383580 | B43: BRICEÑO ANDRADE ADRIAN A | C43: BRICEÃ‘O ADRIAN | D43: =+VLOOKUP(A43,Tabla3[],18,0) -> #N/A | E43: =+VLOOKUP(A43,Tabla3[],7,0) -> #N/A | I43: EMPLEADOS | J43: 0 | L43: =+A43 -> V105383580
A44: J070012250 | B44: C.A. MAFARTA | C44: 13 COBECA | D44: =+VLOOKUP(A44,Tabla3[],18,0) -> DROGUERIAS | E44: =+VLOOKUP(A44,Tabla3[],7,0) -> TACHIRA | F44: 21 | G44: 21001 | I44: POR ASIGNAR | J44: ANDES | L44: =+A44 -> J070012250
A45: J070003448 | B45: CA CERVECERIA REGIONAL | C45: CERV REGIONAL | D45: =+VLOOKUP(A45,Tabla3[],18,0) -> #N/A | E45: =+VLOOKUP(A45,Tabla3[],7,0) -> #N/A | F45: 51 | G45: 51016 | I45: POR ASIGNAR | J45: 0 | L45: =+A45 -> J070003448
A46: V197201033 | B46: CABALLERO SANCHEZ WALTER | C46: CABALLERO WALTE | D46: =+VLOOKUP(A46,Tabla3[],18,0) -> #N/A | E46: =+VLOOKUP(A46,Tabla3[],7,0) -> #N/A | I46: EMPLEADOS | J46: 0 | L46: =+A46 -> V197201033
A47: V124957326 | B47: CABRERA MARTINEZ MICHAEL | C47: CABRERA MICHAEL | D47: =+VLOOKUP(A47,Tabla3[],18,0) -> #N/A | E47: =+VLOOKUP(A47,Tabla3[],7,0) -> #N/A | I47: EMPLEADOS | J47: 0 | L47: =+A47 -> V124957326
A48: J309456440 | B48: CAFOCO TG | C48: CAFOCO TG | D48: =+VLOOKUP(A48,Tabla3[],18,0) -> #N/A | E48: =+VLOOKUP(A48,Tabla3[],7,0) -> #N/A | F48: 11 | G48: 11049 | I48: POR ASIGNAR | J48: 0 | L48: =+A48 -> J309456440
A49: J400023181 | B49: CAJA DE AHORRO DE LA FUNDACION MISION NEGRA HIPOLITA CAMINEH | C49: NEGRA HIPOLITA | D49: =+VLOOKUP(A49,Tabla3[],18,0) -> #N/A | E49: =+VLOOKUP(A49,Tabla3[],7,0) -> #N/A | F49: 10 | G49: 10031 | I49: POR ASIGNAR | J49: 0 | L49: =+A49 -> J400023181
A50: J000745471 | B50: CAJA DE AHORRO DEL PERSONAL DEL BANCO NAC. DE VIVIENDA Y HABITAT | C50: BCO NAC VIVIEND | D50: =+VLOOKUP(A50,Tabla3[],18,0) -> INSTITUCIONAL | E50: =+VLOOKUP(A50,Tabla3[],7,0) -> MIRANDA | F50: 95 | G50: 95002 | I50: POR ASIGNAR | J50: 0 | L50: =+A50 -> J000745471
A51: J312217987 | B51: CAJA DE AHORRO Y CREDITOS DE LOS TRABAJADORES DE BFC | C51: BCO BFC | D51: =+VLOOKUP(A51,Tabla3[],18,0) -> #N/A | E51: =+VLOOKUP(A51,Tabla3[],7,0) -> #N/A | F51: 10 | G51: 10030 | I51: POR ASIGNAR | J51: 0 | L51: =+A51 -> J312217987
A52: V193991510 | B52: CALDERA DIAZ KATHERINE | C52: CALDERA KATHERI | D52: =+VLOOKUP(A52,Tabla3[],18,0) -> #N/A | E52: =+VLOOKUP(A52,Tabla3[],7,0) -> #N/A | I52: EMPLEADOS | J52: 0 | L52: =+A52 -> V193991510
A53: V070767941 | B53: CALDERON FONSECA DULCE MARIA | C53: CALDERON DULCE | D53: =+VLOOKUP(A53,Tabla3[],18,0) -> #N/A | E53: =+VLOOKUP(A53,Tabla3[],7,0) -> #N/A | I53: EMPLEADOS | J53: 0 | L53: =+A53 -> V070767941
A54: J295326394 | B54: CAMPERO, C.A. | C54: CAMPERO | D54: =+VLOOKUP(A54,Tabla3[],18,0) -> DISTRIBUIDOR | E54: =+VLOOKUP(A54,Tabla3[],7,0) -> CARABOBO | F54: 61 | G54: 61010 | I54: POR ASIGNAR | J54: 0 | L54: =+A54 -> J295326394
A55: V153947488 | B55: CARDENAS SURMAI INGRIS DEL V | C55: CARDENAS INGRIS | D55: =+VLOOKUP(A55,Tabla3[],18,0) -> #N/A | E55: =+VLOOKUP(A55,Tabla3[],7,0) -> #N/A | I55: EMPLEADOS | J55: 0 | L55: =+A55 -> V153947488
A56: J412770756 | B56: CAREPHARMA, C.A. | C56: CAREPHARMA, C.A | D56: =+VLOOKUP(A56,Tabla3[],18,0) -> FARMACIAS INDEPENDIENTES | E56: =+VLOOKUP(A56,Tabla3[],7,0) -> MIRANDA | G56: 11040 | I56: INACTIVO | J56: CAPITAL | L56: =+A56 -> J412770756
A57: V101757230 | B57: CARLOS GOMEZ | C57: CARLOS GOMEZ | D57: =+VLOOKUP(A57,Tabla3[],18,0) -> #N/A | E57: =+VLOOKUP(A57,Tabla3[],7,0) -> #N/A | I57: EMPLEADOS | J57: 0 | L57: =+A57 -> V101757230
A58: J313749192 | B58: CARTOFORMAS VENEZOLANAS, C.A. | C58: CARTOFORMAS | D58: =+VLOOKUP(A58,Tabla3[],18,0) -> #N/A | E58: =+VLOOKUP(A58,Tabla3[],7,0) -> #N/A | F58: 96 | G58: 96002 | I58: POR ASIGNAR | J58: 0 | L58: =+A58 -> J313749192
A59: J000056668 | B59: CARTON DE VENEZUELA, S.A. | C59: CARTON DE VZLA | D59: =+VLOOKUP(A59,Tabla3[],18,0) -> #N/A | E59: =+VLOOKUP(A59,Tabla3[],7,0) -> #N/A | F59: 96 | G59: 96001 | I59: POR ASIGNAR | J59: 0 | L59: =+A59 -> J000056668
A60: J311086056 | B60: CASA DE OBLEA, C.A. | C60: CASA DE OBLEA | D60: =+VLOOKUP(A60,Tabla3[],18,0) -> #N/A | E60: =+VLOOKUP(A60,Tabla3[],7,0) -> #N/A | F60: 50 | G60: 50016 | I60: POR ASIGNAR | J60: 0 | L60: =+A60 -> J311086056
A61: J308537853 | B61: CASA TOKIO HIPERMERCADO 2, C.A | C61: CASA TOKIO HIP | D61: =+VLOOKUP(A61,Tabla3[],18,0) -> SUPERMERCADOS INDEPENDIENTES | E61: =+VLOOKUP(A61,Tabla3[],7,0) -> DISTRITO CAPITAL | F61: 58 | G61: 51002 | I61: POR ASIGNAR | J61: CAPITAL | L61: =+A61 -> J308537853
A62: V192091418 | B62: CASTRO ROCHE RICARDO | C62: CASTRO RICARDO | D62: =+VLOOKUP(A62,Tabla3[],18,0) -> #N/A | E62: =+VLOOKUP(A62,Tabla3[],7,0) -> #N/A | I62: EMPLEADOS | J62: 0 | L62: =+A62 -> V192091418
A63: J404278923 | B63: CATTFAVILATVE CAJA DE AHORRO DE LOS TRABJS DE LA FUND. AVILA TVE | C63: CATTFAVILATVE | D63: =+VLOOKUP(A63,Tabla3[],18,0) -> #N/A | E63: =+VLOOKUP(A63,Tabla3[],7,0) -> #N/A | F63: 51 | G63: 51017 | I63: POR ASIGNAR | J63: 0 | L63: =+A63 -> J404278923
A64: J310030090 | B64: CENTRAL EL LOTO DE GUAYANA C.A. | C64: C LOTO GUAYANA | D64: =+VLOOKUP(A64,Tabla3[],18,0) -> MAYORISTAS | E64: =+VLOOKUP(A64,Tabla3[],7,0) -> BOLIVAR | F64: 53 | G64: 53001 | I64: POR ASIGNAR | J64: ORIENTE | L64: =+A64 -> J310030090
A65: J000062757 | B65: CENTRAL MADEIRENSE, C.A. | C65: 02 MADEIRENSE | D65: =+VLOOKUP(A65,Tabla3[],18,0) -> CADENAS - SUPERMERCADOS | E65: =+VLOOKUP(A65,Tabla3[],7,0) -> MIRANDA | F65: 11 | G65: 11003 | I65: POR ASIGNAR | J65: 0 | L65: =+A65 -> J000062757
A66: J095130029 | B66: CENTRAL SANTO TOME I,C.A. | C66: 29 CTRAL.S/TOME | D66: =+VLOOKUP(A66,Tabla3[],18,0) -> #N/A | E66: =+VLOOKUP(A66,Tabla3[],7,0) -> #N/A | F66: 53 | G66: 53002 | I66: POR ASIGNAR | J66: GUAYANA | L66: =+A66 -> J095130029
A67: J308793728 | B67: CENTRAL SANTO TOME II, C.A | C67: 29 CTRAL.S/TOME | D67: =+VLOOKUP(A67,Tabla3[],18,0) -> #N/A | E67: =+VLOOKUP(A67,Tabla3[],7,0) -> #N/A | F67: 53 | G67: 53003 | I67: POR ASIGNAR | J67: GUAYANA | L67: =+A67 -> J308793728
A68: J095124614 | B68: CENTRAL SANTO TOME III,C.A. | C68: 29 CTRAL.S/TOME | D68: =+VLOOKUP(A68,Tabla3[],18,0) -> CADENAS - SUPERMERCADOS | E68: =+VLOOKUP(A68,Tabla3[],7,0) -> BOLIVAR | F68: 52 | G68: 53004 | I68: POR ASIGNAR | J68: ORIENTE SUR | L68: =+A68 -> J095124614
A69: J304836899 | B69: CENTRAL SANTO TOME IV, C.A. | C69: 29 CTRAL.S/TOME | D69: =+VLOOKUP(A69,Tabla3[],18,0) -> #N/A | E69: =+VLOOKUP(A69,Tabla3[],7,0) -> #N/A | F69: 53 | G69: 53005 | I69: POR ASIGNAR | J69: GUAYANA | L69: =+A69 -> J304836899
A70: V148906390 | B70: CESAR ARMAS | C70: CESAR ARMAS | D70: =+VLOOKUP(A70,Tabla3[],18,0) -> #N/A | E70: =+VLOOKUP(A70,Tabla3[],7,0) -> #N/A | I70: EMPLEADOS | J70: 0 | L70: =+A70 -> V148906390
A71: J070137290 | B71: CHARCUTERIA FINA, C.A. | C71: CHARCUTERI FINA | D71: =+VLOOKUP(A71,Tabla3[],18,0) -> DISTRIBUIDOR | E71: =+VLOOKUP(A71,Tabla3[],7,0) -> ZULIA | F71: 62 | G71: 62033 | H71: 2019 | I71: POR ASIGNAR | J71: ZULIA | L71: =+A71 -> J070137290
A72: J303665012 | B72: COLEGIO INTEGRAL EL AVILA | C72: COLEG EL AVILA | D72: =+VLOOKUP(A72,Tabla3[],18,0) -> INSTITUCIONAL | E72: =+VLOOKUP(A72,Tabla3[],7,0) -> MIRANDA | F72: 95 | G72: 95006 | I72: POR ASIGNAR | J72: 0 | L72: =+A72 -> J303665012
A73: J298991569 | B73: COMERCIAL BIG BANG, C.A | C73: COM BIG BANG | D73: =+VLOOKUP(A73,Tabla3[],18,0) -> PERFUMERIAS INDEPENDIENTES | E73: =+VLOOKUP(A73,Tabla3[],7,0) -> DISTRITO CAPITAL | F73: 58 | G73: 50029 | I73: DISTRIBUIDOR | J73: CAPITAL | L73: =+A73 -> J298991569
A74: J313189260 | B74: COMERCIAL CENTRO-CENTRO, C.A | C74: C CENTRO-CENTRO | D74: =+VLOOKUP(A74,Tabla3[],18,0) -> SUPERMERCADOS INDEPENDIENTES | E74: =+VLOOKUP(A74,Tabla3[],7,0) -> DISTRITO CAPITAL | F74: 58 | G74: 51027 | I74: INDEPENDIENTE | J74: CAPITAL | L74: =+A74 -> J313189260
A75: J085323783 | B75: COMERCIAL CHALIKI, C.A. | C75: 54 CHALIKI | D75: =+VLOOKUP(A75,Tabla3[],18,0) -> MAYORISTAS | E75: =+VLOOKUP(A75,Tabla3[],7,0) -> LARA | F75: 23 | G75: 23002 | I75: POR ASIGNAR | J75: CENTRAL | L75: =+A75 -> J085323783
A76: J304015623 | B76: COMERCIAL ERIFAT EA,C.A | C76: COMER ERIFAT EA | D76: =+VLOOKUP(A76,Tabla3[],18,0) -> DISTRIBUIDOR | E76: =+VLOOKUP(A76,Tabla3[],7,0) -> DISTRITO CAPITAL | G76: 50040 | I76: INDEPENDIENTE | J76: CAPITAL | L76: =+A76 -> J304015623
A77: J306927093 | B77: COMERCIAL HONG KONG, C.A. | C77: COM HONG KONG | D77: =+VLOOKUP(A77,Tabla3[],18,0) -> PERFUMERIAS INDEPENDIENTES | E77: =+VLOOKUP(A77,Tabla3[],7,0) -> LARA | F77: 62 | G77: 62001 | I77: POR ASIGNAR | J77: CENTRO-OCCIDENTE | L77: =+A77 -> J306927093
A78: J080183150 | B78: COMERCIAL INDRIAGO C.A. | C78: COM INDRIAGO | D78: =+VLOOKUP(A78,Tabla3[],18,0) -> #N/A | E78: =+VLOOKUP(A78,Tabla3[],7,0) -> #N/A | F78: 52 | G78: 53006 | I78: POR ASIGNAR | J78: 0 | L78: =+A78 -> J080183150
A79: J302754550 | B79: COMERCIAL LA GRAN PARADA, C.A. | C79: 67 GRAN PARADA | D79: =+VLOOKUP(A79,Tabla3[],18,0) -> MAYORISTAS | E79: =+VLOOKUP(A79,Tabla3[],7,0) -> TACHIRA | F79: 63 | G79: 63002 | I79: POR ASIGNAR | J79: ANDES | L79: =+A79 -> J302754550
A80: J095012735 | B80: COMERCIAL LOUMY, C.A. | C80: COMERC LOUMY | D80: =+VLOOKUP(A80,Tabla3[],18,0) -> #N/A | E80: =+VLOOKUP(A80,Tabla3[],7,0) -> #N/A | F80: 53 | G80: 53026 | I80: POR ASIGNAR | J80: GUAYANA | L80: =+A80 -> J095012735
A81: J306456597 | B81: COMERCIAL LUCKY STAR, C.A | C81: COM LUCKY STAR | D81: =+VLOOKUP(A81,Tabla3[],18,0) -> PERFUMERIAS INDEPENDIENTES | E81: =+VLOOKUP(A81,Tabla3[],7,0) -> DISTRITO CAPITAL | G81: 50028 | I81: INDEPENDIENTE | J81: CAPITAL | L81: =+A81 -> J306456597
A82: J309086456 | B82: COMERCIAL MAXI, C.A. | C82: COMERCIAL MAXI | D82: =+VLOOKUP(A82,Tabla3[],18,0) -> PERFUMERIAS INDEPENDIENTES | E82: =+VLOOKUP(A82,Tabla3[],7,0) -> ZULIA | F82: 64 | G82: 64003 | I82: POR ASIGNAR | J82: 0 | L82: =+A82 -> J309086456
A83: J305106266 | B83: COMERCIAL ORIENTE DEL CENTRO, C.A. | C83: COM ORIENTE CEN | D83: =+VLOOKUP(A83,Tabla3[],18,0) -> DISTRIBUIDOR | E83: =+VLOOKUP(A83,Tabla3[],7,0) -> LARA | F83: 62 | G83: 62019 | I83: POR ASIGNAR | J83: CENTRO-OCCIDENTE | L83: =+A83 -> J305106266
A84: J003126829 | B84: COMERCIAL PAGA POCO,C.A. | C84: COM PAGA POCO | D84: =+VLOOKUP(A84,Tabla3[],18,0) -> #N/A | E84: =+VLOOKUP(A84,Tabla3[],7,0) -> #N/A | F84: 50 | G84: 50006 | I84: POR ASIGNAR | J84: 0 | L84: =+A84 -> J003126829
A85: J070304162 | B85: COMERCIAL REYES, C.A. | C85: 09 C. REYES | D85: =+VLOOKUP(A85,Tabla3[],18,0) -> CADENAS - SUPERMERCADOS | E85: =+VLOOKUP(A85,Tabla3[],7,0) -> ZULIA | F85: 21 | G85: 21041 | I85: POR ASIGNAR | J85: 0 | L85: =+A85 -> J070304162
A86: J406180874 | B86: COMERCIAL RIO 21, C.A. | C86: COMERC RIO 21 | D86: =+VLOOKUP(A86,Tabla3[],18,0) -> #N/A | E86: =+VLOOKUP(A86,Tabla3[],7,0) -> #N/A | F86: 62 | G86: 62020 | I86: POR ASIGNAR | J86: CENTRO-OCCIDENTE | L86: =+A86 -> J406180874
A87: J317512448 | B87: COMERCIAL TODO HOGAR K.R 28, C.A. | C87: TODO HOGAR KR28 | D87: =+VLOOKUP(A87,Tabla3[],18,0) -> DISTRIBUIDOR | E87: =+VLOOKUP(A87,Tabla3[],7,0) -> DISTRITO CAPITAL | G87: 50030 | I87: INDEPENDIENTE | J87: CAPITAL | L87: =+A87 -> J317512448
A88: J317194985 | B88: COMERCIAL VICTORIA HL C.A | C88: COM VICTORIA HL | D88: =+VLOOKUP(A88,Tabla3[],18,0) -> PERFUMERIAS INDEPENDIENTES | E88: =+VLOOKUP(A88,Tabla3[],7,0) -> LARA | F88: 23 | G88: 23015 | I88: POR ASIGNAR | J88: CENTRAL | L88: =+A88 -> J317194985
A89: J298396440 | B89: COMERCIAL WYNN, C.A. | C89: COMERCIAL WYNN | D89: =+VLOOKUP(A89,Tabla3[],18,0) -> PERFUMERIAS INDEPENDIENTES | E89: =+VLOOKUP(A89,Tabla3[],7,0) -> DISTRITO CAPITAL | F89: 58 | G89: 54020 | I89: INDEPENDIENTE | J89: CAPITAL | L89: =+A89 -> J298396440
A90: J297781862 | B90: COMERCIALIZADORA 969, C.A. | C90: 40 COMERC. 969 | D90: =+VLOOKUP(A90,Tabla3[],18,0) -> #N/A | E90: =+VLOOKUP(A90,Tabla3[],7,0) -> #N/A | I90: POR ASIGNAR | J90: 0 | L90: =+A90 -> J297781862
A91: J297600760 | B91: COMERCIALIZADORA AMIR, C.A. | C91: COMERC AMIR | D91: =+VLOOKUP(A91,Tabla3[],18,0) -> DISTRIBUIDOR | E91: =+VLOOKUP(A91,Tabla3[],7,0) -> FALCON | F91: 65 | G91: 65014 | I91: POR ASIGNAR | J91: 0 | L91: =+A91 -> J297600760
A92: J310071381 | B92: COMERCIALIZADORA CENTRO GUARENAS, C.A. | C92: C CTRO GUARENAS | D92: =+VLOOKUP(A92,Tabla3[],18,0) -> SUPERMERCADOS INDEPENDIENTES | E92: =+VLOOKUP(A92,Tabla3[],7,0) -> MIRANDA | F92: 56 | G92: 50007 | I92: POR ASIGNAR | J92: CAPITAL | L92: =+A92 -> J310071381
A93: J304303840 | B93: COMERCIALIZADORA DE ALIMENTOS ARUMA C.A. | C93: COM ALIM ARUMA | D93: =+VLOOKUP(A93,Tabla3[],18,0) -> DISTRIBUIDOR | E93: =+VLOOKUP(A93,Tabla3[],7,0) -> MIRANDA | F93: 54 | G93: 54026 | H93: 2020 | J93: CAPITAL | L93: =+A93 -> J304303840
A94: J294014518 | B94: COMERCIALIZADORA DURACENTRO, C.A | C94: COM DURACENTRO | D94: =+VLOOKUP(A94,Tabla3[],18,0) -> #N/A | E94: =+VLOOKUP(A94,Tabla3[],7,0) -> #N/A | F94: 61 | G94: 61003 | I94: POR ASIGNAR | J94: 0 | L94: =+A94 -> J294014518
A95: J409587690 | B95: COMERCIALIZADORA GRAN PROSPERIDAD, C.A | C95: COM GRAN PROSPE | D95: =+VLOOKUP(A95,Tabla3[],18,0) -> DISTRIBUIDOR | E95: =+VLOOKUP(A95,Tabla3[],7,0) -> TRUJILLO | F95: 62 | G95: 62022 | H95: 2019 | I95: POR ASIGNAR | J95: ANDES | L95: =+A95 -> J409587690
A96: J408086379 | B96: COMERCIALIZADORA HECHOS, C.A | C96: COMERC HECHOS | D96: =+VLOOKUP(A96,Tabla3[],18,0) -> DISTRIBUIDOR | E96: =+VLOOKUP(A96,Tabla3[],7,0) -> ZULIA | F96: 62 | G96: 62040 | H96: 2019 | I96: POR ASIGNAR | J96: ZULIA | L96: =+A96 -> J408086379
A97: J307145757 | B97: COMERCIALIZADORA KROMI MARKET, C.A. | C97: 81 KROM.MARKET | D97: =+VLOOKUP(A97,Tabla3[],18,0) -> CADENAS - SUPERMERCADOS | E97: =+VLOOKUP(A97,Tabla3[],7,0) -> CARABOBO | F97: 20 | G97: 20020 | I97: POR ASIGNAR | J97: CENTRAL | L97: =+A97 -> J307145757
A98: J405584017 | B98: COMERCIALIZADORA LA OCCIDENTAL,C.A | C98: COM OCCIDENTAL | D98: =+VLOOKUP(A98,Tabla3[],18,0) -> DISTRIBUIDOR | E98: =+VLOOKUP(A98,Tabla3[],7,0) -> ZULIA | F98: 65 | G98: 65017 | I98: POR ASIGNAR | J98: 0 | L98: =+A98 -> J405584017
A99: J303615600 | B99: COMERCIALIZADORA LIMPIA TODO, C.A. | C99: 68 LIMPIA TODO | D99: =+VLOOKUP(A99,Tabla3[],18,0) -> CADENAS - PERFUMERIAS | E99: =+VLOOKUP(A99,Tabla3[],7,0) -> ANZOATEGUI | F99: 52 | G99: 52001 | I99: POR ASIGNAR | J99: ORIENTE | L99: =+A99 -> J303615600
A100: J307012676 | B100: COMERCIALIZADORA ROMERO 2000,C.A. | C100: COM ROMERO 2000 | D100: =+VLOOKUP(A100,Tabla3[],18,0) -> MAYORISTAS | E100: =+VLOOKUP(A100,Tabla3[],7,0) -> TACHIRA | F100: 63 | G100: 63003 | I100: POR ASIGNAR | J100: ANDES | L100: =+A100 -> J307012676
...

Sheet CLIENTES NUEVA ID ZONA
A1: Número de cliente | B1: Nombre de cliente de maestro de cliente | C1: ID ASESOR ANTERIOR | D1: NUEVA RUTA | E1: NUEVO ASESOR | F1: NUEVO GERENTE | G1: Estado o provincia | H1: REGIÓN | I1: NOMBRE CORTO | J1: ZONA COBRANZA | K1: ASESOR COBRANZA | L1: POTENCIAL ZONA | M1: CONVENIO | N1: Clase de cliente | O1: Días crédito | P1: FRECUENCIA | Q1: APTO | R1: Desc Clase de Cliente | S1: Dirección 1 | T1: Dirección 2 | U1: Ciudad | V1: Observaciones
A2: J413213850 | B2: 3J DISTRIBUCIONES, C.A. | C2: 98 | D2: 98 | E2: =VLOOKUP($D2,'ESTRUCTURA P&B - LP'!$A$1:$F$31,5,0) -> INACTIVO | F2: =VLOOKUP($D2,'ESTRUCTURA P&B - LP'!$A$1:$F$31,6,0) -> INACTIVO | G2: MERIDA | H2: =VLOOKUP(Tabla3[[#This Row],[NUEVA RUTA]],Tabla1[#All],2,0) -> INACTIVO | I2: =VLOOKUP($A2,Clientes!$A$1:$C$1999,3,0) -> 3J DISTRIBUCION | J2: 61 | K2: =VLOOKUP($J2,'ESTRUCTURA P&B - LP'!$A$1:$F$40,5,0) -> JOSEPH PADILLA 61 | L2: =IFERROR(VLOOKUP($J2,'[2]POTENCIAL X ZONA'!$B$4:$G$21,6,0),0) -> P | M2: =IFERROR(VLOOKUP($A2,'Convenio Clientes'!$D:$F,3,0),"SN CNV") -> 21 | N2: 07 | O2: 15 | P2: INACTIVO | Q2: NO | R2: =VLOOKUP($N2,Tabla2[#All],3,0) -> DISTRIBUIDOR | S2: AV INTERCOMUNAL TURMERO MARACAY CC | T2: BOAVENTURA PB LOC 1 SECTOR ENCRUCIJADA | U2: MERIDA
A3: J317255208 | B3: ADMINISTRADORA SD 1980, C.A | C3: 98 | D3: 98 | E3: =VLOOKUP($D3,'ESTRUCTURA P&B - LP'!$A$1:$F$31,5,0) -> INACTIVO | F3: =VLOOKUP($D3,'ESTRUCTURA P&B - LP'!$A$1:$F$31,6,0) -> INACTIVO | G3: ARAGUA | H3: =VLOOKUP(Tabla3[[#This Row],[NUEVA RUTA]],Tabla1[#All],2,0) -> INACTIVO | I3: =VLOOKUP($A3,Clientes!$A$1:$C$1999,3,0) -> ADMINT SD 1980 | J3: 0 | K3: =VLOOKUP($J3,'ESTRUCTURA P&B - LP'!$A$1:$F$40,5,0) -> INACTIVO | L3: =IFERROR(VLOOKUP($J3,'[2]POTENCIAL X ZONA'!$B$4:$G$21,6,0),0) -> 0 | M3: =IFERROR(VLOOKUP($A3,'Convenio Clientes'!$D:$F,3,0),"SN CNV") -> 01 | N3: 03 | O3: 0 | P3: INACTIVO | Q3: NO | R3: =VLOOKUP($N3,Tabla2[#All],3,0) -> CADENAS - SUPERMERCADOS | S3: CALLE ENTRADA SUR EDIF BONSAI PISO 8 | T3: URB SANTA PAULA CARACAS (EL CAFETAL) | U3: TURMERO
A4: V117414546 | B4: ADRIANA PEREIRO NEGRO | C4: 99 | D4: 99 | E4: =VLOOKUP($D4,'ESTRUCTURA P&B - LP'!$A$1:$F$31,5,0) -> E-COMMERCE | F4: =VLOOKUP($D4,'ESTRUCTURA P&B - LP'!$A$1:$F$31,6,0) -> E-COMMERCE | G4: MIRANDA | H4: =VLOOKUP(Tabla3[[#This Row],[NUEVA RUTA]],Tabla1[#All],2,0) -> E-COMMERCE | I4: =VLOOKUP($A4,Clientes!$A$1:$C$1999,3,0) -> ADRIANA PEREIRO | J4: 99 | K4: =VLOOKUP($J4,'ESTRUCTURA P&B - LP'!$A$1:$F$40,5,0) -> E-COMMERCE | L4: =IFERROR(VLOOKUP($J4,'[2]POTENCIAL X ZONA'!$B$4:$G$21,6,0),0) -> 0 | M4: =IFERROR(VLOOKUP($A4,'Convenio Clientes'!$D:$F,3,0),"SN CNV") -> 50 | N4: 10 | O4: 0 | P4: EVENTUAL | Q4: OFICINA | R4: =VLOOKUP($N4,Tabla2[#All],3,0) -> ATENCION AL CLIENTE | S4: AV UNIVERSIDAD ESQUINA LA PEDRERA A | T4: MARCOS PARRA EDF COLON PISO 04 | U4: CARACAS
A5: J501665958 | B5: AGROMAYOR TOCUYITO, C.A. | C5: 20 | D5: 20 | E5: =VLOOKUP($D5,'ESTRUCTURA P&B - LP'!$A$1:$F$31,5,0) -> JUAN LEÓN 20 | F5: =VLOOKUP($D5,'ESTRUCTURA P&B - LP'!$A$1:$F$31,6,0) -> DUBRASKA PÉREZ | G5: CARABOBO | H5: =VLOOKUP(Tabla3[[#This Row],[NUEVA RUTA]],Tabla1[#All],2,0) -> CENTRO-OCCIDENTE | I5: =VLOOKUP($A5,Clientes!$A$1:$C$1999,3,0) -> AGROM TOCUYITO | J5: 20 | K5: =VLOOKUP($J5,'ESTRUCTURA P&B - LP'!$A$1:$F$40,5,0) -> JUAN LEÓN 20 | L5: =IFERROR(VLOOKUP($J5,'[2]POTENCIAL X ZONA'!$B$4:$G$21,6,0),0) -> P | M5: =IFERROR(VLOOKUP($A5,'Convenio Clientes'!$D:$F,3,0),"SN CNV") -> 21 | N5: 07 | O5: 0 | P5: INACTIVO | Q5: NO | R5: =VLOOKUP($N5,Tabla2[#All],3,0) -> DISTRIBUIDOR | S5: AV. 91 LOCAL NRO 90-250 | T5: BARRIO LIBERTADOR | U5: TOCUYITO
A6: J412594982 | B6: AGROPA, C.A | C6: 99 | D6: 99 | E6: =VLOOKUP($D6,'ESTRUCTURA P&B - LP'!$A$1:$F$31,5,0) -> E-COMMERCE | F6: =VLOOKUP($D6,'ESTRUCTURA P&B - LP'!$A$1:$F$31,6,0) -> E-COMMERCE | G6: PORTUGUESA | H6: =VLOOKUP(Tabla3[[#This Row],[NUEVA RUTA]],Tabla1[#All],2,0) -> E-COMMERCE | I6: =VLOOKUP($A6,Clientes!$A$1:$C$1999,3,0) -> AGROPA, C.A. | J6: 99 | K6: =VLOOKUP($J6,'ESTRUCTURA P&B - LP'!$A$1:$F$40,5,0) -> E-COMMERCE | L6: =IFERROR(VLOOKUP($J6,'[2]POTENCIAL X ZONA'!$B$4:$G$21,6,0),0) -> 0 | M6: =IFERROR(VLOOKUP($A6,'Convenio Clientes'!$D:$F,3,0),"SN CNV") -> 50 | N6: 10 | O6: 0 | P6: EVENTUAL | Q6: OFICINA | R6: =VLOOKUP($N6,Tabla2[#All],3,0) -> ATENCION AL CLIENTE | U6: ARAURE
A7: V096825435 | B7: AIDA CAROLINA MEDINA DIAZ | C7: 98 | D7: 95 | E7: =VLOOKUP($D7,'ESTRUCTURA P&B - LP'!$A$1:$F$31,5,0) -> EVENTUALES | F7: =VLOOKUP($D7,'ESTRUCTURA P&B - LP'!$A$1:$F$31,6,0) -> ROSLI APONTE | G7: DISTRITO CAPITAL | H7: =VLOOKUP(Tabla3[[#This Row],[NUEVA RUTA]],Tabla1[#All],2,0) -> OFICINA | I7: =VLOOKUP($A7,Clientes!$A$1:$C$1999,3,0) -> AIDA C. MEDINA | J7: 95 | K7: =VLOOKUP($J7,'ESTRUCTURA P&B - LP'!$A$1:$F$40,5,0) -> EVENTUALES | L7: =IFERROR(VLOOKUP($J7,'[2]POTENCIAL X ZONA'!$B$4:$G$21,6,0),0) -> 0 | M7: =IFERROR(VLOOKUP($A7,'Convenio Clientes'!$D:$F,3,0),"SN CNV") -> 21 | N7: 09 | O7: 0 | P7: EVENTUAL | Q7: OFICINA | R7: =VLOOKUP($N7,Tabla2[#All],3,0) -> INSTITUCIONAL | S7: CALLE TAMARE ENTRE CABURE Y DABAJURO | T7: LOC-2 SECTOR PUERTA MARAVEN PTA CARDON | U7: CARACAS
A8: J402835604 | B8: ALIADOS COMERCIALES, C.A. | C8: 62 | D8: 21 | E8: =VLOOKUP($D8,'ESTRUCTURA P&B - LP'!$A$1:$F$31,5,0) -> ANDREINA RANGEL 21 | F8: =VLOOKUP($D8,'ESTRUCTURA P&B - LP'!$A$1:$F$31,6,0) -> ANDREINA RANGEL | G8: FALCON | H8: =VLOOKUP(Tabla3[[#This Row],[NUEVA RUTA]],Tabla1[#All],2,0) -> OCCIDENTE | I8: =VLOOKUP($A8,Clientes!$A$1:$C$1999,3,0) -> ALIADOS COMERC | J8: 21 | K8: =VLOOKUP($J8,'ESTRUCTURA P&B - LP'!$A$1:$F$40,5,0) -> ANDREINA RANGEL 21 | L8: =IFERROR(VLOOKUP($J8,'[2]POTENCIAL X ZONA'!$B$4:$G$21,6,0),0) -> S | M8: =IFERROR(VLOOKUP($A8,'Convenio Clientes'!$D:$F,3,0),"SN CNV") -> 20 | N8: 07 | O8: 15 | P8: REGULAR | Q8: SI | R8: =VLOOKUP($N8,Tabla2[#All],3,0) -> DISTRIBUIDOR | S8: AV 91 LOCAL N°80-126 SEC, LA FORTALEZA | T8: BARRIO EL LIBERTADOR | U8: PUNTO FIJO
A9: J402802218 | B9: ALIANZA DISTRIBUIDORA C.A | C9: 98 | D9: 98 | E9: =VLOOKUP($D9,'ESTRUCTURA P&B - LP'!$A$1:$F$31,5,0) -> INACTIVO | F9: =VLOOKUP($D9,'ESTRUCTURA P&B - LP'!$A$1:$F$31,6,0) -> INACTIVO | G9: ZULIA | H9: =VLOOKUP(Tabla3[[#This Row],[NUEVA RUTA]],Tabla1[#All],2,0) -> INACTIVO | I9: =VLOOKUP($A9,Clientes!$A$1:$C$1999,3,0) -> 30 SAN JUAN | J9: 0 | K9: =VLOOKUP($J9,'ESTRUCTURA P&B - LP'!$A$1:$F$40,5,0) -> INACTIVO | L9: =IFERROR(VLOOKUP($J9,'[2]POTENCIAL X ZONA'!$B$4:$G$21,6,0),0) -> 0 | M9: =IFERROR(VLOOKUP($A9,'Convenio Clientes'!$D:$F,3,0),"SN CNV") -> 01 | N9: 07 | O9: 0 | P9: INACTIVO | Q9: NO | R9: =VLOOKUP($N9,Tabla2[#All],3,0) -> DISTRIBUIDOR | S9: CALLE CALLEJON MAÑONGO(176) TERRENO | T9: CIVICO NO.91-A-15 LOCAL 1 NRO.1 | U9: MARACAIBO
A10: J317219686 | B10: ALIMENTOS FM C.A. | C10: 98 | D10: 20 | E10: =VLOOKUP($D10,'ESTRUCTURA P&B - LP'!$A$1:$F$31,5,0) -> JUAN LEÓN 20 | F10: =VLOOKUP($D10,'ESTRUCTURA P&B - LP'!$A$1:$F$31,6,0) -> DUBRASKA PÉREZ | G10: CARABOBO | H10: =VLOOKUP(Tabla3[[#This Row],[NUEVA RUTA]],Tabla1[#All],2,0) -> CENTRO-OCCIDENTE | I10: =VLOOKUP($A10,Clientes!$A$1:$C$1999,3,0) -> ALIMENTOS FM | J10: 20 | K10: =VLOOKUP($J10,'ESTRUCTURA P&B - LP'!$A$1:$F$40,5,0) -> JUAN LEÓN 20 | L10: =IFERROR(VLOOKUP($J10,'[2]POTENCIAL X ZONA'!$B$4:$G$21,6,0),0) -> P | M10: =IFERROR(VLOOKUP($A10,'Convenio Clientes'!$D:$F,3,0),"SN CNV") -> 21 | N10: 03 | O10: 30 | P10: INACTIVO | Q10: NO | R10: =VLOOKUP($N10,Tabla2[#All],3,0) -> CADENAS - SUPERMERCADOS | S10: CALLE PRINCIPAL EL COTIJO DE ORIENTE | T10: EDIF 4 PISO 3 APT 438 CONJUNTO RESIDENCIAL AGUA CLARA | U10: NAGUANAGUA
A11: J500127740 | B11: ALIMENTOS RB 2020, C.A | C11: 20 | D11: 20 | E11: =VLOOKUP($D11,'ESTRUCTURA P&B - LP'!$A$1:$F$31,5,0) -> JUAN LEÓN 20 | F11: =VLOOKUP($D11,'ESTRUCTURA P&B - LP'!$A$1:$F$31,6,0) -> DUBRASKA PÉREZ | G11: CARABOBO | H11: CENTRAL | I11: =VLOOKUP($A11,Clientes!$A$1:$C$1999,3,0) -> ALIMENT RB 2020 | J11: 20 | K11: =VLOOKUP($J11,'ESTRUCTURA P&B - LP'!$A$1:$F$40,5,0) -> JUAN LEÓN 20 | L11: =IFERROR(VLOOKUP($J11,'[2]POTENCIAL X ZONA'!$B$4:$G$21,6,0),0) -> P | M11: =IFERROR(VLOOKUP($A11,'Convenio Clientes'!$D:$F,3,0),"SN CNV") -> 01 | N11: 03 | O11: 0 | P11: INACTIVO | Q11: NO | R11: =VLOOKUP($N11,Tabla2[#All],3,0) -> CADENAS - SUPERMERCADOS | U11: VALENCIA
A12: J406761117 | B12: ALLEVENTS, C.A | C12: 98 | D12: 98 | E12: =VLOOKUP($D12,'ESTRUCTURA P&B - LP'!$A$1:$F$31,5,0) -> INACTIVO | F12: =VLOOKUP($D12,'ESTRUCTURA P&B - LP'!$A$1:$F$31,6,0) -> INACTIVO | G12: ANZOATEGUI | H12: =VLOOKUP(Tabla3[[#This Row],[NUEVA RUTA]],Tabla1[#All],2,0) -> INACTIVO | I12: =VLOOKUP($A12,Clientes!$A$1:$C$1999,3,0) -> ALLEVENTS, C.A | J12: 51 | K12: =VLOOKUP($J12,'ESTRUCTURA P&B - LP'!$A$1:$F$40,5,0) -> DIANA DELGADO 51 | L12: =IFERROR(VLOOKUP($J12,'[2]POTENCIAL X ZONA'!$B$4:$G$21,6,0),0) -> P | M12: =IFERROR(VLOOKUP($A12,'Convenio Clientes'!$D:$F,3,0),"SN CNV") -> 20 | N12: 07 | O12: 0 | P12: INACTIVO | Q12: NO | R12: =VLOOKUP($N12,Tabla2[#All],3,0) -> DISTRIBUIDOR | S12: CALLE NIVEL 1 CASA | T12: PARCELA NRO 9-10 ZONA INDUSTRIAL | U12: BARCELONA
A13: J500014325 | B13: ALMACENADORA MILROSS, C.A. | C13: 98 | D13: 98 | E13: =VLOOKUP($D13,'ESTRUCTURA P&B - LP'!$A$1:$F$31,5,0) -> INACTIVO | F13: =VLOOKUP($D13,'ESTRUCTURA P&B - LP'!$A$1:$F$31,6,0) -> INACTIVO | G13: DISTRITO CAPITAL | H13: =VLOOKUP(Tabla3[[#This Row],[NUEVA RUTA]],Tabla1[#All],2,0) -> INACTIVO | I13: =VLOOKUP($A13,Clientes!$A$1:$C$1999,3,0) -> ALMAC MILROSS | J13: 0 | K13: =VLOOKUP($J13,'ESTRUCTURA P&B - LP'!$A$1:$F$40,5,0) -> INACTIVO | L13: =IFERROR(VLOOKUP($J13,'[2]POTENCIAL X ZONA'!$B$4:$G$21,6,0),0) -> 0 | M13: =IFERROR(VLOOKUP($A13,'Convenio Clientes'!$D:$F,3,0),"SN CNV") -> 21 | N13: 07 | O13: 0 | P13: INACTIVO | Q13: NO | R13: =VLOOKUP($N13,Tabla2[#All],3,0) -> DISTRIBUIDOR | S13: AV RIO CAURA CON AV RIO PARAGUA | T13: CC CONCRESA NIVEL 2 LOCAL 111 | U13: CARACAS
A14: J312054280 | B14: AMBIENTADORES ALNI DE VENEZUELA,AMBIVEN,C.A. | C14: 98 | D14: 98 | E14: =VLOOKUP($D14,'ESTRUCTURA P&B - LP'!$A$1:$F$31,5,0) -> INACTIVO | F14: =VLOOKUP($D14,'ESTRUCTURA P&B - LP'!$A$1:$F$31,6,0) -> INACTIVO | G14: MIRANDA | H14: =VLOOKUP(Tabla3[[#This Row],[NUEVA RUTA]],Tabla1[#All],2,0) -> INACTIVO | I14: =VLOOKUP($A14,Clientes!$A$1:$C$1999,3,0) -> AMBIVEN | J14: 95 | K14: =VLOOKUP($J14,'ESTRUCTURA P&B - LP'!$A$1:$F$40,5,0) -> EVENTUALES | L14: =IFERROR(VLOOKUP($J14,'[2]POTENCIAL X ZONA'!$B$4:$G$21,6,0),0) -> 0 | M14: =IFERROR(VLOOKUP($A14,'Convenio Clientes'!$D:$F,3,0),"SN CNV") -> 01 | N14: 07 | O14: 0 | P14: INACTIVO | Q14: NO | R14: =VLOOKUP($N14,Tabla2[#All],3,0) -> DISTRIBUIDOR | S14: URB GUACARA LOS GUAYOS 1ERA ETAPA DE | T14: CIUDAD ALIANZA C.C. ALIANZA MALL PB | U14: CARACAS
A15: J503504641 | B15: AMI DISTRIBUIDORA Y COMERCIALIZADORA , C.A | C15: 23 | D15: 23 | E15: =VLOOKUP($D15,'ESTRUCTURA P&B - LP'!$A$1:$F$31,5,0) -> MARTHA VILORIA | F15: =VLOOKUP($D15,'ESTRUCTURA P&B - LP'!$A$1:$F$31,6,0) -> DUBRASKA PÉREZ | G15: LARA | H15: =VLOOKUP(Tabla3[[#This Row],[NUEVA RUTA]],Tabla1[#All],2,0) -> CENTRO-OCCIDENTE | I15: =VLOOKUP($A15,Clientes!$A$1:$C$1999,3,0) -> AMI DISTRIB | J15: 23 | K15: =VLOOKUP($J15,'ESTRUCTURA P&B - LP'!$A$1:$F$40,5,0) -> MARTHA VILORIA | L15: =IFERROR(VLOOKUP($J15,'[2]POTENCIAL X ZONA'!$B$4:$G$21,6,0),0) -> S | M15: =IFERROR(VLOOKUP($A15,'Convenio Clientes'!$D:$F,3,0),"SN CNV") -> 26 | N15: 07 | O15: 15 | P15: REGULAR | Q15: SI | R15: =VLOOKUP($N15,Tabla2[#All],3,0) -> DISTRIBUIDOR | U15: BARQUISIMETO
A16: J312492031 | B16: AMIFARMACIA, C.A. | C16: 98 | D16: 98 | E16: =VLOOKUP($D16,'ESTRUCTURA P&B - LP'!$A$1:$F$31,5,0) -> INACTIVO | F16: =VLOOKUP($D16,'ESTRUCTURA P&B - LP'!$A$1:$F$31,6,0) -> INACTIVO | G16: CARABOBO | H16: =VLOOKUP(Tabla3[[#This Row],[NUEVA RUTA]],Tabla1[#All],2,0) -> INACTIVO | I16: =VLOOKUP($A16,Clientes!$A$1:$C$1999,3,0) -> 65 LOCATEL | J16: 20 | K16: =VLOOKUP($J16,'ESTRUCTURA P&B - LP'!$A$1:$F$40,5,0) -> JUAN LEÓN 20 | L16: =IFERROR(VLOOKUP($J16,'[2]POTENCIAL X ZONA'!$B$4:$G$21,6,0),0) -> P | M16: =IFERROR(VLOOKUP($A16,'Convenio Clientes'!$D:$F,3,0),"SN CNV") -> 01 | N16: 01 | O16: 15 | P16: INACTIVO | Q16: NO | R16: =VLOOKUP($N16,Tabla2[#All],3,0) -> CADENAS - FARMACIAS | S16: AV 1ERA CON 10MA | T16: EDIF RES DORAMIL PISO PB APT 2 | U16: LOS GUAYOS
A17: V068206150 | B17: ANA MARIA PONCE SARDI | C17: 95 | D17: 90 | E17: =VLOOKUP($D17,'ESTRUCTURA P&B - LP'!$A$1:$F$31,5,0) -> INTER-COMPAÑÍA | F17: =VLOOKUP($D17,'ESTRUCTURA P&B - LP'!$A$1:$F$31,6,0) -> ROSLI APONTE | G17: MIRANDA | H17: =VLOOKUP(Tabla3[[#This Row],[NUEVA RUTA]],Tabla1[#All],2,0) -> OFICINA | I17: =VLOOKUP($A17,Clientes!$A$1:$C$1999,3,0) -> ANA MARIA PONCE | J17: 90 | K17: =VLOOKUP($J17,'ESTRUCTURA P&B - LP'!$A$1:$F$40,5,0) -> INTER-COMPAÑÍA | L17: =IFERROR(VLOOKUP($J17,'[2]POTENCIAL X ZONA'!$B$4:$G$21,6,0),0) -> 0 | M17: =IFERROR(VLOOKUP($A17,'Convenio Clientes'!$D:$F,3,0),"SN CNV") -> 21 | N17: 11 | O17: 0 | P17: EVENTUAL | Q17: OFICINA | R17: =VLOOKUP($N17,Tabla2[#All],3,0) -> EMPLEADOS | S17: AV. TEHERAN EDIF JUAN VIVES SURIA PISO 6 APTO 1A06A | T17: MONTALBAN III | U17: CARACAS
A18: V225666314 | B18: ANAROSBER PAREJO REYES | C18: 99 | D18: 99 | E18: =VLOOKUP($D18,'ESTRUCTURA P&B - LP'!$A$1:$F$31,5,0) -> E-COMMERCE | F18: =VLOOKUP($D18,'ESTRUCTURA P&B - LP'!$A$1:$F$31,6,0) -> E-COMMERCE | G18: MIRANDA | H18: =VLOOKUP(Tabla3[[#This Row],[NUEVA RUTA]],Tabla1[#All],2,0) -> E-COMMERCE | I18: =VLOOKUP($A18,Clientes!$A$1:$C$1999,3,0) -> ANAROSBER PAREJ | J18: 99 | K18: =VLOOKUP($J18,'ESTRUCTURA P&B - LP'!$A$1:$F$40,5,0) -> E-COMMERCE | L18: =IFERROR(VLOOKUP($J18,'[2]POTENCIAL X ZONA'!$B$4:$G$21,6,0),0) -> 0 | M18: =IFERROR(VLOOKUP($A18,'Convenio Clientes'!$D:$F,3,0),"SN CNV") -> 50 | N18: 10 | O18: 0 | P18: EVENTUAL | Q18: OFICINA | R18: =VLOOKUP($N18,Tabla2[#All],3,0) -> ATENCION AL CLIENTE | U18: CHARALLAVE
A19: V141955400 | B19: ANGEL ALEXIS SAYAGO | C19: 98 | D19: 98 | E19: =VLOOKUP($D19,'ESTRUCTURA P&B - LP'!$A$1:$F$31,5,0) -> INACTIVO | F19: =VLOOKUP($D19,'ESTRUCTURA P&B - LP'!$A$1:$F$31,6,0) -> INACTIVO | G19: DISTRITO CAPITAL | H19: =VLOOKUP(Tabla3[[#This Row],[NUEVA RUTA]],Tabla1[#All],2,0) -> INACTIVO | I19: =VLOOKUP($A19,Clientes!$A$1:$C$1999,3,0) -> ANGEL A SAYAGO | J19: 90 | K19: =VLOOKUP($J19,'ESTRUCTURA P&B - LP'!$A$1:$F$40,5,0) -> INTER-COMPAÑÍA | L19: =IFERROR(VLOOKUP($J19,'[2]POTENCIAL X ZONA'!$B$4:$G$21,6,0),0) -> 0 | M19: =IFERROR(VLOOKUP($A19,'Convenio Clientes'!$D:$F,3,0),"SN CNV") -> 21 | N19: 09 | O19: 0 | P19: INACTIVO | Q19: NO | R19: =VLOOKUP($N19,Tabla2[#All],3,0) -> INSTITUCIONAL | S19: AV BERMUDEZ CON LA AVENIDA MIRANDA | T19: LOCAL DIAGONAL A LA PLAZA BOLIVAR | U19: CARACAS
A20: J412891260 | B20: ARABITO MARKET, C.A. | C20: 98 | D20: 12 | E20: =VLOOKUP($D20,'ESTRUCTURA P&B - LP'!$A$1:$F$31,5,0) -> JUAN LEÓN 12 | F20: =VLOOKUP($D20,'ESTRUCTURA P&B - LP'!$A$1:$F$31,6,0) -> DUBRASKA PÉREZ | G20: ARAGUA | H20: =VLOOKUP(Tabla3[[#This Row],[NUEVA RUTA]],Tabla1[#All],2,0) -> CENTRO-OCCIDENTE | I20: =VLOOKUP($A20,Clientes!$A$1:$C$1999,3,0) -> ARABITO MARKET | J20: 12 | K20: =VLOOKUP($J20,'ESTRUCTURA P&B - LP'!$A$1:$F$40,5,0) -> JUAN LEÓN 12 | L20: =IFERROR(VLOOKUP($J20,'[2]POTENCIAL X ZONA'!$B$4:$G$21,6,0),0) -> P | M20: =IFERROR(VLOOKUP($A20,'Convenio Clientes'!$D:$F,3,0),"SN CNV") -> 21 | N20: 03 | O20: 45 | P20: EVENTUAL | Q20: SI | R20: =VLOOKUP($N20,Tabla2[#All],3,0) -> CADENAS - SUPERMERCADOS | S20: AV BOLIVAR CASA NRO 6 -12 SECTOR LA | U20: MARACAY
A21: J298008040 | B21: ARCO SUMINISTROS, C.A. | C21: 98 | D21: 98 | E21: =VLOOKUP($D21,'ESTRUCTURA P&B - LP'!$A$1:$F$31,5,0) -> INACTIVO | F21: =VLOOKUP($D21,'ESTRUCTURA P&B - LP'!$A$1:$F$31,6,0) -> INACTIVO | G21: MERIDA | H21: =VLOOKUP(Tabla3[[#This Row],[NUEVA RUTA]],Tabla1[#All],2,0) -> INACTIVO | I21: =VLOOKUP($A21,Clientes!$A$1:$C$1999,3,0) -> ARCO SUMINISTRO | J21: 0 | K21: =VLOOKUP($J21,'ESTRUCTURA P&B - LP'!$A$1:$F$40,5,0) -> INACTIVO | L21: =IFERROR(VLOOKUP($J21,'[2]POTENCIAL X ZONA'!$B$4:$G$21,6,0),0) -> 0 | M21: =IFERROR(VLOOKUP($A21,'Convenio Clientes'!$D:$F,3,0),"SN CNV") -> 01 | N21: 07 | O21: 0 | P21: INACTIVO | Q21: NO | R21: =VLOOKUP($N21,Tabla2[#All],3,0) -> DISTRIBUIDOR | S21: AV LAS ESCUELAS EDIF CAJA DE AHORRO | T21: DEL EJERCITO BOLIVARIANO PISO PB | U21: MERIDA
A22: J294462847 | B22: ASOC CIVIL CAJA DE AHORRO DEL EJERC BOLIVARIANO | C22: 98 | D22: 98 | E22: =VLOOKUP($D22,'ESTRUCTURA P&B - LP'!$A$1:$F$31,5,0) -> INACTIVO | F22: =VLOOKUP($D22,'ESTRUCTURA P&B - LP'!$A$1:$F$31,6,0) -> INACTIVO | G22: DISTRITO CAPITAL | H22: =VLOOKUP(Tabla3[[#This Row],[NUEVA RUTA]],Tabla1[#All],2,0) -> INACTIVO | I22: =VLOOKUP($A22,Clientes!$A$1:$C$1999,3,0) -> EJERC BOLIVARIA | J22: 0 | K22: =VLOOKUP($J22,'ESTRUCTURA P&B - LP'!$A$1:$F$40,5,0) -> INACTIVO | L22: =IFERROR(VLOOKUP($J22,'[2]POTENCIAL X ZONA'!$B$4:$G$21,6,0),0) -> 0 | M22: =IFERROR(VLOOKUP($A22,'Convenio Clientes'!$D:$F,3,0),"SN CNV") -> 01 | N22: 09 | O22: 0 | P22: INACTIVO | Q22: NO | R22: =VLOOKUP($N22,Tabla2[#All],3,0) -> INSTITUCIONAL | S22: AV 3RA CON 6TA TRANSV EDIF INTER | T22: PISO 3 OF ALTAMIRA URB ALTAMIRA | U22: CARACAS
A23: J308487406 | B23: ASOC CIVIL INSTITUTO DE TEOLOGIA PARA RELIGIOSOS | C23: 95 | D23: 95 | E23: =VLOOKUP($D23,'ESTRUCTURA P&B - LP'!$A$1:$F$31,5,0) -> EVENTUALES | F23: =VLOOKUP($D23,'ESTRUCTURA P&B - LP'!$A$1:$F$31,6,0) -> ROSLI APONTE | G23: MIRANDA | H23: =VLOOKUP(Tabla3[[#This Row],[NUEVA RUTA]],Tabla1[#All],2,0) -> OFICINA | I23: =VLOOKUP($A23,Clientes!$A$1:$C$1999,3,0) -> ASOC C TEOLOGIA | J23: 95 | K23: =VLOOKUP($J23,'ESTRUCTURA P&B - LP'!$A$1:$F$40,5,0) -> EVENTUALES | L23: =IFERROR(VLOOKUP($J23,'[2]POTENCIAL X ZONA'!$B$4:$G$21,6,0),0) -> 0 | M23: =IFERROR(VLOOKUP($A23,'Convenio Clientes'!$D:$F,3,0),"SN CNV") -> 21 | N23: 09 | O23: 0 | P23: EVENTUAL | Q23: OFICINA | R23: =VLOOKUP($N23,Tabla2[#All],3,0) -> INSTITUCIONAL | S23: AV. SAN FELIPE | T23: EDIFICIO DON BOSCO 88 PISO 1 | U23: CARACAS
A24: J001222642 | B24: ASOCIACION DAMAS SALESIANAS | C24: 98 | D24: 95 | E24: =VLOOKUP($D24,'ESTRUCTURA P&B - LP'!$A$1:$F$31,5,0) -> EVENTUALES | F24: =VLOOKUP($D24,'ESTRUCTURA P&B - LP'!$A$1:$F$31,6,0) -> ROSLI APONTE | G24: MIRANDA | H24: =VLOOKUP(Tabla3[[#This Row],[NUEVA RUTA]],Tabla1[#All],2,0) -> OFICINA | I24: =VLOOKUP($A24,Clientes!$A$1:$C$1999,3,0) -> ASOC DAMAS SALE | J24: 90 | K24: =VLOOKUP($J24,'ESTRUCTURA P&B - LP'!$A$1:$F$40,5,0) -> INTER-COMPAÑÍA | L24: =IFERROR(VLOOKUP($J24,'[2]POTENCIAL X ZONA'!$B$4:$G$21,6,0),0) -> 0 | M24: =IFERROR(VLOOKUP($A24,'Convenio Clientes'!$D:$F,3,0),"SN CNV") -> 21 | N24: 17 | O24: 0 | P24: EVENTUAL | Q24: OFICINA | R24: =VLOOKUP($N24,Tabla2[#All],3,0) -> OTROS | S24: AV. LA ESTANCIA CC C.C.C.TAMANACO, | T24: TORRE C NIVEL 13 OFICINA 1304 | U24: CARACAS
A25: J404498923 | B25: ASOCOMPRA ASOCIACIÓN DE COMPRADORES, A.C. | C25: 98 | D25: 98 | E25: =VLOOKUP($D25,'ESTRUCTURA P&B - LP'!$A$1:$F$31,5,0) -> INACTIVO | F25: =VLOOKUP($D25,'ESTRUCTURA P&B - LP'!$A$1:$F$31,6,0) -> INACTIVO | G25: MIRANDA | H25: =VLOOKUP(Tabla3[[#This Row],[NUEVA RUTA]],Tabla1[#All],2,0) -> INACTIVO | I25: =VLOOKUP($A25,Clientes!$A$1:$C$1999,3,0) -> ASOCOMPRA | J25: 10 | K25: =VLOOKUP($J25,'ESTRUCTURA P&B - LP'!$A$1:$F$40,5,0) -> MILAGROS FERNANDEZ 10 | L25: =IFERROR(VLOOKUP($J25,'[2]POTENCIAL X ZONA'!$B$4:$G$21,6,0),0) -> B | M25: =IFERROR(VLOOKUP($A25,'Convenio Clientes'!$D:$F,3,0),"SN CNV") -> 20 | N25: 09 | O25: 7 | P25: INACTIVO | Q25: NO | R25: =VLOOKUP($N25,Tabla2[#All],3,0) -> INSTITUCIONAL | S25: ZONA IND. LAS VEGAS 1RA TRANSVERSAL | T25: PARCELA 18 | U25: CARACAS
A26: J504755699 | B26: ATLANTICO CENTER PZO, C.A | C26: 52 | D26: 52 | E26: =VLOOKUP($D26,'ESTRUCTURA P&B - LP'!$A$1:$F$31,5,0) -> DIANA DELGADO 52 | F26: =VLOOKUP($D26,'ESTRUCTURA P&B - LP'!$A$1:$F$31,6,0) -> DIANA DELGADO | G26: BOLIVAR | H26: ORIENTE SUR | I26: =VLOOKUP($A26,Clientes!$A$1:$C$1999,3,0) -> ATLANTIC CENTER | J26: 52 | K26: =VLOOKUP($J26,'ESTRUCTURA P&B - LP'!$A$1:$F$40,5,0) -> DIANA DELGADO 52 | L26: =IFERROR(VLOOKUP($J26,'[2]POTENCIAL X ZONA'!$B$4:$G$21,6,0),0) -> S | M26: =IFERROR(VLOOKUP($A26,'Convenio Clientes'!$D:$F,3,0),"SN CNV") -> 20 | N26: 07 | O26: 0 | P26: EVENTUAL | Q26: SI | R26: =VLOOKUP($N26,Tabla2[#All],3,0) -> DISTRIBUIDOR | U26: CIUDAD GUAYANA
A27: J504648450 | B27: AURA STUDIO 2022, CA | C27: 99 | D27: 99 | E27: =VLOOKUP($D27,'ESTRUCTURA P&B - LP'!$A$1:$F$31,5,0) -> E-COMMERCE | F27: =VLOOKUP($D27,'ESTRUCTURA P&B - LP'!$A$1:$F$31,6,0) -> E-COMMERCE | G27: MIRANDA | H27: =VLOOKUP(Tabla3[[#This Row],[NUEVA RUTA]],Tabla1[#All],2,0) -> E-COMMERCE | I27: =VLOOKUP($A27,Clientes!$A$1:$C$1999,3,0) -> AURA STUDIO2022 | J27: 99 | K27: =VLOOKUP($J27,'ESTRUCTURA P&B - LP'!$A$1:$F$40,5,0) -> E-COMMERCE | L27: =IFERROR(VLOOKUP($J27,'[2]POTENCIAL X ZONA'!$B$4:$G$21,6,0),0) -> 0 | M27: =IFERROR(VLOOKUP($A27,'Convenio Clientes'!$D:$F,3,0),"SN CNV") -> 50 | N27: 10 | O27: 0 | P27: EVENTUAL | Q27: OFICINA | R27: =VLOOKUP($N27,Tabla2[#All],3,0) -> ATENCION AL CLIENTE | S27: 0 | T27: 0 | U27: CARACAS
A28: J075245113 | B28: AUTO MERCADO SAN DIEGO, C.A. | C28: 98 | D28: 12 | E28: =VLOOKUP($D28,'ESTRUCTURA P&B - LP'!$A$1:$F$31,5,0) -> JUAN LEÓN 12 | F28: =VLOOKUP($D28,'ESTRUCTURA P&B - LP'!$A$1:$F$31,6,0) -> DUBRASKA PÉREZ | G28: ARAGUA | H28: =VLOOKUP(Tabla3[[#This Row],[NUEVA RUTA]],Tabla1[#All],2,0) -> CENTRO-OCCIDENTE | I28: =VLOOKUP($A28,Clientes!$A$1:$C$1999,3,0) -> 37 SAN DIEGO | J28: 12 | K28: =VLOOKUP($J28,'ESTRUCTURA P&B - LP'!$A$1:$F$40,5,0) -> JUAN LEÓN 12 | L28: =IFERROR(VLOOKUP($J28,'[2]POTENCIAL X ZONA'!$B$4:$G$21,6,0),0) -> P | M28: =IFERROR(VLOOKUP($A28,'Convenio Clientes'!$D:$F,3,0),"SN CNV") -> 21 | N28: 03 | O28: 0 | P28: EVENTUAL | Q28: SI | R28: =VLOOKUP($N28,Tabla2[#All],3,0) -> CADENAS - SUPERMERCADOS | S28: AV OESTE 16 ESQUINA COCHERA | T28: LOCAL PLANTA BAJA NRO 38 | U28: CAGUA
A29: J413118440 | B29: AUTOMERCADO CHINATOWN SAN JUAN 2020, C.A | C29: 98 | D29: 98 | E29: =VLOOKUP($D29,'ESTRUCTURA P&B - LP'!$A$1:$F$31,5,0) -> INACTIVO | F29: =VLOOKUP($D29,'ESTRUCTURA P&B - LP'!$A$1:$F$31,6,0) -> INACTIVO | G29: DISTRITO CAPITAL | H29: =VLOOKUP(Tabla3[[#This Row],[NUEVA RUTA]],Tabla1[#All],2,0) -> INACTIVO | I29: =VLOOKUP($A29,Clientes!$A$1:$C$1999,3,0) -> CHINAT SAN JUAN | J29: 57 | K29: =VLOOKUP($J29,'ESTRUCTURA P&B - LP'!$A$1:$F$40,5,0) -> CARLOS ZURITA | L29: =IFERROR(VLOOKUP($J29,'[2]POTENCIAL X ZONA'!$B$4:$G$21,6,0),0) -> 0 | M29: =IFERROR(VLOOKUP($A29,'Convenio Clientes'!$D:$F,3,0),"SN CNV") -> 21 | N29: 15 | O29: 7 | P29: INACTIVO | Q29: NO | R29: =VLOOKUP($N29,Tabla2[#All],3,0) -> MAYORISTAS | S29: CTRA NACIONAL SAN CRISOBAL-CAPACHO | T29: L GALPON SEC ZORCA PROVIDENCIA | U29: CARACAS
A30: J304983905 | B30: AUTOMERCADO COSMO FRONTERA, C.A | C30: 98 | D30: 98 | E30: =VLOOKUP($D30,'ESTRUCTURA P&B - LP'!$A$1:$F$31,5,0) -> INACTIVO | F30: =VLOOKUP($D30,'ESTRUCTURA P&B - LP'!$A$1:$F$31,6,0) -> INACTIVO | G30: TACHIRA | H30: =VLOOKUP(Tabla3[[#This Row],[NUEVA RUTA]],Tabla1[#All],2,0) -> INACTIVO | I30: =VLOOKUP($A30,Clientes!$A$1:$C$1999,3,0) -> AUT COSMO FRONT | J30: 0 | K30: =VLOOKUP($J30,'ESTRUCTURA P&B - LP'!$A$1:$F$40,5,0) -> INACTIVO | L30: =IFERROR(VLOOKUP($J30,'[2]POTENCIAL X ZONA'!$B$4:$G$21,6,0),0) -> 0 | M30: =IFERROR(VLOOKUP($A30,'Convenio Clientes'!$D:$F,3,0),"SN CNV") -> 01 | N30: 06 | O30: 0 | P30: INACTIVO | Q30: NO | R30: =VLOOKUP($N30,Tabla2[#All],3,0) -> SUPERMERCADOS INDEPENDIENTES | S30: 3rA CON 5tA TRANSV.LOS PALOS GDES.URB. | T30: LOS PALOS GRANDES C.C.EL PATIO LC 7-8 | U30: SAN CRISTOBAL
A31: J000859400 | B31: AUTOMERCADO EL PATIO LOS PALOS GRANDES, C.A. | C31: 98 | D31: 98 | E31: =VLOOKUP($D31,'ESTRUCTURA P&B - LP'!$A$1:$F$31,5,0) -> INACTIVO | F31: =VLOOKUP($D31,'ESTRUCTURA P&B - LP'!$A$1:$F$31,6,0) -> INACTIVO | G31: MIRANDA | H31: =VLOOKUP(Tabla3[[#This Row],[NUEVA RUTA]],Tabla1[#All],2,0) -> INACTIVO | I31: =VLOOKUP($A31,Clientes!$A$1:$C$1999,3,0) -> 70 EL PATIO | J31: 0 | K31: =VLOOKUP($J31,'ESTRUCTURA P&B - LP'!$A$1:$F$40,5,0) -> INACTIVO | L31: =IFERROR(VLOOKUP($J31,'[2]POTENCIAL X ZONA'!$B$4:$G$21,6,0),0) -> 0 | M31: =IFERROR(VLOOKUP($A31,'Convenio Clientes'!$D:$F,3,0),"SN CNV") -> 01 | N31: 03 | O31: 0 | P31: INACTIVO | Q31: NO | R31: =VLOOKUP($N31,Tabla2[#All],3,0) -> CADENAS - SUPERMERCADOS | S31: AV LA TRINIDAD EL HATILLO CON CALLE EL MURO | T31: EDIF NRO 1PISO PB LOCAL LA MURALLA URB EL HATILLO | U31: CARACAS
A32: J500412940 | B32: AUTOMERCADO LA MURALLA 1061 C.A | C32: 57 | D32: 10 | E32: =VLOOKUP($D32,'ESTRUCTURA P&B - LP'!$A$1:$F$31,5,0) -> MILAGROS FERNANDEZ 10 | F32: =VLOOKUP($D32,'ESTRUCTURA P&B - LP'!$A$1:$F$31,6,0) -> MILAGROS FERNANDEZ | G32: MIRANDA | H32: =VLOOKUP(Tabla3[[#This Row],[NUEVA RUTA]],Tabla1[#All],2,0) -> CAPITAL | I32: =VLOOKUP($A32,Clientes!$A$1:$C$1999,3,0) -> AUT LA MURALLA | J32: 10 | K32: =VLOOKUP($J32,'ESTRUCTURA P&B - LP'!$A$1:$F$40,5,0) -> MILAGROS FERNANDEZ 10 | L32: =IFERROR(VLOOKUP($J32,'[2]POTENCIAL X ZONA'!$B$4:$G$21,6,0),0) -> B | M32: =IFERROR(VLOOKUP($A32,'Convenio Clientes'!$D:$F,3,0),"SN CNV") -> 22 | N32: 06 | O32: 30 | P32: REGULAR | Q32: SI | R32: =VLOOKUP($N32,Tabla2[#All],3,0) -> SUPERMERCADOS INDEPENDIENTES | U32: CARACAS
A33: J003720224 | B33: AUTOMERCADO LA MURALLA C.A. | C33: 57 | D33: 10 | E33: =VLOOKUP($D33,'ESTRUCTURA P&B - LP'!$A$1:$F$31,5,0) -> MILAGROS FERNANDEZ 10 | F33: =VLOOKUP($D33,'ESTRUCTURA P&B - LP'!$A$1:$F$31,6,0) -> MILAGROS FERNANDEZ | G33: MIRANDA | H33: =VLOOKUP(Tabla3[[#This Row],[NUEVA RUTA]],Tabla1[#All],2,0) -> CAPITAL | I33: =VLOOKUP($A33,Clientes!$A$1:$C$1999,3,0) -> AUT LA MURALLA | J33: 10 | K33: =VLOOKUP($J33,'ESTRUCTURA P&B - LP'!$A$1:$F$40,5,0) -> MILAGROS FERNANDEZ 10 | L33: =IFERROR(VLOOKUP($J33,'[2]POTENCIAL X ZONA'!$B$4:$G$21,6,0),0) -> B | M33: =IFERROR(VLOOKUP($A33,'Convenio Clientes'!$D:$F,3,0),"SN CNV") -> 22 | N33: 06 | O33: 30 | P33: REGULAR | Q33: SI | R33: =VLOOKUP($N33,Tabla2[#All],3,0) -> SUPERMERCADOS INDEPENDIENTES | S33: AV FRANCISCO DE MIRANDA CON SAN IGNACIO DE LOYOLA | T33: EDIF VALMY PISO 2 OF 22 | U33: CARACAS
A34: J000811601 | B34: AUTOMERCADO LUZ C.A. | C34: 98 | D34: 98 | E34: =VLOOKUP($D34,'ESTRUCTURA P&B - LP'!$A$1:$F$31,5,0) -> INACTIVO | F34: =VLOOKUP($D34,'ESTRUCTURA P&B - LP'!$A$1:$F$31,6,0) -> INACTIVO | G34: MIRANDA | H34: =VLOOKUP(Tabla3[[#This Row],[NUEVA RUTA]],Tabla1[#All],2,0) -> INACTIVO | I34: =VLOOKUP($A34,Clientes!$A$1:$C$1999,3,0) -> AUTOMERCADO LUZ | J34: 95 | K34: =VLOOKUP($J34,'ESTRUCTURA P&B - LP'!$A$1:$F$40,5,0) -> EVENTUALES | L34: =IFERROR(VLOOKUP($J34,'[2]POTENCIAL X ZONA'!$B$4:$G$21,6,0),0) -> 0 | M34: =IFERROR(VLOOKUP($A34,'Convenio Clientes'!$D:$F,3,0),"SN CNV") -> 21 | N34: 03 | O34: 45 | P34: INACTIVO | Q34: NO | R34: =VLOOKUP($N34,Tabla2[#All],3,0) -> CADENAS - SUPERMERCADOS | S34: 6TA. TRANSV. ENTRE ALTAMIRA Y LOS | T34: PALOS GRANDES, ALTAMIRA QUINTA AKOBA | U34: CARACAS
A35: J000537585 | B35: AUTOMERCADO SAN LORENZO C.A. | C35: 98 | D35: 98 | E35: =VLOOKUP($D35,'ESTRUCTURA P&B - LP'!$A$1:$F$31,5,0) -> INACTIVO | F35: =VLOOKUP($D35,'ESTRUCTURA P&B - LP'!$A$1:$F$31,6,0) -> INACTIVO | G35: MIRANDA | H35: =VLOOKUP(Tabla3[[#This Row],[NUEVA RUTA]],Tabla1[#All],2,0) -> INACTIVO | I35: =VLOOKUP($A35,Clientes!$A$1:$C$1999,3,0) -> AUT SAN LORENZO | J35: 57 | K35: =VLOOKUP($J35,'ESTRUCTURA P&B - LP'!$A$1:$F$40,5,0) -> CARLOS ZURITA | L35: =IFERROR(VLOOKUP($J35,'[2]POTENCIAL X ZONA'!$B$4:$G$21,6,0),0) -> 0 | M35: =IFERROR(VLOOKUP($A35,'Convenio Clientes'!$D:$F,3,0),"SN CNV") -> 01 | N35: 06 | O35: 7 | P35: INACTIVO | Q35: NO | R35: =VLOOKUP($N35,Tabla2[#All],3,0) -> SUPERMERCADOS INDEPENDIENTES | S35: CALLE A C/ CALLE C EDIF LAS ROSAS PISO | T35: PB LOCAL 1-6 URB SANTA ROSA DE LIMA | U35: CARACAS
A36: J002099712 | B36: AUTOMERCADO SANTA ROSA DE LIMA C.A | C36: 98 | D36: 98 | E36: =VLOOKUP($D36,'ESTRUCTURA P&B - LP'!$A$1:$F$31,5,0) -> INACTIVO | F36: =VLOOKUP($D36,'ESTRUCTURA P&B - LP'!$A$1:$F$31,6,0) -> INACTIVO | G36: MIRANDA | H36: =VLOOKUP(Tabla3[[#This Row],[NUEVA RUTA]],Tabla1[#All],2,0) -> INACTIVO | I36: =VLOOKUP($A36,Clientes!$A$1:$C$1999,3,0) -> STA ROSA LIMA | J36: 57 | K36: =VLOOKUP($J36,'ESTRUCTURA P&B - LP'!$A$1:$F$40,5,0) -> CARLOS ZURITA | L36: =IFERROR(VLOOKUP($J36,'[2]POTENCIAL X ZONA'!$B$4:$G$21,6,0),0) -> 0 | M36: =IFERROR(VLOOKUP($A36,'Convenio Clientes'!$D:$F,3,0),"SN CNV") -> 01 | N36: 06 | O36: 7 | P36: INACTIVO | Q36: NO | R36: =VLOOKUP($N36,Tabla2[#All],3,0) -> SUPERMERCADOS INDEPENDIENTES | S36: CTRA PANAMERICANA KM 20, CALLE LOS PINOS | T36: LOCAL NRO N° 1 y 2 SECTOR CORRALITO | U36: CARACAS
A37: J298782366 | B37: AUTOMERCADOS FRESCO MARKET AFN C.A. | C37: 50 | D37: 10 | E37: =VLOOKUP($D37,'ESTRUCTURA P&B - LP'!$A$1:$F$31,5,0) -> MILAGROS FERNANDEZ 10 | F37: =VLOOKUP($D37,'ESTRUCTURA P&B - LP'!$A$1:$F$31,6,0) -> MILAGROS FERNANDEZ | G37: MIRANDA | H37: =VLOOKUP(Tabla3[[#This Row],[NUEVA RUTA]],Tabla1[#All],2,0) -> CAPITAL | I37: =VLOOKUP($A37,Clientes!$A$1:$C$1999,3,0) -> 66 FRESC.MARKET | J37: 10 | K37: =VLOOKUP($J37,'ESTRUCTURA P&B - LP'!$A$1:$F$40,5,0) -> MILAGROS FERNANDEZ 10 | L37: =IFERROR(VLOOKUP($J37,'[2]POTENCIAL X ZONA'!$B$4:$G$21,6,0),0) -> B | M37: =IFERROR(VLOOKUP($A37,'Convenio Clientes'!$D:$F,3,0),"SN CNV") -> 22 | N37: 06 | O37: 30 | P37: REGULAR | Q37: SI | R37: =VLOOKUP($N37,Tabla2[#All],3,0) -> SUPERMERCADOS INDEPENDIENTES | S37: CALLE SOJO CON CALLE CARABOBO | T37: QTA. IBAIONDO NRO N/A | U37: CARRIZAL
A38: J305113530 | B38: AUTOMERCADOS KLASSE, C.A. | C38: 98 | D38: 98 | E38: =VLOOKUP($D38,'ESTRUCTURA P&B - LP'!$A$1:$F$31,5,0) -> INACTIVO | F38: =VLOOKUP($D38,'ESTRUCTURA P&B - LP'!$A$1:$F$31,6,0) -> INACTIVO | G38: MIRANDA | H38: =VLOOKUP(Tabla3[[#This Row],[NUEVA RUTA]],Tabla1[#All],2,0) -> INACTIVO | I38: =VLOOKUP($A38,Clientes!$A$1:$C$1999,3,0) -> AUT KLASSE | J38: 0 | K38: =VLOOKUP($J38,'ESTRUCTURA P&B - LP'!$A$1:$F$40,5,0) -> INACTIVO | L38: =IFERROR(VLOOKUP($J38,'[2]POTENCIAL X ZONA'!$B$4:$G$21,6,0),0) -> 0 | M38: =IFERROR(VLOOKUP($A38,'Convenio Clientes'!$D:$F,3,0),"SN CNV") -> 01 | N38: 06 | O38: 0 | P38: INACTIVO | Q38: NO | R38: =VLOOKUP($N38,Tabla2[#All],3,0) -> SUPERMERCADOS INDEPENDIENTES | S38: AAV SAN SEBASTIAN EDIF PLAZA'S | T38: PISO PB OF UNICA | U38: CARACAS
A39: J306725024 | B39: AUTOMERCADOS PLAZA'S, C.A. | C39: 58 | D39: 10 | E39: =VLOOKUP($D39,'ESTRUCTURA P&B - LP'!$A$1:$F$31,5,0) -> MILAGROS FERNANDEZ 10 | F39: =VLOOKUP($D39,'ESTRUCTURA P&B - LP'!$A$1:$F$31,6,0) -> MILAGROS FERNANDEZ | G39: MIRANDA | H39: =VLOOKUP(Tabla3[[#This Row],[NUEVA RUTA]],Tabla1[#All],2,0) -> CAPITAL | I39: =VLOOKUP($A39,Clientes!$A$1:$C$1999,3,0) -> 42 PLAZA | J39: 10 | K39: =VLOOKUP($J39,'ESTRUCTURA P&B - LP'!$A$1:$F$40,5,0) -> MILAGROS FERNANDEZ 10 | L39: =IFERROR(VLOOKUP($J39,'[2]POTENCIAL X ZONA'!$B$4:$G$21,6,0),0) -> B | M39: =IFERROR(VLOOKUP($A39,'Convenio Clientes'!$D:$F,3,0),"SN CNV") -> 22 | N39: 03 | O39: 60 | P39: EVENTUAL | Q39: SI | R39: =VLOOKUP($N39,Tabla2[#All],3,0) -> CADENAS - SUPERMERCADOS | S39: AV LARA CRUCE CON CALLE BRANGER | T39: CC REGIONAL LOCAL SUPERMERCADO | U39: CARACAS
A40: J407238035 | B40: AUTOMERCADOS SUPER REY VALENCIA C,A | C40: 98 | D40: 98 | E40: =VLOOKUP($D40,'ESTRUCTURA P&B - LP'!$A$1:$F$31,5,0) -> INACTIVO | F40: =VLOOKUP($D40,'ESTRUCTURA P&B - LP'!$A$1:$F$31,6,0) -> INACTIVO | G40: CARABOBO | H40: =VLOOKUP(Tabla3[[#This Row],[NUEVA RUTA]],Tabla1[#All],2,0) -> INACTIVO | I40: =VLOOKUP($A40,Clientes!$A$1:$C$1999,3,0) -> AUTOM SUPER REY | J40: 12 | K40: =VLOOKUP($J40,'ESTRUCTURA P&B - LP'!$A$1:$F$40,5,0) -> JUAN LEÓN 12 | L40: =IFERROR(VLOOKUP($J40,'[2]POTENCIAL X ZONA'!$B$4:$G$21,6,0),0) -> P | M40: =IFERROR(VLOOKUP($A40,'Convenio Clientes'!$D:$F,3,0),"SN CNV") -> 01 | N40: 06 | O40: 15 | P40: INACTIVO | Q40: NO | R40: =VLOOKUP($N40,Tabla2[#All],3,0) -> SUPERMERCADOS INDEPENDIENTES | S40: CALLE SOUBLETTE C/C BOYACA CC 19 | T40: DE ABRIL N MZZ. SECTOR CENTRO | U40: VALENCIA
A41: J316324311 | B41: AUTOMERCADOS SUPER REY, C.A | C41: 98 | D41: 98 | E41: =VLOOKUP($D41,'ESTRUCTURA P&B - LP'!$A$1:$F$31,5,0) -> INACTIVO | F41: =VLOOKUP($D41,'ESTRUCTURA P&B - LP'!$A$1:$F$31,6,0) -> INACTIVO | G41: ARAGUA | H41: =VLOOKUP(Tabla3[[#This Row],[NUEVA RUTA]],Tabla1[#All],2,0) -> INACTIVO | I41: =VLOOKUP($A41,Clientes!$A$1:$C$1999,3,0) -> AUTOM SUPER REY | J41: 12 | K41: =VLOOKUP($J41,'ESTRUCTURA P&B - LP'!$A$1:$F$40,5,0) -> JUAN LEÓN 12 | L41: =IFERROR(VLOOKUP($J41,'[2]POTENCIAL X ZONA'!$B$4:$G$21,6,0),0) -> P | M41: =IFERROR(VLOOKUP($A41,'Convenio Clientes'!$D:$F,3,0),"SN CNV") -> 01 | N41: 06 | O41: 0 | P41: INACTIVO | Q41: NO | R41: =VLOOKUP($N41,Tabla2[#All],3,0) -> SUPERMERCADOS INDEPENDIENTES | S41: 4AV. DE PREBO URB. EL PARRAL | T41: C.C PIAZZA, LOCAL 15 Y 16 | U41: MARACAY
A42: J310186839 | B42: AUTOSALUD FARMACIA, C.A. | C42: 98 | D42: 98 | E42: =VLOOKUP($D42,'ESTRUCTURA P&B - LP'!$A$1:$F$31,5,0) -> INACTIVO | F42: =VLOOKUP($D42,'ESTRUCTURA P&B - LP'!$A$1:$F$31,6,0) -> INACTIVO | G42: CARABOBO | H42: =VLOOKUP(Tabla3[[#This Row],[NUEVA RUTA]],Tabla1[#All],2,0) -> INACTIVO | I42: =VLOOKUP($A42,Clientes!$A$1:$C$1999,3,0) -> 65 LOCATEL | J42: 0 | K42: =VLOOKUP($J42,'ESTRUCTURA P&B - LP'!$A$1:$F$40,5,0) -> INACTIVO | L42: =IFERROR(VLOOKUP($J42,'[2]POTENCIAL X ZONA'!$B$4:$G$21,6,0),0) -> 0 | M42: =IFERROR(VLOOKUP($A42,'Convenio Clientes'!$D:$F,3,0),"SN CNV") -> 01 | N42: 01 | O42: 0 | P42: INACTIVO | Q42: NO | R42: =VLOOKUP($N42,Tabla2[#All],3,0) -> CADENAS - FARMACIAS | S42: AV PRINCIPAL CC PARQUE AVILA NIVEL C-1 | T42: LOCAL 3 URB TERRAZAS DEL AVILA CARACAS | U42: VALENCIA
A43: J316786110 | B43: AVILA PINTURAS, C.A. | C43: 98 | D43: =+C43 -> 98 | E43: =VLOOKUP($D43,'ESTRUCTURA P&B - LP'!$A$1:$F$31,5,0) -> INACTIVO | F43: =VLOOKUP($D43,'ESTRUCTURA P&B - LP'!$A$1:$F$31,6,0) -> INACTIVO | G43: MIRANDA | H43: =VLOOKUP(Tabla3[[#This Row],[NUEVA RUTA]],Tabla1[#All],2,0) -> INACTIVO | I43: =VLOOKUP($A43,Clientes!$A$1:$C$1999,3,0) -> AVILA PINTURA | J43: 95 | K43: =VLOOKUP($J43,'ESTRUCTURA P&B - LP'!$A$1:$F$40,5,0) -> EVENTUALES | L43: =IFERROR(VLOOKUP($J43,'[2]POTENCIAL X ZONA'!$B$4:$G$21,6,0),0) -> 0 | M43: =IFERROR(VLOOKUP($A43,'Convenio Clientes'!$D:$F,3,0),"SN CNV") -> 21 | N43: 09 | O43: 0 | P43: EVENTUAL | Q43: OFICINA | R43: =VLOOKUP($N43,Tabla2[#All],3,0) -> INSTITUCIONAL | S43: AV SOUBLETTE EDIF PARCELA 95 Y 96 MANZANA | T43: E PISO 0 LOCAL COMERCIAL URB MIRAMAR | U43: CARACAS
A44: J401272827 | B44: BAHIA SUPERMARKET, C.A | C44: 10 | D44: 10 | E44: =VLOOKUP($D44,'ESTRUCTURA P&B - LP'!$A$1:$F$31,5,0) -> MILAGROS FERNANDEZ 10 | F44: =VLOOKUP($D44,'ESTRUCTURA P&B - LP'!$A$1:$F$31,6,0) -> MILAGROS FERNANDEZ | G44: LA GUAIRA | H44: =VLOOKUP(Tabla3[[#This Row],[NUEVA RUTA]],Tabla1[#All],2,0) -> CAPITAL | I44: =VLOOKUP($A44,Clientes!$A$1:$C$1999,3,0) -> BAHIA SUPERMARK | J44: =+D44 -> 10 | K44: =VLOOKUP($J44,'ESTRUCTURA P&B - LP'!$A$1:$F$40,5,0) -> MILAGROS FERNANDEZ 10 | L44: =IFERROR(VLOOKUP($J44,'[2]POTENCIAL X ZONA'!$B$4:$G$21,6,0),0) -> B | M44: =IFERROR(VLOOKUP($A44,'Convenio Clientes'!$D:$F,3,0),"SN CNV") -> 21 | N44: 03 | O44: 21 | P44: INACTIVO | Q44: NO | R44: =VLOOKUP($N44,Tabla2[#All],3,0) -> CADENAS - SUPERMERCADOS | S44: AV URDANETA ESQ LAS CARMELITAS TORRE | T44: FNCIERA PISO 22 OF VICEPRESID CARACAS | U44: LA GUAIRA
A45: G200001100 | B45: BANCO CENTRAL DE VENEZUELA | C45: 98 | D45: =Tabla3[[#This Row],[ID ASESOR ANTERIOR]] -> 98 | E45: =VLOOKUP($D45,'ESTRUCTURA P&B - LP'!$A$1:$F$31,5,0) -> INACTIVO | F45: =VLOOKUP($D45,'ESTRUCTURA P&B - LP'!$A$1:$F$31,6,0) -> INACTIVO | G45: DISTRITO CAPITAL | H45: =VLOOKUP(Tabla3[[#This Row],[NUEVA RUTA]],Tabla1[#All],2,0) -> INACTIVO | I45: =VLOOKUP($A45,Clientes!$A$1:$C$1999,3,0) -> BCO CTRAL VZLA | J45: 10 | K45: =VLOOKUP($J45,'ESTRUCTURA P&B - LP'!$A$1:$F$40,5,0) -> MILAGROS FERNANDEZ 10 | L45: =IFERROR(VLOOKUP($J45,'[2]POTENCIAL X ZONA'!$B$4:$G$21,6,0),0) -> B | M45: =IFERROR(VLOOKUP($A45,'Convenio Clientes'!$D:$F,3,0),"SN CNV") -> 01 | N45: 09 | O45: 0 | P45: INACTIVO | Q45: NO | R45: =VLOOKUP($N45,Tabla2[#All],3,0) -> INSTITUCIONAL | S45: AV.ALBERTO A.TORREALBA,C/C PROGRESO | T45: CC LOCATEL NIV-1,LOC-68 URB. JARD ALTO | U45: CARACAS
A46: J314850890 | B46: BARINTEL FARMACIA, C.A. | C46: 23 | D46: 23 | E46: =VLOOKUP($D46,'ESTRUCTURA P&B - LP'!$A$1:$F$31,5,0) -> MARTHA VILORIA | F46: =VLOOKUP($D46,'ESTRUCTURA P&B - LP'!$A$1:$F$31,6,0) -> DUBRASKA PÉREZ | G46: BARINAS | H46: =VLOOKUP(Tabla3[[#This Row],[NUEVA RUTA]],Tabla1[#All],2,0) -> CENTRO-OCCIDENTE | I46: =VLOOKUP($A46,Clientes!$A$1:$C$1999,3,0) -> 65 LOCATEL | J46: 23 | K46: =VLOOKUP($J46,'ESTRUCTURA P&B - LP'!$A$1:$F$40,5,0) -> MARTHA VILORIA | L46: =IFERROR(VLOOKUP($J46,'[2]POTENCIAL X ZONA'!$B$4:$G$21,6,0),0) -> S | M46: =IFERROR(VLOOKUP($A46,'Convenio Clientes'!$D:$F,3,0),"SN CNV") -> 21 | N46: 01 | O46: 15 | P46: REGULAR | Q46: SI | R46: =VLOOKUP($N46,Tabla2[#All],3,0) -> CADENAS - FARMACIAS | S46: CALLE SANCHEZ CARRERO NORTE NRO.14 | T46: EDF LUNA BELLA LOCAL PB | U46: BARINAS
A47: J314527363 | B47: BAZAR AVANZA, C.A. | C47: 98 | D47: 98 | E47: =VLOOKUP($D47,'ESTRUCTURA P&B - LP'!$A$1:$F$31,5,0) -> INACTIVO | F47: =VLOOKUP($D47,'ESTRUCTURA P&B - LP'!$A$1:$F$31,6,0) -> INACTIVO | G47: ARAGUA | H47: =VLOOKUP(Tabla3[[#This Row],[NUEVA RUTA]],Tabla1[#All],2,0) -> INACTIVO | I47: =VLOOKUP($A47,Clientes!$A$1:$C$1999,3,0) -> BAZAR AVANZA | J47: 12 | K47: =VLOOKUP($J47,'ESTRUCTURA P&B - LP'!$A$1:$F$40,5,0) -> JUAN LEÓN 12 | L47: =IFERROR(VLOOKUP($J47,'[2]POTENCIAL X ZONA'!$B$4:$G$21,6,0),0) -> P | M47: =IFERROR(VLOOKUP($A47,'Convenio Clientes'!$D:$F,3,0),"SN CNV") -> 21 | N47: 15 | O47: 7 | P47: INACTIVO | Q47: NO | R47: =VLOOKUP($N47,Tabla2[#All],3,0) -> MAYORISTAS | S47: CALLE 92 ENTRE AV 19 Y 20 CASA 12-78 SECTOR | T47: ENTRANDO POR LA ESTACION DE SERVICIOS MIRANDA | U47: MARACAY
A48: J501317623 | B48: BIG BANG IMPORT, C.A | C48: 50 | D48: 50 | E48: =VLOOKUP($D48,'ESTRUCTURA P&B - LP'!$A$1:$F$31,5,0) -> BETSY CASTRO | F48: =VLOOKUP($D48,'ESTRUCTURA P&B - LP'!$A$1:$F$31,6,0) -> MILAGROS FERNANDEZ | G48: DISTRITO CAPITAL | H48: =VLOOKUP(Tabla3[[#This Row],[NUEVA RUTA]],Tabla1[#All],2,0) -> CAPITAL | I48: =VLOOKUP($A48,Clientes!$A$1:$C$1999,3,0) -> BIG BANG IMPORT | J48: 50 | K48: =VLOOKUP($J48,'ESTRUCTURA P&B - LP'!$A$1:$F$40,5,0) -> BETSY CASTRO | L48: =IFERROR(VLOOKUP($J48,'[2]POTENCIAL X ZONA'!$B$4:$G$21,6,0),0) -> B | M48: =IFERROR(VLOOKUP($A48,'Convenio Clientes'!$D:$F,3,0),"SN CNV") -> 20 | N48: 07 | O48: 15 | P48: INACTIVO | Q48: NO | R48: =VLOOKUP($N48,Tabla2[#All],3,0) -> DISTRIBUIDOR | S48: CALLE TRANSVERSAL N° 2 LOCAL GALPÓN 7 Y 8 | T48: ZONA IND. LOS PINOS | U48: CARACAS
A49: J410939648 | B49: BIG DISTRIBUCIONES, CA | C49: 98 | D49: 98 | E49: =VLOOKUP($D49,'ESTRUCTURA P&B - LP'!$A$1:$F$31,5,0) -> INACTIVO | F49: =VLOOKUP($D49,'ESTRUCTURA P&B - LP'!$A$1:$F$31,6,0) -> INACTIVO | G49: ZULIA | H49: =VLOOKUP(Tabla3[[#This Row],[NUEVA RUTA]],Tabla1[#All],2,0) -> INACTIVO | I49: =VLOOKUP($A49,Clientes!$A$1:$C$1999,3,0) -> BIG DISTRIB | J49: 0 | K49: =VLOOKUP($J49,'ESTRUCTURA P&B - LP'!$A$1:$F$40,5,0) -> INACTIVO | L49: =IFERROR(VLOOKUP($J49,'[2]POTENCIAL X ZONA'!$B$4:$G$21,6,0),0) -> 0 | M49: =IFERROR(VLOOKUP($A49,'Convenio Clientes'!$D:$F,3,0),"SN CNV") -> 01 | N49: 07 | O49: 0 | P49: INACTIVO | Q49: NO | R49: =VLOOKUP($N49,Tabla2[#All],3,0) -> DISTRIBUIDOR | S49: AV MAÑONGO CC PATIO TRIGAL PLANTA NIVEL BAJA LOCAL N°400 | T49: SECTOR S-4 | U49: MARACAIBO
A50: J403114099 | B50: BIOMERCADOS, C.A | C50: 98 | D50: 98 | E50: =VLOOKUP($D50,'ESTRUCTURA P&B - LP'!$A$1:$F$31,5,0) -> INACTIVO | F50: =VLOOKUP($D50,'ESTRUCTURA P&B - LP'!$A$1:$F$31,6,0) -> INACTIVO | G50: CARABOBO | H50: =VLOOKUP(Tabla3[[#This Row],[NUEVA RUTA]],Tabla1[#All],2,0) -> INACTIVO | I50: =VLOOKUP($A50,Clientes!$A$1:$C$1999,3,0) -> BIOMERCADOS | J50: =+D50 -> 98 | K50: =VLOOKUP($J50,'ESTRUCTURA P&B - LP'!$A$1:$F$40,5,0) -> INACTIVO | L50: =IFERROR(VLOOKUP($J50,'[2]POTENCIAL X ZONA'!$B$4:$G$21,6,0),0) -> 0 | M50: =IFERROR(VLOOKUP($A50,'Convenio Clientes'!$D:$F,3,0),"SN CNV") -> 21 | N50: 03 | O50: 30 | P50: INACTIVO | Q50: NO | R50: =VLOOKUP($N50,Tabla2[#All],3,0) -> CADENAS - SUPERMERCADOS | S50: AV OCTAVIO VIANA VIA EL SOMBRERO LOCAL | T50: S/N, SECTOR ZONA INDUSTRIAL DEL IQUE | U50: VALENCIA
A51: J311205268 | B51: BLITZ 2010 C.A. | C51: 98 | D51: 98 | E51: =VLOOKUP($D51,'ESTRUCTURA P&B - LP'!$A$1:$F$31,5,0) -> INACTIVO | F51: =VLOOKUP($D51,'ESTRUCTURA P&B - LP'!$A$1:$F$31,6,0) -> INACTIVO | G51: GUARICO | H51: =VLOOKUP(Tabla3[[#This Row],[NUEVA RUTA]],Tabla1[#All],2,0) -> INACTIVO | I51: =VLOOKUP($A51,Clientes!$A$1:$C$1999,3,0) -> BLITZ 2010 | J51: 0 | K51: =VLOOKUP($J51,'ESTRUCTURA P&B - LP'!$A$1:$F$40,5,0) -> INACTIVO | L51: =IFERROR(VLOOKUP($J51,'[2]POTENCIAL X ZONA'!$B$4:$G$21,6,0),0) -> 0 | M51: =IFERROR(VLOOKUP($A51,'Convenio Clientes'!$D:$F,3,0),"SN CNV") -> 01 | N51: 07 | O51: 0 | P51: INACTIVO | Q51: NO | R51: =VLOOKUP($N51,Tabla2[#All],3,0) -> DISTRIBUIDOR | S51: AV EEUU CON CALLE ARGENTINA | T51: MANZANA 18 LOCAL PARCELA NRO 3 | U51: CALABOZO
A52: J502230076 | B52: BODEGON LA CANAIMA, C.A | C52: 98 | D52: 98 | E52: =VLOOKUP($D52,'ESTRUCTURA P&B - LP'!$A$1:$F$31,5,0) -> INACTIVO | F52: =VLOOKUP($D52,'ESTRUCTURA P&B - LP'!$A$1:$F$31,6,0) -> INACTIVO | G52: MIRANDA | H52: =VLOOKUP(Tabla3[[#This Row],[NUEVA RUTA]],Tabla1[#All],2,0) -> INACTIVO | I52: =VLOOKUP($A52,Clientes!$A$1:$C$1999,3,0) -> BODEGON CANAIMA | J52: 10 | K52: =VLOOKUP($J52,'ESTRUCTURA P&B - LP'!$A$1:$F$40,5,0) -> MILAGROS FERNANDEZ 10 | L52: =IFERROR(VLOOKUP($J52,'[2]POTENCIAL X ZONA'!$B$4:$G$21,6,0),0) -> B | M52: =IFERROR(VLOOKUP($A52,'Convenio Clientes'!$D:$F,3,0),"SN CNV") -> 21 | N52: 03 | O52: 21 | P52: INACTIVO | Q52: NO | R52: =VLOOKUP($N52,Tabla2[#All],3,0) -> CADENAS - SUPERMERCADOS | S52: AV ESQUINA AV.BOLIVAR SECTOR LAS ACACIAS EDF GINER | T52: PISO 1 LOCAL N° 1 Y 2 URB LAS ACACIAS | U52: CARACAS
A53: J500257520 | B53: BODEGON LA CARIBEÑA II, C.A. | C53: 52 | D53: 52 | E53: =VLOOKUP($D53,'ESTRUCTURA P&B - LP'!$A$1:$F$31,5,0) -> DIANA DELGADO 52 | F53: =VLOOKUP($D53,'ESTRUCTURA P&B - LP'!$A$1:$F$31,6,0) -> DIANA DELGADO | G53: BOLIVAR | H53: =VLOOKUP(Tabla3[[#This Row],[NUEVA RUTA]],Tabla1[#All],2,0) -> ORIENTE SUR | I53: =VLOOKUP($A53,Clientes!$A$1:$C$1999,3,0) -> BGON L CARIBEÑA | J53: 52 | K53: =VLOOKUP($J53,'ESTRUCTURA P&B - LP'!$A$1:$F$40,5,0) -> DIANA DELGADO 52 | L53: =IFERROR(VLOOKUP($J53,'[2]POTENCIAL X ZONA'!$B$4:$G$21,6,0),0) -> S | M53: =IFERROR(VLOOKUP($A53,'Convenio Clientes'!$D:$F,3,0),"SN CNV") -> 21 | N53: 16 | O53: 10 | P53: INACTIVO | Q53: NO | R53: =VLOOKUP($N53,Tabla2[#All],3,0) -> BODEGONES | S53: AV UNIVERSIDAD LOCAL ANEXO A/A | T53: ESTACION DE SERVICIO PARAMACAY | U53: PUERTO ORDAZ | V53: CERRÓ 1/7/25
A54: J306948953 | B54: BODEGON MILLENNIUM, C.A. | C54: 98 | D54: 98 | E54: =VLOOKUP($D54,'ESTRUCTURA P&B - LP'!$A$1:$F$31,5,0) -> INACTIVO | F54: =VLOOKUP($D54,'ESTRUCTURA P&B - LP'!$A$1:$F$31,6,0) -> INACTIVO | G54: CARABOBO | H54: =VLOOKUP(Tabla3[[#This Row],[NUEVA RUTA]],Tabla1[#All],2,0) -> INACTIVO | I54: =VLOOKUP($A54,Clientes!$A$1:$C$1999,3,0) -> BOD MILLENNIUM | J54: 20 | K54: =VLOOKUP($J54,'ESTRUCTURA P&B - LP'!$A$1:$F$40,5,0) -> JUAN LEÓN 20 | L54: =IFERROR(VLOOKUP($J54,'[2]POTENCIAL X ZONA'!$B$4:$G$21,6,0),0) -> P | M54: =IFERROR(VLOOKUP($A54,'Convenio Clientes'!$D:$F,3,0),"SN CNV") -> 21 | N54: 03 | O54: 30 | P54: INACTIVO | Q54: NO | R54: =VLOOKUP($N54,Tabla2[#All],3,0) -> CADENAS - SUPERMERCADOS | S54: AV 91 ENTRE CALLES 79G Y 79I | T54: LOCAL NRO 79G-71 | U54: NAGUANAGUA
A55: J411076112 | B55: BOGA COSMETICS C.A | C55: 62 | D55: 21 | E55: =VLOOKUP($D55,'ESTRUCTURA P&B - LP'!$A$1:$F$31,5,0) -> ANDREINA RANGEL 21 | F55: =VLOOKUP($D55,'ESTRUCTURA P&B - LP'!$A$1:$F$31,6,0) -> ANDREINA RANGEL | G55: ZULIA | H55: =VLOOKUP(Tabla3[[#This Row],[NUEVA RUTA]],Tabla1[#All],2,0) -> OCCIDENTE | I55: =VLOOKUP($A55,Clientes!$A$1:$C$1999,3,0) -> 30 SAN JUAN | J55: 62 | K55: =VLOOKUP($J55,'ESTRUCTURA P&B - LP'!$A$1:$F$40,5,0) -> ANDREINA RANGEL 62 | L55: =IFERROR(VLOOKUP($J55,'[2]POTENCIAL X ZONA'!$B$4:$G$21,6,0),0) -> S | M55: =IFERROR(VLOOKUP($A55,'Convenio Clientes'!$D:$F,3,0),"SN CNV") -> 20 | N55: 07 | O55: 15 | P55: REGULAR | Q55: SI | R55: =VLOOKUP($N55,Tabla2[#All],3,0) -> DISTRIBUIDOR | S55: CLL PPAL RIVERAS DEL TORBES LOC.GALPON | T55: NRO.L-04,SECTOR BARRANCAS TARIBA | U55: MARACAIBO
A56: J070012250 | B56: C.A. MAFARTA | C56: 21 | D56: 21 | E56: =VLOOKUP($D56,'ESTRUCTURA P&B - LP'!$A$1:$F$31,5,0) -> ANDREINA RANGEL 21 | F56: =VLOOKUP($D56,'ESTRUCTURA P&B - LP'!$A$1:$F$31,6,0) -> ANDREINA RANGEL | G56: TACHIRA | H56: =VLOOKUP(Tabla3[[#This Row],[NUEVA RUTA]],Tabla1[#All],2,0) -> OCCIDENTE | I56: =VLOOKUP($A56,Clientes!$A$1:$C$1999,3,0) -> 13 COBECA | J56: 21 | K56: =VLOOKUP($J56,'ESTRUCTURA P&B - LP'!$A$1:$F$40,5,0) -> ANDREINA RANGEL 21 | L56: =IFERROR(VLOOKUP($J56,'[2]POTENCIAL X ZONA'!$B$4:$G$21,6,0),0) -> S | M56: =IFERROR(VLOOKUP($A56,'Convenio Clientes'!$D:$F,3,0),"SN CNV") -> 21 | N56: 08 | O56: 30 | P56: REGULAR | Q56: SI | R56: =VLOOKUP($N56,Tabla2[#All],3,0) -> DROGUERIAS | S56: AV VENEZUELA EDIF TORRE BANAVIH PISO 3 | T56: OF 3 URB EL ROSAL | U56: SAN CRISTOBAL
A57: J000745471 | B57: CAJA DE AHORRO DEL PERSONAL DEL BANCO NAC. DE VIVIENDA Y HABITAT | C57: 98 | D57: 98 | E57: =VLOOKUP($D57,'ESTRUCTURA P&B - LP'!$A$1:$F$31,5,0) -> INACTIVO | F57: =VLOOKUP($D57,'ESTRUCTURA P&B - LP'!$A$1:$F$31,6,0) -> INACTIVO | G57: MIRANDA | H57: =VLOOKUP(Tabla3[[#This Row],[NUEVA RUTA]],Tabla1[#All],2,0) -> INACTIVO | I57: =VLOOKUP($A57,Clientes!$A$1:$C$1999,3,0) -> BCO NAC VIVIEND | J57: 0 | K57: =VLOOKUP($J57,'ESTRUCTURA P&B - LP'!$A$1:$F$40,5,0) -> INACTIVO | L57: =IFERROR(VLOOKUP($J57,'[2]POTENCIAL X ZONA'!$B$4:$G$21,6,0),0) -> 0 | M57: =IFERROR(VLOOKUP($A57,'Convenio Clientes'!$D:$F,3,0),"SN CNV") -> 01 | N57: 09 | O57: 0 | P57: INACTIVO | Q57: NO | R57: =VLOOKUP($N57,Tabla2[#All],3,0) -> INSTITUCIONAL | S57: AV ANDRES BELLO | T57: CALLE 4 CON CALLE 5 | U57: CARACAS
A58: J294280986 | B58: CALIFORNIA HOME FASHIONS, C.A. | C58: 98 | D58: 98 | E58: =VLOOKUP($D58,'ESTRUCTURA P&B - LP'!$A$1:$F$31,5,0) -> INACTIVO | F58: =VLOOKUP($D58,'ESTRUCTURA P&B - LP'!$A$1:$F$31,6,0) -> INACTIVO | G58: MIRANDA | H58: =VLOOKUP(Tabla3[[#This Row],[NUEVA RUTA]],Tabla1[#All],2,0) -> INACTIVO | I58: =VLOOKUP($A58,Clientes!$A$1:$C$1999,3,0) -> CALIFORNIA HOME | J58: 0 | K58: =VLOOKUP($J58,'ESTRUCTURA P&B - LP'!$A$1:$F$40,5,0) -> INACTIVO | L58: =IFERROR(VLOOKUP($J58,'[2]POTENCIAL X ZONA'!$B$4:$G$21,6,0),0) -> 0 | M58: =IFERROR(VLOOKUP($A58,'Convenio Clientes'!$D:$F,3,0),"SN CNV") -> 01 | N58: 07 | O58: 0 | P58: INACTIVO | Q58: NO | R58: =VLOOKUP($N58,Tabla2[#All],3,0) -> DISTRIBUIDOR | S58: CALLE GUZMAN BLANCO CASA NRO 102-82 | T58: SECTOR LOS COLORADOS VALENCIA VALENCIA | U58: CARACAS
A59: J295326394 | B59: CAMPERO, C.A. | C59: 98 | D59: 98 | E59: =VLOOKUP($D59,'ESTRUCTURA P&B - LP'!$A$1:$F$31,5,0) -> INACTIVO | F59: =VLOOKUP($D59,'ESTRUCTURA P&B - LP'!$A$1:$F$31,6,0) -> INACTIVO | G59: CARABOBO | H59: =VLOOKUP(Tabla3[[#This Row],[NUEVA RUTA]],Tabla1[#All],2,0) -> INACTIVO | I59: =VLOOKUP($A59,Clientes!$A$1:$C$1999,3,0) -> CAMPERO | J59: 0 | K59: =VLOOKUP($J59,'ESTRUCTURA P&B - LP'!$A$1:$F$40,5,0) -> INACTIVO | L59: =IFERROR(VLOOKUP($J59,'[2]POTENCIAL X ZONA'!$B$4:$G$21,6,0),0) -> 0 | M59: =IFERROR(VLOOKUP($A59,'Convenio Clientes'!$D:$F,3,0),"SN CNV") -> 01 | N59: 07 | O59: 0 | P59: INACTIVO | Q59: NO | R59: =VLOOKUP($N59,Tabla2[#All],3,0) -> DISTRIBUIDOR | S59: AV PRINCIPAL DE SAN LUIS | T59: EDIF TORRE MAYUPAN PISO 1 OF 1-1 | U59: VALENCIA
A60: J501815860 | B60: CAPITALINA DE ALIMENTOS 212, C.A | C60: 10 | D60: 10 | E60: =VLOOKUP($D60,'ESTRUCTURA P&B - LP'!$A$1:$F$31,5,0) -> MILAGROS FERNANDEZ 10 | F60: =VLOOKUP($D60,'ESTRUCTURA P&B - LP'!$A$1:$F$31,6,0) -> MILAGROS FERNANDEZ | G60: MIRANDA | H60: =VLOOKUP(Tabla3[[#This Row],[NUEVA RUTA]],Tabla1[#All],2,0) -> CAPITAL | I60: =VLOOKUP($A60,Clientes!$A$1:$C$1999,3,0) -> CAPIT DE ALIMEN | J60: 10 | K60: =VLOOKUP($J60,'ESTRUCTURA P&B - LP'!$A$1:$F$40,5,0) -> MILAGROS FERNANDEZ 10 | L60: =IFERROR(VLOOKUP($J60,'[2]POTENCIAL X ZONA'!$B$4:$G$21,6,0),0) -> B | M60: =IFERROR(VLOOKUP($A60,'Convenio Clientes'!$D:$F,3,0),"SN CNV") -> 21 | N60: 07 | O60: 0 | P60: INACTIVO | Q60: NO | R60: =VLOOKUP($N60,Tabla2[#All],3,0) -> DISTRIBUIDOR | S60: 0 | T60: 0 | U60: CARACAS
A61: J412770756 | B61: CAREPHARMA, C.A. | C61: 98 | D61: 98 | E61: =VLOOKUP($D61,'ESTRUCTURA P&B - LP'!$A$1:$F$31,5,0) -> INACTIVO | F61: =VLOOKUP($D61,'ESTRUCTURA P&B - LP'!$A$1:$F$31,6,0) -> INACTIVO | G61: MIRANDA | H61: =VLOOKUP(Tabla3[[#This Row],[NUEVA RUTA]],Tabla1[#All],2,0) -> INACTIVO | I61: =VLOOKUP($A61,Clientes!$A$1:$C$1999,3,0) -> CAREPHARMA, C.A | J61: 0 | K61: =VLOOKUP($J61,'ESTRUCTURA P&B - LP'!$A$1:$F$40,5,0) -> INACTIVO | L61: =IFERROR(VLOOKUP($J61,'[2]POTENCIAL X ZONA'!$B$4:$G$21,6,0),0) -> 0 | M61: =IFERROR(VLOOKUP($A61,'Convenio Clientes'!$D:$F,3,0),"SN CNV") -> 01 | N61: 04 | O61: 0 | P61: INACTIVO | Q61: NO | R61: =VLOOKUP($N61,Tabla2[#All],3,0) -> FARMACIAS INDEPENDIENTES | S61: CALLE FINAL CALLE LAS DELIAS EDIF | T61: GALPON S/N PISO 2 LOCAL S/N SECTOR | U61: CARACAS
A62: V146234417 | B62: CARLOS ALFONSO ALVAREZ ARELLANO | C62: 98 | D62: 98 | E62: =VLOOKUP($D62,'ESTRUCTURA P&B - LP'!$A$1:$F$31,5,0) -> INACTIVO | F62: =VLOOKUP($D62,'ESTRUCTURA P&B - LP'!$A$1:$F$31,6,0) -> INACTIVO | G62: MERIDA | H62: =VLOOKUP(Tabla3[[#This Row],[NUEVA RUTA]],Tabla1[#All],2,0) -> INACTIVO | I62: =VLOOKUP($A62,Clientes!$A$1:$C$1999,3,0) -> CARLOS ALVAREZ | J62: =+D62 -> 98 | K62: =VLOOKUP($J62,'ESTRUCTURA P&B - LP'!$A$1:$F$40,5,0) -> INACTIVO | L62: =IFERROR(VLOOKUP($J62,'[2]POTENCIAL X ZONA'!$B$4:$G$21,6,0),0) -> 0 | M62: =IFERROR(VLOOKUP($A62,'Convenio Clientes'!$D:$F,3,0),"SN CNV") -> 26 | N62: 07 | O62: 15 | P62: INACTIVO | Q62: NO | R62: =VLOOKUP($N62,Tabla2[#All],3,0) -> DISTRIBUIDOR | S62: AV SUR 13 CRUZ DE CANDELARIA A MIGUELACHO | T62: EDIF CANDELARIA PLAZA PISO PB LOCAL 1,2,3 | U62: EJIDO
A63: J308537853 | B63: CASA TOKIO HIPERMERCADO 2, C.A | C63: 98 | D63: 98 | E63: =VLOOKUP($D63,'ESTRUCTURA P&B - LP'!$A$1:$F$31,5,0) -> INACTIVO | F63: =VLOOKUP($D63,'ESTRUCTURA P&B - LP'!$A$1:$F$31,6,0) -> INACTIVO | G63: DISTRITO CAPITAL | H63: =VLOOKUP(Tabla3[[#This Row],[NUEVA RUTA]],Tabla1[#All],2,0) -> INACTIVO | I63: =VLOOKUP($A63,Clientes!$A$1:$C$1999,3,0) -> CASA TOKIO HIP | J63: 50 | K63: =VLOOKUP($J63,'ESTRUCTURA P&B - LP'!$A$1:$F$40,5,0) -> BETSY CASTRO | L63: =IFERROR(VLOOKUP($J63,'[2]POTENCIAL X ZONA'!$B$4:$G$21,6,0),0) -> B | M63: =IFERROR(VLOOKUP($A63,'Convenio Clientes'!$D:$F,3,0),"SN CNV") -> 01 | N63: 06 | O63: 15 | P63: INACTIVO | Q63: NO | R63: =VLOOKUP($N63,Tabla2[#All],3,0) -> SUPERMERCADOS INDEPENDIENTES | S63: AV ANTONIO DE BERRIOS MANZANA 14 | T63: LOC S/N EL POLLITO | U63: CARACAS
A64: J312768320 | B64: CATANIA HIPERMERCADO, C.A. | C64: 20 | D64: 20 | E64: =VLOOKUP($D64,'ESTRUCTURA P&B - LP'!$A$1:$F$31,5,0) -> JUAN LEÓN 20 | F64: =VLOOKUP($D64,'ESTRUCTURA P&B - LP'!$A$1:$F$31,6,0) -> DUBRASKA PÉREZ | G64: CARABOBO | H64: =VLOOKUP(Tabla3[[#This Row],[NUEVA RUTA]],Tabla1[#All],2,0) -> CENTRO-OCCIDENTE | I64: =VLOOKUP($A64,Clientes!$A$1:$C$1999,3,0) -> CATANIA HIPER | J64: 20 | K64: =VLOOKUP($J64,'ESTRUCTURA P&B - LP'!$A$1:$F$40,5,0) -> JUAN LEÓN 20 | L64: =IFERROR(VLOOKUP($J64,'[2]POTENCIAL X ZONA'!$B$4:$G$21,6,0),0) -> P | M64: =IFERROR(VLOOKUP($A64,'Convenio Clientes'!$D:$F,3,0),"SN CNV") -> 21 | N64: 03 | O64: 30 | P64: REGULAR | Q64: SI | R64: =VLOOKUP($N64,Tabla2[#All],3,0) -> CADENAS - SUPERMERCADOS | S64: CALLE BOLIVAR EDF MAPORAL PB | T64: PISO PB APT P/B SECTOR EL ARENAL | U64: PUERTO CABELLO
A65: J310030090 | B65: CENTRAL EL LOTO DE GUAYANA C.A. | C65: 98 | D65: 98 | E65: =VLOOKUP($D65,'ESTRUCTURA P&B - LP'!$A$1:$F$31,5,0) -> INACTIVO | F65: =VLOOKUP($D65,'ESTRUCTURA P&B - LP'!$A$1:$F$31,6,0) -> INACTIVO | G65: BOLIVAR | H65: =VLOOKUP(Tabla3[[#This Row],[NUEVA RUTA]],Tabla1[#All],2,0) -> INACTIVO | I65: =VLOOKUP($A65,Clientes!$A$1:$C$1999,3,0) -> C LOTO GUAYANA | J65: 0 | K65: =VLOOKUP($J65,'ESTRUCTURA P&B - LP'!$A$1:$F$40,5,0) -> INACTIVO | L65: =IFERROR(VLOOKUP($J65,'[2]POTENCIAL X ZONA'!$B$4:$G$21,6,0),0) -> 0 | M65: =IFERROR(VLOOKUP($A65,'Convenio Clientes'!$D:$F,3,0),"SN CNV") -> 01 | N65: 15 | O65: 0 | P65: INACTIVO | Q65: NO | R65: =VLOOKUP($N65,Tabla2[#All],3,0) -> MAYORISTAS | S65: CTRA.VIEJA PETARE STA LUCIA, KM 5, ED. | T65: CM P-PB, OF CTRO CM, FILAS DE MARICHE | U65: SAN FELIX
A66: J000062757 | B66: CENTRAL MADEIRENSE, C.A. | C66: 98 | D66: 98 | E66: =VLOOKUP($D66,'ESTRUCTURA P&B - LP'!$A$1:$F$31,5,0) -> INACTIVO | F66: =VLOOKUP($D66,'ESTRUCTURA P&B - LP'!$A$1:$F$31,6,0) -> INACTIVO | G66: MIRANDA | H66: =VLOOKUP(Tabla3[[#This Row],[NUEVA RUTA]],Tabla1[#All],2,0) -> INACTIVO | I66: =VLOOKUP($A66,Clientes!$A$1:$C$1999,3,0) -> 02 MADEIRENSE | J66: 0 | K66: =VLOOKUP($J66,'ESTRUCTURA P&B - LP'!$A$1:$F$40,5,0) -> INACTIVO | L66: =IFERROR(VLOOKUP($J66,'[2]POTENCIAL X ZONA'!$B$4:$G$21,6,0),0) -> 0 | M66: =IFERROR(VLOOKUP($A66,'Convenio Clientes'!$D:$F,3,0),"SN CNV") -> 21 | N66: 03 | O66: 0 | P66: INACTIVO | Q66: NO | R66: =VLOOKUP($N66,Tabla2[#All],3,0) -> CADENAS - SUPERMERCADOS | S66: CALLE 78 DR. PORTILLO CON AV. 3-F. | T66: 0 | U66: CARACAS
A67: J070137290 | B67: CHARCUTERIA FINA, C.A. | C67: 98 | D67: 98 | E67: =VLOOKUP($D67,'ESTRUCTURA P&B - LP'!$A$1:$F$31,5,0) -> INACTIVO | F67: =VLOOKUP($D67,'ESTRUCTURA P&B - LP'!$A$1:$F$31,6,0) -> INACTIVO | G67: ZULIA | H67: =VLOOKUP(Tabla3[[#This Row],[NUEVA RUTA]],Tabla1[#All],2,0) -> INACTIVO | I67: =VLOOKUP($A67,Clientes!$A$1:$C$1999,3,0) -> CHARCUTERI FINA | J67: 0 | K67: =VLOOKUP($J67,'ESTRUCTURA P&B - LP'!$A$1:$F$40,5,0) -> INACTIVO | L67: =IFERROR(VLOOKUP($J67,'[2]POTENCIAL X ZONA'!$B$4:$G$21,6,0),0) -> 0 | M67: =IFERROR(VLOOKUP($A67,'Convenio Clientes'!$D:$F,3,0),"SN CNV") -> 01 | N67: 07 | O67: 0 | P67: INACTIVO | Q67: NO | R67: =VLOOKUP($N67,Tabla2[#All],3,0) -> DISTRIBUIDOR | S67: CALLE UNV METROPOLITANA. EDF COLEGIO | T67: INTEGRAL EL AVILA PISO 1. | U67: MARACAIBO
A68: J500839014 | B68: CLINICAS SOLUMEDICA, C.A. | C68: 99 | D68: 99 | E68: =VLOOKUP($D68,'ESTRUCTURA P&B - LP'!$A$1:$F$31,5,0) -> E-COMMERCE | F68: =VLOOKUP($D68,'ESTRUCTURA P&B - LP'!$A$1:$F$31,6,0) -> E-COMMERCE | G68: MIRANDA | H68: =VLOOKUP(Tabla3[[#This Row],[NUEVA RUTA]],Tabla1[#All],2,0) -> E-COMMERCE | I68: =VLOOKUP($A68,Clientes!$A$1:$C$1999,3,0) -> CLIN SOLUMEDICA | J68: 99 | K68: =VLOOKUP($J68,'ESTRUCTURA P&B - LP'!$A$1:$F$40,5,0) -> E-COMMERCE | L68: =IFERROR(VLOOKUP($J68,'[2]POTENCIAL X ZONA'!$B$4:$G$21,6,0),0) -> 0 | M68: =IFERROR(VLOOKUP($A68,'Convenio Clientes'!$D:$F,3,0),"SN CNV") -> 50 | N68: 10 | O68: 0 | P68: EVENTUAL | Q68: OFICINA | R68: =VLOOKUP($N68,Tabla2[#All],3,0) -> ATENCION AL CLIENTE | S68: AV PRINCIPAL FRANCISCO DE MIRANDA EDIF | T68: CENTRO RESIDENCIAL LA CALIFORNIA PISO PB | U68: CARACAS
A69: J503504170 | B69: CN MILENIUM, C.A | C69: 50 | D69: 50 | E69: =VLOOKUP($D69,'ESTRUCTURA P&B - LP'!$A$1:$F$31,5,0) -> BETSY CASTRO | F69: =VLOOKUP($D69,'ESTRUCTURA P&B - LP'!$A$1:$F$31,6,0) -> MILAGROS FERNANDEZ | G69: MIRANDA | H69: =VLOOKUP(Tabla3[[#This Row],[NUEVA RUTA]],Tabla1[#All],2,0) -> CAPITAL | I69: =VLOOKUP($A69,Clientes!$A$1:$C$1999,3,0) -> COM NUEVO MILEN | J69: 50 | K69: =VLOOKUP($J69,'ESTRUCTURA P&B - LP'!$A$1:$F$40,5,0) -> BETSY CASTRO | L69: =IFERROR(VLOOKUP($J69,'[2]POTENCIAL X ZONA'!$B$4:$G$21,6,0),0) -> B | M69: =IFERROR(VLOOKUP($A69,'Convenio Clientes'!$D:$F,3,0),"SN CNV") -> 20 | N69: 07 | O69: 21 | P69: REGULAR | Q69: SI | R69: =VLOOKUP($N69,Tabla2[#All],3,0) -> DISTRIBUIDOR | U69: CARACAS
A70: J303665012 | B70: COLEGIO INTEGRAL EL AVILA | C70: 95 | D70: 95 | E70: =VLOOKUP($D70,'ESTRUCTURA P&B - LP'!$A$1:$F$31,5,0) -> EVENTUALES | F70: =VLOOKUP($D70,'ESTRUCTURA P&B - LP'!$A$1:$F$31,6,0) -> ROSLI APONTE | G70: MIRANDA | H70: =VLOOKUP(Tabla3[[#This Row],[NUEVA RUTA]],Tabla1[#All],2,0) -> OFICINA | I70: =VLOOKUP($A70,Clientes!$A$1:$C$1999,3,0) -> COLEG EL AVILA | J70: 95 | K70: =VLOOKUP($J70,'ESTRUCTURA P&B - LP'!$A$1:$F$40,5,0) -> EVENTUALES | L70: =IFERROR(VLOOKUP($J70,'[2]POTENCIAL X ZONA'!$B$4:$G$21,6,0),0) -> 0 | M70: =IFERROR(VLOOKUP($A70,'Convenio Clientes'!$D:$F,3,0),"SN CNV") -> 21 | N70: 09 | O70: 0 | P70: EVENTUAL | Q70: OFICINA | R70: =VLOOKUP($N70,Tabla2[#All],3,0) -> INSTITUCIONAL | S70: AV FUERZAS ARMADAS, CALLE NORTE 7 | T70: EDIF RES FLAMBOYAN PISO LOCAL PB | U70: CARACAS
A71: J501696497 | B71: COLLINS VIVAS DISTRIBUCIONES COLVID, C.A | C71: 60 | D71: 60 | E71: =VLOOKUP($D71,'ESTRUCTURA P&B - LP'!$A$1:$F$31,5,0) -> JOSEPH PADILLA | F71: =VLOOKUP($D71,'ESTRUCTURA P&B - LP'!$A$1:$F$31,6,0) -> ANDREINA RANGEL | G71: TACHIRA | H71: =VLOOKUP(Tabla3[[#This Row],[NUEVA RUTA]],Tabla1[#All],2,0) -> OCCIDENTE | I71: =VLOOKUP($A71,Clientes!$A$1:$C$1999,3,0) -> COLLINS VIVAS | J71: 60 | K71: =VLOOKUP($J71,'ESTRUCTURA P&B - LP'!$A$1:$F$40,5,0) -> JOSEPH PADILLA | L71: =IFERROR(VLOOKUP($J71,'[2]POTENCIAL X ZONA'!$B$4:$G$21,6,0),0) -> S | M71: =IFERROR(VLOOKUP($A71,'Convenio Clientes'!$D:$F,3,0),"SN CNV") -> 26 | N71: 07 | O71: 15 | P71: REGULAR | Q71: SI | R71: =VLOOKUP($N71,Tabla2[#All],3,0) -> DISTRIBUIDOR | S71: AV LUIS DEL VALLE GARCÍA EDF OCP | T71: N 34 PISO 2 LOCAL P2-15 | U71: SAN CRISTOBAL
A72: J298991569 | B72: COMERCIAL BIG BANG, C.A | C72: 98 | D72: 98 | E72: =VLOOKUP($D72,'ESTRUCTURA P&B - LP'!$A$1:$F$31,5,0) -> INACTIVO | F72: =VLOOKUP($D72,'ESTRUCTURA P&B - LP'!$A$1:$F$31,6,0) -> INACTIVO | G72: DISTRITO CAPITAL | H72: =VLOOKUP(Tabla3[[#This Row],[NUEVA RUTA]],Tabla1[#All],2,0) -> INACTIVO | I72: =VLOOKUP($A72,Clientes!$A$1:$C$1999,3,0) -> COM BIG BANG | J72: 57 | K72: =VLOOKUP($J72,'ESTRUCTURA P&B - LP'!$A$1:$F$40,5,0) -> CARLOS ZURITA | L72: =IFERROR(VLOOKUP($J72,'[2]POTENCIAL X ZONA'!$B$4:$G$21,6,0),0) -> 0 | M72: =IFERROR(VLOOKUP($A72,'Convenio Clientes'!$D:$F,3,0),"SN CNV") -> 20 | N72: 05 | O72: 15 | P72: INACTIVO | Q72: NO | R72: =VLOOKUP($N72,Tabla2[#All],3,0) -> PERFUMERIAS INDEPENDIENTES | S72: AV BOLIVAR OESTE LOCAL NRO 74 | T72: SECTOR CENTRO MARACAY | U72: CARACAS
A73: J412900390 | B73: COMERCIAL BUEN FUTURO 2018, C.A. | C73: 98 | D73: 98 | E73: =VLOOKUP($D73,'ESTRUCTURA P&B - LP'!$A$1:$F$31,5,0) -> INACTIVO | F73: =VLOOKUP($D73,'ESTRUCTURA P&B - LP'!$A$1:$F$31,6,0) -> INACTIVO | G73: ARAGUA | H73: =VLOOKUP(Tabla3[[#This Row],[NUEVA RUTA]],Tabla1[#All],2,0) -> INACTIVO | I73: =VLOOKUP($A73,Clientes!$A$1:$C$1999,3,0) -> COM BUEN FUTURO | J73: 12 | K73: =VLOOKUP($J73,'ESTRUCTURA P&B - LP'!$A$1:$F$40,5,0) -> JUAN LEÓN 12 | L73: =IFERROR(VLOOKUP($J73,'[2]POTENCIAL X ZONA'!$B$4:$G$21,6,0),0) -> P | M73: =IFERROR(VLOOKUP($A73,'Convenio Clientes'!$D:$F,3,0),"SN CNV") -> 01 | N73: 05 | O73: 15 | P73: INACTIVO | Q73: NO | R73: =VLOOKUP($N73,Tabla2[#All],3,0) -> PERFUMERIAS INDEPENDIENTES | S73: AV BARALT EDIF CARONI PISO PB LOCAL | T73: 1502 URB EL SILENCIO | U73: MARACAY
A74: J313189260 | B74: COMERCIAL CENTRO-CENTRO, C.A | C74: 50 | D74: 50 | E74: =VLOOKUP($D74,'ESTRUCTURA P&B - LP'!$A$1:$F$31,5,0) -> BETSY CASTRO | F74: =VLOOKUP($D74,'ESTRUCTURA P&B - LP'!$A$1:$F$31,6,0) -> MILAGROS FERNANDEZ | G74: DISTRITO CAPITAL | H74: =VLOOKUP(Tabla3[[#This Row],[NUEVA RUTA]],Tabla1[#All],2,0) -> CAPITAL | I74: =VLOOKUP($A74,Clientes!$A$1:$C$1999,3,0) -> C CENTRO-CENTRO | J74: 50 | K74: =VLOOKUP($J74,'ESTRUCTURA P&B - LP'!$A$1:$F$40,5,0) -> BETSY CASTRO | L74: =IFERROR(VLOOKUP($J74,'[2]POTENCIAL X ZONA'!$B$4:$G$21,6,0),0) -> B | M74: =IFERROR(VLOOKUP($A74,'Convenio Clientes'!$D:$F,3,0),"SN CNV") -> 22 | N74: 06 | O74: 7 | P74: INACTIVO | Q74: NO | R74: =VLOOKUP($N74,Tabla2[#All],3,0) -> SUPERMERCADOS INDEPENDIENTES | S74: CALLE 26 ENTRE CARRERAS 21 Y 22 | T74: EDF C.C. CHALIKI | U74: CARACAS
A75: J085323783 | B75: COMERCIAL CHALIKI, C.A. | C75: 23 | D75: 23 | E75: =VLOOKUP($D75,'ESTRUCTURA P&B - LP'!$A$1:$F$31,5,0) -> MARTHA VILORIA | F75: =VLOOKUP($D75,'ESTRUCTURA P&B - LP'!$A$1:$F$31,6,0) -> DUBRASKA PÉREZ | G75: LARA | H75: =VLOOKUP(Tabla3[[#This Row],[NUEVA RUTA]],Tabla1[#All],2,0) -> CENTRO-OCCIDENTE | I75: =VLOOKUP($A75,Clientes!$A$1:$C$1999,3,0) -> 54 CHALIKI | J75: 23 | K75: =VLOOKUP($J75,'ESTRUCTURA P&B - LP'!$A$1:$F$40,5,0) -> MARTHA VILORIA | L75: =IFERROR(VLOOKUP($J75,'[2]POTENCIAL X ZONA'!$B$4:$G$21,6,0),0) -> S | M75: =IFERROR(VLOOKUP($A75,'Convenio Clientes'!$D:$F,3,0),"SN CNV") -> 01 | N75: 15 | O75: 7 | P75: INACTIVO | Q75: NO | R75: =VLOOKUP($N75,Tabla2[#All],3,0) -> MAYORISTAS | S75: AV. SAN MARTIN ENTRE AV SANTANDER Y CALLE 1 | T75: EDIF TROPICANA PISO P.B LOCAL 2 | U75: BARQUISIMETO
A76: J304015623 | B76: COMERCIAL ERIFAT EA,C.A | C76: 98 | D76: 98 | E76: =VLOOKUP($D76,'ESTRUCTURA P&B - LP'!$A$1:$F$31,5,0) -> INACTIVO | F76: =VLOOKUP($D76,'ESTRUCTURA P&B - LP'!$A$1:$F$31,6,0) -> INACTIVO | G76: DISTRITO CAPITAL | H76: =VLOOKUP(Tabla3[[#This Row],[NUEVA RUTA]],Tabla1[#All],2,0) -> INACTIVO | I76: =VLOOKUP($A76,Clientes!$A$1:$C$1999,3,0) -> COMER ERIFAT EA | J76: 0 | K76: =VLOOKUP($J76,'ESTRUCTURA P&B - LP'!$A$1:$F$40,5,0) -> INACTIVO | L76: =IFERROR(VLOOKUP($J76,'[2]POTENCIAL X ZONA'!$B$4:$G$21,6,0),0) -> 0 | M76: =IFERROR(VLOOKUP($A76,'Convenio Clientes'!$D:$F,3,0),"SN CNV") -> 01 | N76: 07 | O76: 0 | P76: INACTIVO | Q76: NO | R76: =VLOOKUP($N76,Tabla2[#All],3,0) -> DISTRIBUIDOR | S76: CALLE BELEN LOCAL NRO 08 SECTOR | T76: CENTRO DE SAN MATEO | U76: CARACAS
A77: J501753873 | B77: COMERCIAL GRAN FAMILIAS, C.A. | C77: 12 | D77: 12 | E77: =VLOOKUP($D77,'ESTRUCTURA P&B - LP'!$A$1:$F$31,5,0) -> JUAN LEÓN 12 | F77: =VLOOKUP($D77,'ESTRUCTURA P&B - LP'!$A$1:$F$31,6,0) -> DUBRASKA PÉREZ | G77: ARAGUA | H77: =VLOOKUP(Tabla3[[#This Row],[NUEVA RUTA]],Tabla1[#All],2,0) -> CENTRO-OCCIDENTE | I77: =VLOOKUP($A77,Clientes!$A$1:$C$1999,3,0) -> COME GRAN FAMIL | J77: =+D77 -> 12 | K77: =VLOOKUP($J77,'ESTRUCTURA P&B - LP'!$A$1:$F$40,5,0) -> JUAN LEÓN 12 | L77: =IFERROR(VLOOKUP($J77,'[2]POTENCIAL X ZONA'!$B$4:$G$21,6,0),0) -> P | M77: =IFERROR(VLOOKUP($A77,'Convenio Clientes'!$D:$F,3,0),"SN CNV") -> 21 | N77: 06 | O77: 7 | P77: INACTIVO | Q77: NO | R77: =VLOOKUP($N77,Tabla2[#All],3,0) -> SUPERMERCADOS INDEPENDIENTES | S77: AV 20 ENTRE 28 Y 29 N° 28-87 | T77: 0 | U77: SAN MATEO
A78: J306927093 | B78: COMERCIAL HONG KONG, C.A. | C78: 98 | D78: 98 | E78: =VLOOKUP($D78,'ESTRUCTURA P&B - LP'!$A$1:$F$31,5,0) -> INACTIVO | F78: =VLOOKUP($D78,'ESTRUCTURA P&B - LP'!$A$1:$F$31,6,0) -> INACTIVO | G78: LARA | H78: =VLOOKUP(Tabla3[[#This Row],[NUEVA RUTA]],Tabla1[#All],2,0) -> INACTIVO | I78: =VLOOKUP($A78,Clientes!$A$1:$C$1999,3,0) -> COM HONG KONG | J78: 0 | K78: =VLOOKUP($J78,'ESTRUCTURA P&B - LP'!$A$1:$F$40,5,0) -> INACTIVO | L78: =IFERROR(VLOOKUP($J78,'[2]POTENCIAL X ZONA'!$B$4:$G$21,6,0),0) -> 0 | M78: =IFERROR(VLOOKUP($A78,'Convenio Clientes'!$D:$F,3,0),"SN CNV") -> 01 | N78: 05 | O78: 0 | P78: INACTIVO | Q78: NO | R78: =VLOOKUP($N78,Tabla2[#All],3,0) -> PERFUMERIAS INDEPENDIENTES | S78: CARRERA 10 BIS GALPON LA GRAN PARADA | T78: LA CONCORDIA | U78: BARQUISIMETO
A79: J302754550 | B79: COMERCIAL LA GRAN PARADA, C.A. | C79: 98 | D79: 98 | E79: =VLOOKUP($D79,'ESTRUCTURA P&B - LP'!$A$1:$F$31,5,0) -> INACTIVO | F79: =VLOOKUP($D79,'ESTRUCTURA P&B - LP'!$A$1:$F$31,6,0) -> INACTIVO | G79: TACHIRA | H79: =VLOOKUP(Tabla3[[#This Row],[NUEVA RUTA]],Tabla1[#All],2,0) -> INACTIVO | I79: =VLOOKUP($A79,Clientes!$A$1:$C$1999,3,0) -> 67 GRAN PARADA | J79: 60 | K79: =VLOOKUP($J79,'ESTRUCTURA P&B - LP'!$A$1:$F$40,5,0) -> JOSEPH PADILLA | L79: =IFERROR(VLOOKUP($J79,'[2]POTENCIAL X ZONA'!$B$4:$G$21,6,0),0) -> S | M79: =IFERROR(VLOOKUP($A79,'Convenio Clientes'!$D:$F,3,0),"SN CNV") -> 21 | N79: 15 | O79: 15 | P79: INACTIVO | Q79: NO | R79: =VLOOKUP($N79,Tabla2[#All],3,0) -> MAYORISTAS | S79: AV FUERZAS ARMADAS CON ESQ. CRUCESITA | T79: EDIF DOLAMIL PISO B LOCAL 1 Y 2 | U79: SAN CRISTOBAL
A80: J306456597 | B80: COMERCIAL LUCKY STAR, C.A | C80: 50 | D80: 99 | E80: =VLOOKUP($D80,'ESTRUCTURA P&B - LP'!$A$1:$F$31,5,0) -> E-COMMERCE | F80: =VLOOKUP($D80,'ESTRUCTURA P&B - LP'!$A$1:$F$31,6,0) -> E-COMMERCE | G80: DISTRITO CAPITAL | H80: =VLOOKUP(Tabla3[[#This Row],[NUEVA RUTA]],Tabla1[#All],2,0) -> E-COMMERCE | I80: =VLOOKUP($A80,Clientes!$A$1:$C$1999,3,0) -> COM LUCKY STAR | J80: 99 | K80: =VLOOKUP($J80,'ESTRUCTURA P&B - LP'!$A$1:$F$40,5,0) -> E-COMMERCE | L80: =IFERROR(VLOOKUP($J80,'[2]POTENCIAL X ZONA'!$B$4:$G$21,6,0),0) -> 0 | M80: =IFERROR(VLOOKUP($A80,'Convenio Clientes'!$D:$F,3,0),"SN CNV") -> 50 | N80: 05 | O80: 0 | P80: EVENTUAL | Q80: SI | R80: =VLOOKUP($N80,Tabla2[#All],3,0) -> PERFUMERIAS INDEPENDIENTES | S80: CTRA NACIONAL VALENCIA-GUACARA | T80: LOCAL NRO C194- 3526 URB LAS | U80: CARACAS
A81: J413002973 | B81: COMERCIAL LV, C.A. | C81: 52 | D81: 52 | E81: =VLOOKUP($D81,'ESTRUCTURA P&B - LP'!$A$1:$F$31,5,0) -> DIANA DELGADO 52 | F81: =VLOOKUP($D81,'ESTRUCTURA P&B - LP'!$A$1:$F$31,6,0) -> DIANA DELGADO | G81: CARABOBO | H81: =VLOOKUP(Tabla3[[#This Row],[NUEVA RUTA]],Tabla1[#All],2,0) -> ORIENTE SUR | I81: =VLOOKUP($A81,Clientes!$A$1:$C$1999,3,0) -> COMERCIAL LV, C | J81: =+D81 -> 52 | K81: =VLOOKUP($J81,'ESTRUCTURA P&B - LP'!$A$1:$F$40,5,0) -> DIANA DELGADO 52 | L81: =IFERROR(VLOOKUP($J81,'[2]POTENCIAL X ZONA'!$B$4:$G$21,6,0),0) -> S | M81: =IFERROR(VLOOKUP($A81,'Convenio Clientes'!$D:$F,3,0),"SN CNV") -> 20 | N81: 07 | O81: 15 | P81: INACTIVO | Q81: NO | R81: =VLOOKUP($N81,Tabla2[#All],3,0) -> DISTRIBUIDOR | S81: CLLE 148 VIA PALITO BLANCO CC MERCOSUR | T81: NIVEL PB LOCAL A1-14 ZONA INDUSTRIAL | U81: LOS GUAYOS
A82: J309086456 | B82: COMERCIAL MAXI, C.A. | C82: 98 | D82: 98 | E82: =VLOOKUP($D82,'ESTRUCTURA P&B - LP'!$A$1:$F$31,5,0) -> INACTIVO | F82: =VLOOKUP($D82,'ESTRUCTURA P&B - LP'!$A$1:$F$31,6,0) -> INACTIVO | G82: ZULIA | H82: =VLOOKUP(Tabla3[[#This Row],[NUEVA RUTA]],Tabla1[#All],2,0) -> INACTIVO | I82: =VLOOKUP($A82,Clientes!$A$1:$C$1999,3,0) -> COMERCIAL MAXI | J82: 0 | K82: =VLOOKUP($J82,'ESTRUCTURA P&B - LP'!$A$1:$F$40,5,0) -> INACTIVO | L82: =IFERROR(VLOOKUP($J82,'[2]POTENCIAL X ZONA'!$B$4:$G$21,6,0),0) -> 0 | M82: =IFERROR(VLOOKUP($A82,'Convenio Clientes'!$D:$F,3,0),"SN CNV") -> 01 | N82: 05 | O82: 0 | P82: INACTIVO | Q82: NO | R82: =VLOOKUP($N82,Tabla2[#All],3,0) -> PERFUMERIAS INDEPENDIENTES | S82: AV CEMENTERIO LOCAL NRO S/N SECTOR | T82: POZO HONDO ENTRADA EL PINAL | U82: SAN FRANCISCO
A83: J090217304 | B83: COMERCIAL MONTALBÁN, C.A. | C83: 61 | D83: 61 | E83: =VLOOKUP($D83,'ESTRUCTURA P&B - LP'!$A$1:$F$31,5,0) -> JOSEPH PADILLA 61 | F83: =VLOOKUP($D83,'ESTRUCTURA P&B - LP'!$A$1:$F$31,6,0) -> ANDREINA RANGEL | G83: MERIDA | H83: =VLOOKUP(Tabla3[[#This Row],[NUEVA RUTA]],Tabla1[#All],2,0) -> OCCIDENTE | I83: =VLOOKUP($A83,Clientes!$A$1:$C$1999,3,0) -> COM MONTALBAN | J83: 61 | K83: =VLOOKUP($J83,'ESTRUCTURA P&B - LP'!$A$1:$F$40,5,0) -> JOSEPH PADILLA 61 | L83: =IFERROR(VLOOKUP($J83,'[2]POTENCIAL X ZONA'!$B$4:$G$21,6,0),0) -> P | M83: =IFERROR(VLOOKUP($A83,'Convenio Clientes'!$D:$F,3,0),"SN CNV") -> 21 | N83: 05 | O83: 15 | P83: INACTIVO | Q83: NO | R83: =VLOOKUP($N83,Tabla2[#All],3,0) -> PERFUMERIAS INDEPENDIENTES | S83: AV VARGAS ENTRE 22 Y 21 LOCAL 20-58 | T83: SECTOR CENTRO BARQUISIMETO | U83: MERIDA
A84: J305106266 | B84: COMERCIAL ORIENTE DEL CENTRO, C.A. | C84: 98 | D84: 98 | E84: =VLOOKUP($D84,'ESTRUCTURA P&B - LP'!$A$1:$F$31,5,0) -> INACTIVO | F84: =VLOOKUP($D84,'ESTRUCTURA P&B - LP'!$A$1:$F$31,6,0) -> INACTIVO | G84: LARA | H84: =VLOOKUP(Tabla3[[#This Row],[NUEVA RUTA]],Tabla1[#All],2,0) -> INACTIVO | I84: =VLOOKUP($A84,Clientes!$A$1:$C$1999,3,0) -> COM ORIENTE CEN | J84: 0 | K84: =VLOOKUP($J84,'ESTRUCTURA P&B - LP'!$A$1:$F$40,5,0) -> INACTIVO | L84: =IFERROR(VLOOKUP($J84,'[2]POTENCIAL X ZONA'!$B$4:$G$21,6,0),0) -> 0 | M84: =IFERROR(VLOOKUP($A84,'Convenio Clientes'!$D:$F,3,0),"SN CNV") -> 01 | N84: 07 | O84: 0 | P84: INACTIVO | Q84: NO | R84: =VLOOKUP($N84,Tabla2[#All],3,0) -> DISTRIBUIDOR | S84: CR 21 ENTRE CALLES 30 Y 31 | T84: CASA NRO 30-71 | U84: BARQUISIMETO
A85: J410126175 | B85: COMERCIAL PRISMA 21,CA (COMERCIAL PRISMA 21,CA) | C85: 23 | D85: 23 | E85: =VLOOKUP($D85,'ESTRUCTURA P&B - LP'!$A$1:$F$31,5,0) -> MARTHA VILORIA | F85: =VLOOKUP($D85,'ESTRUCTURA P&B - LP'!$A$1:$F$31,6,0) -> DUBRASKA PÉREZ | G85: LARA | H85: =VLOOKUP(Tabla3[[#This Row],[NUEVA RUTA]],Tabla1[#All],2,0) -> CENTRO-OCCIDENTE | I85: =VLOOKUP($A85,Clientes!$A$1:$C$1999,3,0) -> COM PRISMA 21 | J85: 23 | K85: =VLOOKUP($J85,'ESTRUCTURA P&B - LP'!$A$1:$F$40,5,0) -> MARTHA VILORIA | L85: =IFERROR(VLOOKUP($J85,'[2]POTENCIAL X ZONA'!$B$4:$G$21,6,0),0) -> S | M85: =IFERROR(VLOOKUP($A85,'Convenio Clientes'!$D:$F,3,0),"SN CNV") -> 21 | N85: 07 | O85: 15 | P85: INACTIVO | Q85: NO | R85: =VLOOKUP($N85,Tabla2[#All],3,0) -> DISTRIBUIDOR | S85: AV.64-A,N° 137-06, ZONA INDUSTRIAL | T85: DETRÁS DE COLGATE | U85: BARQUISIMETO
A86: J070304162 | B86: COMERCIAL REYES, C.A. | C86: 21 | D86: 21 | E86: =VLOOKUP($D86,'ESTRUCTURA P&B - LP'!$A$1:$F$31,5,0) -> ANDREINA RANGEL 21 | F86: =VLOOKUP($D86,'ESTRUCTURA P&B - LP'!$A$1:$F$31,6,0) -> ANDREINA RANGEL | G86: ZULIA | H86: =VLOOKUP(Tabla3[[#This Row],[NUEVA RUTA]],Tabla1[#All],2,0) -> OCCIDENTE | I86: =VLOOKUP($A86,Clientes!$A$1:$C$1999,3,0) -> 09 C. REYES | J86: 0 | K86: =VLOOKUP($J86,'ESTRUCTURA P&B - LP'!$A$1:$F$40,5,0) -> INACTIVO | L86: =IFERROR(VLOOKUP($J86,'[2]POTENCIAL X ZONA'!$B$4:$G$21,6,0),0) -> 0 | M86: =IFERROR(VLOOKUP($A86,'Convenio Clientes'!$D:$F,3,0),"SN CNV") -> 01 | N86: 03 | O86: 0 | P86: INACTIVO | Q86: NO | R86: =VLOOKUP($N86,Tabla2[#All],3,0) -> CADENAS - SUPERMERCADOS | S86: AV FUERZAS ARMADAS ESQUINA DE CRUSESITA | T86: A SAN MIGUEL LOCAL KISMET NRO A B SOTANO | U86: MARACAIBO
A87: J317512448 | B87: COMERCIAL TODO HOGAR K.R 28, C.A. | C87: 50 | D87: 50 | E87: =VLOOKUP($D87,'ESTRUCTURA P&B - LP'!$A$1:$F$31,5,0) -> BETSY CASTRO | F87: =VLOOKUP($D87,'ESTRUCTURA P&B - LP'!$A$1:$F$31,6,0) -> MILAGROS FERNANDEZ | G87: DISTRITO CAPITAL | H87: =VLOOKUP(Tabla3[[#This Row],[NUEVA RUTA]],Tabla1[#All],2,0) -> CAPITAL | I87: =VLOOKUP($A87,Clientes!$A$1:$C$1999,3,0) -> TODO HOGAR KR28 | J87: 50 | K87: =VLOOKUP($J87,'ESTRUCTURA P&B - LP'!$A$1:$F$40,5,0) -> BETSY CASTRO | L87: =IFERROR(VLOOKUP($J87,'[2]POTENCIAL X ZONA'!$B$4:$G$21,6,0),0) -> B | M87: =IFERROR(VLOOKUP($A87,'Convenio Clientes'!$D:$F,3,0),"SN CNV") -> 20 | N87: 07 | O87: 21 | P87: REGULAR | Q87: SI | R87: =VLOOKUP($N87,Tabla2[#All],3,0) -> DISTRIBUIDOR | S87: CR 21 ESQ CALLE 28 EDIF ARSENICO P-PB | T87: LOCAL S/N SEC. CENTRO | U87: CARACAS
A88: J317194985 | B88: COMERCIAL VICTORIA HL C.A | C88: 23 | D88: 23 | E88: =VLOOKUP($D88,'ESTRUCTURA P&B - LP'!$A$1:$F$31,5,0) -> MARTHA VILORIA | F88: =VLOOKUP($D88,'ESTRUCTURA P&B - LP'!$A$1:$F$31,6,0) -> DUBRASKA PÉREZ | G88: LARA | H88: =VLOOKUP(Tabla3[[#This Row],[NUEVA RUTA]],Tabla1[#All],2,0) -> CENTRO-OCCIDENTE | I88: =VLOOKUP($A88,Clientes!$A$1:$C$1999,3,0) -> COM VICTORIA HL | J88: 23 | K88: =VLOOKUP($J88,'ESTRUCTURA P&B - LP'!$A$1:$F$40,5,0) -> MARTHA VILORIA | L88: =IFERROR(VLOOKUP($J88,'[2]POTENCIAL X ZONA'!$B$4:$G$21,6,0),0) -> S | M88: =IFERROR(VLOOKUP($A88,'Convenio Clientes'!$D:$F,3,0),"SN CNV") -> 20 | N88: 05 | O88: 15 | P88: REGULAR | Q88: SI | R88: =VLOOKUP($N88,Tabla2[#All],3,0) -> PERFUMERIAS INDEPENDIENTES | S88: AV FUERZAS ARMADAS ESQ. SAN MIGUEL | T88: EDIF GRANOR PISO PB LOCAL A Y B | U88: BARQUISIMETO
A89: J298396440 | B89: COMERCIAL WYNN, C.A. | C89: 58 | D89: 50 | E89: =VLOOKUP($D89,'ESTRUCTURA P&B - LP'!$A$1:$F$31,5,0) -> BETSY CASTRO | F89: =VLOOKUP($D89,'ESTRUCTURA P&B - LP'!$A$1:$F$31,6,0) -> MILAGROS FERNANDEZ | G89: DISTRITO CAPITAL | H89: =VLOOKUP(Tabla3[[#This Row],[NUEVA RUTA]],Tabla1[#All],2,0) -> CAPITAL | I89: =VLOOKUP($A89,Clientes!$A$1:$C$1999,3,0) -> COMERCIAL WYNN | J89: 57 | K89: =VLOOKUP($J89,'ESTRUCTURA P&B - LP'!$A$1:$F$40,5,0) -> CARLOS ZURITA | L89: =IFERROR(VLOOKUP($J89,'[2]POTENCIAL X ZONA'!$B$4:$G$21,6,0),0) -> 0 | M89: =IFERROR(VLOOKUP($A89,'Convenio Clientes'!$D:$F,3,0),"SN CNV") -> 21 | N89: 05 | O89: 15 | P89: INACTIVO | Q89: NO | R89: =VLOOKUP($N89,Tabla2[#All],3,0) -> PERFUMERIAS INDEPENDIENTES | S89: CALLE D ENTRE AV 2 Y AV 1 LOCAL S/N | T89: SECTOR ZONA INDUSTRIAL SANTA ANA DE | U89: CARACAS
A90: J501628785 | B90: COMERCIALIZADORA 3B GROUP, C.A | C90: 50 | D90: 50 | E90: =VLOOKUP($D90,'ESTRUCTURA P&B - LP'!$A$1:$F$31,5,0) -> BETSY CASTRO | F90: =VLOOKUP($D90,'ESTRUCTURA P&B - LP'!$A$1:$F$31,6,0) -> MILAGROS FERNANDEZ | G90: DISTRITO CAPITAL | H90: =VLOOKUP(Tabla3[[#This Row],[NUEVA RUTA]],Tabla1[#All],2,0) -> CAPITAL | I90: =VLOOKUP($A90,Clientes!$A$1:$C$1999,3,0) -> TODO HOGAR KR28 | J90: 50 | K90: =VLOOKUP($J90,'ESTRUCTURA P&B - LP'!$A$1:$F$40,5,0) -> BETSY CASTRO | L90: =IFERROR(VLOOKUP($J90,'[2]POTENCIAL X ZONA'!$B$4:$G$21,6,0),0) -> B | M90: =IFERROR(VLOOKUP($A90,'Convenio Clientes'!$D:$F,3,0),"SN CNV") -> 20 | N90: 07 | O90: 15 | P90: INACTIVO | Q90: NO | R90: =VLOOKUP($N90,Tabla2[#All],3,0) -> DISTRIBUIDOR | U90: CARACAS | V90: 21/11/25 va a facturar por TOTAL SERVICE
A91: J413109956 | B91: COMERCIALIZADORA 91-84, C.A. | C91: 62 | D91: 62 | E91: =VLOOKUP($D91,'ESTRUCTURA P&B - LP'!$A$1:$F$31,5,0) -> ANDREINA RANGEL 62 | F91: =VLOOKUP($D91,'ESTRUCTURA P&B - LP'!$A$1:$F$31,6,0) -> ANDREINA RANGEL | G91: ZULIA | H91: =VLOOKUP(Tabla3[[#This Row],[NUEVA RUTA]],Tabla1[#All],2,0) -> OCCIDENTE | I91: =VLOOKUP($A91,Clientes!$A$1:$C$1999,3,0) -> COMERC 91-84 | J91: 62 | K91: =VLOOKUP($J91,'ESTRUCTURA P&B - LP'!$A$1:$F$40,5,0) -> ANDREINA RANGEL 62 | L91: =IFERROR(VLOOKUP($J91,'[2]POTENCIAL X ZONA'!$B$4:$G$21,6,0),0) -> S | M91: =IFERROR(VLOOKUP($A91,'Convenio Clientes'!$D:$F,3,0),"SN CNV") -> 20 | N91: 07 | O91: 15 | P91: REGULAR | Q91: SI | R91: =VLOOKUP($N91,Tabla2[#All],3,0) -> DISTRIBUIDOR | U91: MARACAIBO
A92: J297600760 | B92: COMERCIALIZADORA AMIR, C.A. | C92: 95 | D92: 98 | E92: =VLOOKUP($D92,'ESTRUCTURA P&B - LP'!$A$1:$F$31,5,0) -> INACTIVO | F92: =VLOOKUP($D92,'ESTRUCTURA P&B - LP'!$A$1:$F$31,6,0) -> INACTIVO | G92: FALCON | H92: =VLOOKUP(Tabla3[[#This Row],[NUEVA RUTA]],Tabla1[#All],2,0) -> INACTIVO | I92: =VLOOKUP($A92,Clientes!$A$1:$C$1999,3,0) -> COMERC AMIR | J92: 0 | K92: =VLOOKUP($J92,'ESTRUCTURA P&B - LP'!$A$1:$F$40,5,0) -> INACTIVO | L92: =IFERROR(VLOOKUP($J92,'[2]POTENCIAL X ZONA'!$B$4:$G$21,6,0),0) -> 0 | M92: =IFERROR(VLOOKUP($A92,'Convenio Clientes'!$D:$F,3,0),"SN CNV") -> 01 | N92: 07 | O92: 0 | P92: INACTIVO | Q92: NO | R92: =VLOOKUP($N92,Tabla2[#All],3,0) -> DISTRIBUIDOR | S92: AV. INTERC. GUARENAS GUATIRE | T92: CC NUEVA CASARAPA NIVEL PB LOCAL D-1 | U92: CORO
A93: J505419056 | B93: COMERCIALIZADORA CATARIVE, C.A | C93: 23 | D93: 23 | E93: =VLOOKUP($D93,'ESTRUCTURA P&B - LP'!$A$1:$F$31,5,0) -> MARTHA VILORIA | F93: =VLOOKUP($D93,'ESTRUCTURA P&B - LP'!$A$1:$F$31,6,0) -> DUBRASKA PÉREZ | G93: LARA | H93: =VLOOKUP(Tabla3[[#This Row],[NUEVA RUTA]],Tabla1[#All],2,0) -> CENTRO-OCCIDENTE | I93: =VLOOKUP($A93,Clientes!$A$1:$C$1999,3,0) -> COM CATARIVE | J93: 23 | K93: =VLOOKUP($J93,'ESTRUCTURA P&B - LP'!$A$1:$F$40,5,0) -> MARTHA VILORIA | L93: =IFERROR(VLOOKUP($J93,'[2]POTENCIAL X ZONA'!$B$4:$G$21,6,0),0) -> S | M93: =IFERROR(VLOOKUP($A93,'Convenio Clientes'!$D:$F,3,0),"SN CNV") -> 20 | N93: 07 | O93: 15 | P93: INACTIVO | Q93: NO | R93: =VLOOKUP($N93,Tabla2[#All],3,0) -> DISTRIBUIDOR | U93: BARQUISIMETO | V93: CAMBIO DE RAZÓN SOCIAL A COMERCIALIZADORA CIANFAR, C.A.
A94: J310071381 | B94: COMERCIALIZADORA CENTRO GUARENAS, C.A. | C94: 56 | D94: 10 | E94: =VLOOKUP($D94,'ESTRUCTURA P&B - LP'!$A$1:$F$31,5,0) -> MILAGROS FERNANDEZ 10 | F94: =VLOOKUP($D94,'ESTRUCTURA P&B - LP'!$A$1:$F$31,6,0) -> MILAGROS FERNANDEZ | G94: MIRANDA | H94: =VLOOKUP(Tabla3[[#This Row],[NUEVA RUTA]],Tabla1[#All],2,0) -> CAPITAL | I94: =VLOOKUP($A94,Clientes!$A$1:$C$1999,3,0) -> C CTRO GUARENAS | J94: 10 | K94: =VLOOKUP($J94,'ESTRUCTURA P&B - LP'!$A$1:$F$40,5,0) -> MILAGROS FERNANDEZ 10 | L94: =IFERROR(VLOOKUP($J94,'[2]POTENCIAL X ZONA'!$B$4:$G$21,6,0),0) -> B | M94: =IFERROR(VLOOKUP($A94,'Convenio Clientes'!$D:$F,3,0),"SN CNV") -> 22 | N94: 06 | O94: 21 | P94: REGULAR | Q94: SI | R94: =VLOOKUP($N94,Tabla2[#All],3,0) -> SUPERMERCADOS INDEPENDIENTES | S94: CALLE PRINCIPAL EDIF GALPON B | T94: PISO PB LOCAL S/N | U94: GUARENAS
A95: J304303840 | B95: COMERCIALIZADORA DE ALIMENTOS ARUMA C.A. | C95: 50 | D95: 50 | E95: =VLOOKUP($D95,'ESTRUCTURA P&B - LP'!$A$1:$F$31,5,0) -> BETSY CASTRO | F95: =VLOOKUP($D95,'ESTRUCTURA P&B - LP'!$A$1:$F$31,6,0) -> MILAGROS FERNANDEZ | G95: MIRANDA | H95: =VLOOKUP(Tabla3[[#This Row],[NUEVA RUTA]],Tabla1[#All],2,0) -> CAPITAL | I95: =VLOOKUP($A95,Clientes!$A$1:$C$1999,3,0) -> COM ALIM ARUMA | J95: 50 | K95: =VLOOKUP($J95,'ESTRUCTURA P&B - LP'!$A$1:$F$40,5,0) -> BETSY CASTRO | L95: =IFERROR(VLOOKUP($J95,'[2]POTENCIAL X ZONA'!$B$4:$G$21,6,0),0) -> B | M95: =IFERROR(VLOOKUP($A95,'Convenio Clientes'!$D:$F,3,0),"SN CNV") -> 21 | N95: 07 | O95: 15 | P95: INACTIVO | Q95: NO | R95: =VLOOKUP($N95,Tabla2[#All],3,0) -> DISTRIBUIDOR | S95: AV 88, CENTRO CIUDAD COMERCIAL | T95: LOTE 25 LOCAL PARCELA 03 Y 08 | U95: GUATIRE
A96: J412864769 | B96: COMERCIALIZADORA GLOBAL C Y D, C.A | C96: 20 | D96: 20 | E96: =VLOOKUP($D96,'ESTRUCTURA P&B - LP'!$A$1:$F$31,5,0) -> JUAN LEÓN 20 | F96: =VLOOKUP($D96,'ESTRUCTURA P&B - LP'!$A$1:$F$31,6,0) -> DUBRASKA PÉREZ | G96: CARABOBO | H96: =VLOOKUP(Tabla3[[#This Row],[NUEVA RUTA]],Tabla1[#All],2,0) -> CENTRO-OCCIDENTE | I96: =VLOOKUP($A96,Clientes!$A$1:$C$1999,3,0) -> COM GLOBAL CYD | J96: 20 | K96: =VLOOKUP($J96,'ESTRUCTURA P&B - LP'!$A$1:$F$40,5,0) -> JUAN LEÓN 20 | L96: =IFERROR(VLOOKUP($J96,'[2]POTENCIAL X ZONA'!$B$4:$G$21,6,0),0) -> P | M96: =IFERROR(VLOOKUP($A96,'Convenio Clientes'!$D:$F,3,0),"SN CNV") -> 21 | N96: 05 | O96: 30 | P96: EVENTUAL | Q96: SI | R96: =VLOOKUP($N96,Tabla2[#All],3,0) -> PERFUMERIAS INDEPENDIENTES | S96: CALLE 10 LOCAL SANTINI NRO 6 | T96: SECTOR CENTRO | U96: VALENCIA
A97: J503546956 | B97: COMERCIALIZADORA GRAM MARK 23, C.A | C97: 20 | D97: 20 | E97: =VLOOKUP($D97,'ESTRUCTURA P&B - LP'!$A$1:$F$31,5,0) -> JUAN LEÓN 20 | F97: =VLOOKUP($D97,'ESTRUCTURA P&B - LP'!$A$1:$F$31,6,0) -> DUBRASKA PÉREZ | G97: CARABOBO | H97: CENTRO | I97: =VLOOKUP($A97,Clientes!$A$1:$C$1999,3,0) -> COM GRAM MARK | J97: 20 | K97: =VLOOKUP($J97,'ESTRUCTURA P&B - LP'!$A$1:$F$40,5,0) -> JUAN LEÓN 20 | L97: =IFERROR(VLOOKUP($J97,'[2]POTENCIAL X ZONA'!$B$4:$G$21,6,0),0) -> P | M97: =IFERROR(VLOOKUP($A97,'Convenio Clientes'!$D:$F,3,0),"SN CNV") -> 21 | N97: 15 | O97: 0 | P97: INACTIVO | Q97: NO | R97: =VLOOKUP($N97,Tabla2[#All],3,0) -> MAYORISTAS | U97: LOS GUAYOS
A98: J409587690 | B98: COMERCIALIZADORA GRAN PROSPERIDAD, C.A | C98: 62 | D98: 62 | E98: =VLOOKUP($D98,'ESTRUCTURA P&B - LP'!$A$1:$F$31,5,0) -> ANDREINA RANGEL 62 | F98: =VLOOKUP($D98,'ESTRUCTURA P&B - LP'!$A$1:$F$31,6,0) -> ANDREINA RANGEL | G98: TRUJILLO | H98: =VLOOKUP(Tabla3[[#This Row],[NUEVA RUTA]],Tabla1[#All],2,0) -> OCCIDENTE | I98: =VLOOKUP($A98,Clientes!$A$1:$C$1999,3,0) -> COM GRAN PROSPE | J98: 62 | K98: =VLOOKUP($J98,'ESTRUCTURA P&B - LP'!$A$1:$F$40,5,0) -> ANDREINA RANGEL 62 | L98: =IFERROR(VLOOKUP($J98,'[2]POTENCIAL X ZONA'!$B$4:$G$21,6,0),0) -> S | M98: =IFERROR(VLOOKUP($A98,'Convenio Clientes'!$D:$F,3,0),"SN CNV") -> 01 | N98: 07 | O98: 7 | P98: INACTIVO | Q98: NO | R98: =VLOOKUP($N98,Tabla2[#All],3,0) -> DISTRIBUIDOR | S98: AV 3Y SAN MARTIN ENTRE CALLES 82B Y 83 | T98: CC LOS PIRINEOS NIVEL 1 LOCAL 31 Y 32 | U98: VALERA
A99: J408086379 | B99: COMERCIALIZADORA HECHOS, C.A | C99: 62 | D99: 62 | E99: =VLOOKUP($D99,'ESTRUCTURA P&B - LP'!$A$1:$F$31,5,0) -> ANDREINA RANGEL 62 | F99: =VLOOKUP($D99,'ESTRUCTURA P&B - LP'!$A$1:$F$31,6,0) -> ANDREINA RANGEL | G99: ZULIA | H99: =VLOOKUP(Tabla3[[#This Row],[NUEVA RUTA]],Tabla1[#All],2,0) -> OCCIDENTE | I99: =VLOOKUP($A99,Clientes!$A$1:$C$1999,3,0) -> COMERC HECHOS | J99: 0 | K99: =VLOOKUP($J99,'ESTRUCTURA P&B - LP'!$A$1:$F$40,5,0) -> INACTIVO | L99: =IFERROR(VLOOKUP($J99,'[2]POTENCIAL X ZONA'!$B$4:$G$21,6,0),0) -> 0 | M99: =IFERROR(VLOOKUP($A99,'Convenio Clientes'!$D:$F,3,0),"SN CNV") -> 01 | N99: 07 | O99: 0 | P99: INACTIVO | Q99: NO | R99: =VLOOKUP($N99,Tabla2[#All],3,0) -> DISTRIBUIDOR | S99: CALLE 137 N° 114-40 CC V AVENIDA | T99: NIVEL PLANTA LOCAL H-1 | U99: MARACAIBO
A100: J307145757 | B100: COMERCIALIZADORA KROMI MARKET, C.A. | C100: 20 | D100: 20 | E100: =VLOOKUP($D100,'ESTRUCTURA P&B - LP'!$A$1:$F$31,5,0) -> JUAN LEÓN 20 | F100: =VLOOKUP($D100,'ESTRUCTURA P&B - LP'!$A$1:$F$31,6,0) -> DUBRASKA PÉREZ | G100: CARABOBO | H100: =VLOOKUP(Tabla3[[#This Row],[NUEVA RUTA]],Tabla1[#All],2,0) -> CENTRO-OCCIDENTE | I100: =VLOOKUP($A100,Clientes!$A$1:$C$1999,3,0) -> 81 KROM.MARKET | J100: 20 | K100: =VLOOKUP($J100,'ESTRUCTURA P&B - LP'!$A$1:$F$40,5,0) -> JUAN LEÓN 20 | L100: =IFERROR(VLOOKUP($J100,'[2]POTENCIAL X ZONA'!$B$4:$G$21,6,0),0) -> P | M100: =IFERROR(VLOOKUP($A100,'Convenio Clientes'!$D:$F,3,0),"SN CNV") -> 21 | N100: 03 | O100: 15 | P100: EVENTUAL | Q100: SI | R100: =VLOOKUP($N100,Tabla2[#All],3,0) -> CADENAS - SUPERMERCADOS | S100: AV LAS PALMAS ENTRE 4 TRANSVERSAL | T100: Y ROMULO GALLEGOS EDIF LAS PALMAS | U100: VALENCIA
...

Sheet Convenio Clientes
B2: ASESOR | C2: GERENTE | D2: RIF | E2: NOMBRE DE CLEINTE | F2: CONVENIO
B3: =IFERROR(VLOOKUP($D3,'CLIENTES NUEVA ID ZONA'!$A:$F,5,0),"INACTIVO") -> ANDREINA RANGEL 21 | C3: =IFERROR(VLOOKUP($D3,'CLIENTES NUEVA ID ZONA'!$A:$F,6,0),"INACTIVO") -> ANDREINA RANGEL | D3: J403154490 | E3: FARMACIA FARMAESTRELLA, C.A | F3: 01
B4: =IFERROR(VLOOKUP($D4,'CLIENTES NUEVA ID ZONA'!$A:$F,5,0),"INACTIVO") -> ANDREINA RANGEL 21 | C4: =IFERROR(VLOOKUP($D4,'CLIENTES NUEVA ID ZONA'!$A:$F,6,0),"INACTIVO") -> ANDREINA RANGEL | D4: J409767205 | E4: DROGUERIA FARMACEUTICA 24, C.A | F4: 26
B5: =IFERROR(VLOOKUP($D5,'CLIENTES NUEVA ID ZONA'!$A:$F,5,0),"INACTIVO") -> ANDREINA RANGEL 21 | C5: =IFERROR(VLOOKUP($D5,'CLIENTES NUEVA ID ZONA'!$A:$F,6,0),"INACTIVO") -> ANDREINA RANGEL | D5: J070012250 | E5: C.A. MAFARTA | F5: 21
B6: =IFERROR(VLOOKUP($D6,'CLIENTES NUEVA ID ZONA'!$A:$F,5,0),"INACTIVO") -> ANDREINA RANGEL 21 | C6: =IFERROR(VLOOKUP($D6,'CLIENTES NUEVA ID ZONA'!$A:$F,6,0),"INACTIVO") -> ANDREINA RANGEL | D6: J070095008 | E6: DROGUERIA COBECA OCCIDENTE,C.A. | F6: 21 | I6: Leyenda
B7: =IFERROR(VLOOKUP($D7,'CLIENTES NUEVA ID ZONA'!$A:$F,5,0),"INACTIVO") -> ANDREINA RANGEL 21 | C7: =IFERROR(VLOOKUP($D7,'CLIENTES NUEVA ID ZONA'!$A:$F,6,0),"INACTIVO") -> ANDREINA RANGEL | D7: J070114606 | E7: FARMACIAS GALERIAS COMPRE CON MENOS,C.A. | F7: 01 | I7: Convenio | J7: Descripción
B8: =IFERROR(VLOOKUP($D8,'CLIENTES NUEVA ID ZONA'!$A:$F,5,0),"INACTIVO") -> ANDREINA RANGEL 21 | C8: =IFERROR(VLOOKUP($D8,'CLIENTES NUEVA ID ZONA'!$A:$F,6,0),"INACTIVO") -> ANDREINA RANGEL | D8: J075361776 | E8: DROGUERIA COBECA CENTRO C.A. | F8: 21 | I8: 01 | J8: Clientes General - Bolívares | K8: =COUNTIF($F$2:$F$1080,I8) -> 527
B9: =IFERROR(VLOOKUP($D9,'CLIENTES NUEVA ID ZONA'!$A:$F,5,0),"INACTIVO") -> ANDREINA RANGEL 21 | C9: =IFERROR(VLOOKUP($D9,'CLIENTES NUEVA ID ZONA'!$A:$F,6,0),"INACTIVO") -> ANDREINA RANGEL | D9: J298430958 | E9: FARMACIA COLSALUD C.A. | F9: 01 | I9: 21 | J9: Clientes General - Dólares | K9: =COUNTIF($F$2:$F$1080,I9) -> 239
B10: =IFERROR(VLOOKUP($D10,'CLIENTES NUEVA ID ZONA'!$A:$F,5,0),"INACTIVO") -> ANDREINA RANGEL 21 | C10: =IFERROR(VLOOKUP($D10,'CLIENTES NUEVA ID ZONA'!$A:$F,6,0),"INACTIVO") -> ANDREINA RANGEL | D10: J299310131 | E10: FARMACIA LAS RUBIO C.A. | F10: 01 | I10: 03 | J10: Desc 2% - Bolívares | K10: =COUNTIF($F$2:$F$1080,I10) -> 0
B11: =IFERROR(VLOOKUP($D11,'CLIENTES NUEVA ID ZONA'!$A:$F,5,0),"INACTIVO") -> ANDREINA RANGEL 21 | C11: =IFERROR(VLOOKUP($D11,'CLIENTES NUEVA ID ZONA'!$A:$F,6,0),"INACTIVO") -> ANDREINA RANGEL | D11: J300666204 | E11: DROGUERIA COBECA ORIENTE C.A. | F11: 21 | I11: 23 | J11: Desc 2% - Dólares | K11: =COUNTIF($F$2:$F$1080,I11) -> 1
B12: =IFERROR(VLOOKUP($D12,'CLIENTES NUEVA ID ZONA'!$A:$F,5,0),"INACTIVO") -> ANDREINA RANGEL 21 | C12: =IFERROR(VLOOKUP($D12,'CLIENTES NUEVA ID ZONA'!$A:$F,6,0),"INACTIVO") -> ANDREINA RANGEL | D12: J308620483 | E12: FARMACIA COVIDES, C.A. | F12: 01 | I12: 04 | J12: Desc 3% - Bolívares | K12: =COUNTIF($F$2:$F$1080,I12) -> 1
B13: =IFERROR(VLOOKUP($D13,'CLIENTES NUEVA ID ZONA'!$A:$F,5,0),"INACTIVO") -> ANDREINA RANGEL 21 | C13: =IFERROR(VLOOKUP($D13,'CLIENTES NUEVA ID ZONA'!$A:$F,6,0),"INACTIVO") -> ANDREINA RANGEL | D13: J311877053 | E13: DROGUERIA MEDICA DEL SUR C.A. | F13: 01 | I13: 24 | J13: Desc 3% - Dólares | K13: =COUNTIF($F$2:$F$1080,I13) -> 3
B14: =IFERROR(VLOOKUP($D14,'CLIENTES NUEVA ID ZONA'!$A:$F,5,0),"INACTIVO") -> ANDREINA RANGEL 21 | C14: =IFERROR(VLOOKUP($D14,'CLIENTES NUEVA ID ZONA'!$A:$F,6,0),"INACTIVO") -> ANDREINA RANGEL | D14: J314890638 | E14: DROGUERIA COL MEDICA, S.A. | F14: 01 | I14: 06 | J14: Desc 5% - Bolívares | K14: =COUNTIF($F$2:$F$1080,I14) -> 2
B15: =IFERROR(VLOOKUP($D15,'CLIENTES NUEVA ID ZONA'!$A:$F,5,0),"INACTIVO") -> ANDREINA RANGEL 21 | C15: =IFERROR(VLOOKUP($D15,'CLIENTES NUEVA ID ZONA'!$A:$F,6,0),"INACTIVO") -> ANDREINA RANGEL | D15: J405979062 | E15: DROGUERIA Y SUMINISTROS DROFARZUCA C.A | F15: 26 | I15: 26 | J15: Desc 5% - Dólares | K15: =COUNTIF($F$2:$F$1080,I15) -> 96
B16: =IFERROR(VLOOKUP($D16,'CLIENTES NUEVA ID ZONA'!$A:$F,5,0),"INACTIVO") -> ANDREINA RANGEL 21 | C16: =IFERROR(VLOOKUP($D16,'CLIENTES NUEVA ID ZONA'!$A:$F,6,0),"INACTIVO") -> ANDREINA RANGEL | D16: J406823570 | E16: FARMACIA FARMA SERVICIO MARACAIBO, C.A | F16: 01 | I16: 10 | J16: Desc 10% - Bolívares | K16: =COUNTIF($F$2:$F$1080,I16) -> 12
B17: =IFERROR(VLOOKUP($D17,'CLIENTES NUEVA ID ZONA'!$A:$F,5,0),"INACTIVO") -> ANDREINA RANGEL 21 | C17: =IFERROR(VLOOKUP($D17,'CLIENTES NUEVA ID ZONA'!$A:$F,6,0),"INACTIVO") -> ANDREINA RANGEL | D17: J406897205 | E17: DROGUERIA MEDICA ESPECIAL, C.A | F17: 01 | I17: 20 | J17: Desc 10% - Dólares | K17: =COUNTIF($F$2:$F$1080,I17) -> 105
B18: =IFERROR(VLOOKUP($D18,'CLIENTES NUEVA ID ZONA'!$A:$F,5,0),"INACTIVO") -> ANDREINA RANGEL 21 | C18: =IFERROR(VLOOKUP($D18,'CLIENTES NUEVA ID ZONA'!$A:$F,6,0),"INACTIVO") -> ANDREINA RANGEL | D18: J407332775 | E18: FARMACIA SUPERSALUD DEL ZULIA, C.A | F18: 01 | I18: 15 | J18: Ecommerce - Bolívares | K18: =COUNTIF($F$2:$F$1080,I18) -> 0
B19: =IFERROR(VLOOKUP($D19,'CLIENTES NUEVA ID ZONA'!$A:$F,5,0),"INACTIVO") -> ANDREINA RANGEL 21 | C19: =IFERROR(VLOOKUP($D19,'CLIENTES NUEVA ID ZONA'!$A:$F,6,0),"INACTIVO") -> ANDREINA RANGEL | D19: J409182002 | E19: FARMACIA FARMAEXPRESS 24 LA 72, CA | F19: 01 | I19: 50 | J19: Ecommerce - Dólares | K19: =COUNTIF($F$2:$F$1080,I19) -> 75
... B21: =IFERROR(VLOOKUP($D21,'CLIENTES NUEVA ID ZONA'!$A:$F,5,0),"INACTIVO") -> ANDREINA RANGEL 21 | C21: =IFERROR(VLOOKUP($D21,'CLIENTES NUEVA ID ZONA'!$A:$F,6,0),"INACTIVO") -> ANDREINA RANGEL | D21: J500325371 | E21: FARMACIA FARMAEXPRESS 24 SAN FRANCISCO, C.A. | F21: 21 | I21: 22 | J21: Mas 5% del canal 21 - Dólares | K21: =COUNTIF($F$2:$F$1080,I21) -> 12
B22: =IFERROR(VLOOKUP($D22,'CLIENTES NUEVA ID ZONA'!$A:$F,5,0),"INACTIVO") -> ANDREINA RANGEL 21 | C22: =IFERROR(VLOOKUP($D22,'CLIENTES NUEVA ID ZONA'!$A:$F,6,0),"INACTIVO") -> ANDREINA RANGEL | D22: J298069783 | E22: FARMACIA LA LAGO,C.A. | F22: 21
B23: =IFERROR(VLOOKUP($D23,'CLIENTES NUEVA ID ZONA'!$A:$F,5,0),"INACTIVO") -> ANDREINA RANGEL 21 | C23: =IFERROR(VLOOKUP($D23,'CLIENTES NUEVA ID ZONA'!$A:$F,6,0),"INACTIVO") -> ANDREINA RANGEL | D23: J400145171 | E23: FARMACIA TIERRA NEGRA, C.A. | F23: 21
B24: =IFERROR(VLOOKUP($D24,'CLIENTES NUEVA ID ZONA'!$A:$F,5,0),"INACTIVO") -> ANDREINA RANGEL 21 | C24: =IFERROR(VLOOKUP($D24,'CLIENTES NUEVA ID ZONA'!$A:$F,6,0),"INACTIVO") -> ANDREINA RANGEL | D24: J411801313 | E24: FARMACIA AVENIDA UNIVERSIDAD, CA | F24: 21
B25: =IFERROR(VLOOKUP($D25,'CLIENTES NUEVA ID ZONA'!$A:$F,5,0),"INACTIVO") -> ANDREINA RANGEL 21 | C25: =IFERROR(VLOOKUP($D25,'CLIENTES NUEVA ID ZONA'!$A:$F,6,0),"INACTIVO") -> ANDREINA RANGEL | D25: J500029780 | E25: DROGUERIA DROPLUS OCCIDENTE, C.A | F25: 26
B26: =IFERROR(VLOOKUP($D26,'CLIENTES NUEVA ID ZONA'!$A:$F,5,0),"INACTIVO") -> JOSEPH PADILLA 61 | C26: =IFERROR(VLOOKUP($D26,'CLIENTES NUEVA ID ZONA'!$A:$F,6,0),"INACTIVO") -> ANDREINA RANGEL | D26: J312256761 | E26: DROGUERIA EL BIENESTAR DROBIENCA, C.A. | F26: 26
B27: =IFERROR(VLOOKUP($D27,'CLIENTES NUEVA ID ZONA'!$A:$F,5,0),"INACTIVO") -> ANDREINA RANGEL 21 | C27: =IFERROR(VLOOKUP($D27,'CLIENTES NUEVA ID ZONA'!$A:$F,6,0),"INACTIVO") -> ANDREINA RANGEL | D27: J500925115 | E27: DROGUERIA EDA, C.A | F27: 26
B28: =IFERROR(VLOOKUP($D28,'CLIENTES NUEVA ID ZONA'!$A:$F,5,0),"INACTIVO") -> ANDREINA RANGEL 21 | C28: =IFERROR(VLOOKUP($D28,'CLIENTES NUEVA ID ZONA'!$A:$F,6,0),"INACTIVO") -> ANDREINA RANGEL | D28: J408567709 | E28: DROGUERIA DROMARKO, C.A | F28: 26
B29: =IFERROR(VLOOKUP($D29,'CLIENTES NUEVA ID ZONA'!$A:$F,5,0),"INACTIVO") -> ANDREINA RANGEL 21 | C29: =IFERROR(VLOOKUP($D29,'CLIENTES NUEVA ID ZONA'!$A:$F,6,0),"INACTIVO") -> ANDREINA RANGEL | D29: J501933669 | E29: DROGUERIA 365, C.A | F29: 26
B30: =IFERROR(VLOOKUP($D30,'CLIENTES NUEVA ID ZONA'!$A:$F,5,0),"INACTIVO") -> JOSEPH PADILLA 61 | C30: =IFERROR(VLOOKUP($D30,'CLIENTES NUEVA ID ZONA'!$A:$F,6,0),"INACTIVO") -> ANDREINA RANGEL | D30: J303525938 | E30: H.A ESPOSITO, C.A | F30: 20
B31: =IFERROR(VLOOKUP($D31,'CLIENTES NUEVA ID ZONA'!$A:$F,5,0),"INACTIVO") -> ANDREINA RANGEL 62 | C31: =IFERROR(VLOOKUP($D31,'CLIENTES NUEVA ID ZONA'!$A:$F,6,0),"INACTIVO") -> ANDREINA RANGEL | D31: J305479925 | E31: DISTRIBUCIONES VERA, C.A. | F31: 21
B32: =IFERROR(VLOOKUP($D32,'CLIENTES NUEVA ID ZONA'!$A:$F,5,0),"INACTIVO") -> ANDREINA RANGEL 62 | C32: =IFERROR(VLOOKUP($D32,'CLIENTES NUEVA ID ZONA'!$A:$F,6,0),"INACTIVO") -> ANDREINA RANGEL | D32: J308460281 | E32: CREA - DESARROLLOS, SOCIEDAD ANONIMA (CREDESA) | F32: 21
B33: =IFERROR(VLOOKUP($D33,'CLIENTES NUEVA ID ZONA'!$A:$F,5,0),"INACTIVO") -> ANDREINA RANGEL 62 | C33: =IFERROR(VLOOKUP($D33,'CLIENTES NUEVA ID ZONA'!$A:$F,6,0),"INACTIVO") -> ANDREINA RANGEL | D33: J403830339 | E33: MARKET DISTRIBUICIONES,C.A | F33: 20
... B198: =IFERROR(VLOOKUP($D198,'CLIENTES NUEVA ID ZONA'!$A:$F,5,0),"INACTIVO") -> EDUWARD MARTÍNEZ | C198: =IFERROR(VLOOKUP($D198,'CLIENTES NUEVA ID ZONA'!$A:$F,6,0),"INACTIVO") -> MILAGROS FERNANDEZ | D198: J307494166 | E198: FARMACIA LOCPAR 18, C.A. | F198: 21
B199: =IFERROR(VLOOKUP($D199,'CLIENTES NUEVA ID ZONA'!$A:$F,5,0),"INACTIVO") -> ELVIS RONDON | C199: =IFERROR(VLOOKUP($D199,'CLIENTES NUEVA ID ZONA'!$A:$F,6,0),"INACTIVO") -> MILAGROS FERNANDEZ | D199: J307976420 | E199: FARMACIA NORAM, C.A. | F199: 21
B200: =IFERROR(VLOOKUP($D200,'CLIENTES NUEVA ID ZONA'!$A:$F,5,0),"INACTIVO") -> ELVIS RONDON | C200: =IFERROR(VLOOKUP($D200,'CLIENTES NUEVA ID ZONA'!$A:$F,6,0),"INACTIVO") -> MILAGROS FERNANDEZ | D200: J311583939 | E200: FARMACIA 9 ENE, C.A. | F200: 21
B201: =IFERROR(VLOOKUP($D201,'CLIENTES NUEVA ID ZONA'!$A:$F,5,0),"INACTIVO") -> INACTIVO | C201: =IFERROR(VLOOKUP($D201,'CLIENTES NUEVA ID ZONA'!$A:$F,6,0),"INACTIVO") -> INACTIVO | D201: J311609946 | E201: FARMACIA SALUD GUAYCAR C.A. | F201: 01
B202: =IFERROR(VLOOKUP($D202,'CLIENTES NUEVA ID ZONA'!$A:$F,5,0),"INACTIVO") -> EDUWARD MARTÍNEZ | C202: =IFERROR(VLOOKUP($D202,'CLIENTES NUEVA ID ZONA'!$A:$F,6,0),"INACTIVO") -> MILAGROS FERNANDEZ | D202: J502022120 | E202: FARMACIA LCT 18, C.A | F202: 21
B203: =IFERROR(VLOOKUP($D203,'CLIENTES NUEVA ID ZONA'!$A:$F,5,0),"INACTIVO") -> EVENTUALES | C203: =IFERROR(VLOOKUP($D203,'CLIENTES NUEVA ID ZONA'!$A:$F,6,0),"INACTIVO") -> ROSLI APONTE | D203: J300706206 | E203: INDUSTRIAS CORPAÑAL, C.A. | F203: 01
B204: =IFERROR(VLOOKUP($D204,'CLIENTES NUEVA ID ZONA'!$A:$F,5,0),"INACTIVO") -> EVENTUALES | C204: =IFERROR(VLOOKUP($D204,'CLIENTES NUEVA ID ZONA'!$A:$F,6,0),"INACTIVO") -> ROSLI APONTE | D204: J308487406 | E204: ASOC CIVIL INSTITUTO DE TEOLOGIA PARA RELIGIOSOS | F204: 21
B205: =IFERROR(VLOOKUP($D205,'CLIENTES NUEVA ID ZONA'!$A:$F,5,0),"INACTIVO") -> DUBRASKA PÉREZ 11 | C205: =IFERROR(VLOOKUP($D205,'CLIENTES NUEVA ID ZONA'!$A:$F,6,0),"INACTIVO") -> DUBRASKA PÉREZ | D205: J313650153 | E205: CONFECCIONES Y DISTRIBUIDORA P.H.E.S. C.A. | F205: 01
B206: =IFERROR(VLOOKUP($D206,'CLIENTES NUEVA ID ZONA'!$A:$F,5,0),"INACTIVO") -> EVENTUALES | C206: =IFERROR(VLOOKUP($D206,'CLIENTES NUEVA ID ZONA'!$A:$F,6,0),"INACTIVO") -> ROSLI APONTE | D206: J002416262 | E206: CONDOMINIO RES. EL NARANJAL TORRE D (X) | F206: 21
B207: =IFERROR(VLOOKUP($D207,'CLIENTES NUEVA ID ZONA'!$A:$F,5,0),"INACTIVO") -> INACTIVO | C207: =IFERROR(VLOOKUP($D207,'CLIENTES NUEVA ID ZONA'!$A:$F,6,0),"INACTIVO") -> INACTIVO | D207: J090010637 | E207: TENERIA RUBIO, C.A. | F207: 01
B208: =IFERROR(VLOOKUP($D208,'CLIENTES NUEVA ID ZONA'!$A:$F,5,0),"INACTIVO") -> EVENTUALES | C208: =IFERROR(VLOOKUP($D208,'CLIENTES NUEVA ID ZONA'!$A:$F,6,0),"INACTIVO") -> ROSLI APONTE | D208: J297727710 | E208: INVERSIONES Y SERVICIOS LARA, C.A | F208: 21
B209: =IFERROR(VLOOKUP($D209,'CLIENTES NUEVA ID ZONA'!$A:$F,5,0),"INACTIVO") -> INACTIVO | C209: =IFERROR(VLOOKUP($D209,'CLIENTES NUEVA ID ZONA'!$A:$F,6,0),"INACTIVO") -> INACTIVO | D209: J309256017 | E209: RESIDENCIAS JARDIN SANTA EDUVIGIS | F209: 01
B210: =IFERROR(VLOOKUP($D210,'CLIENTES NUEVA ID ZONA'!$A:$F,5,0),"INACTIVO") -> INACTIVO | C210: =IFERROR(VLOOKUP($D210,'CLIENTES NUEVA ID ZONA'!$A:$F,6,0),"INACTIVO") -> INACTIVO | D210: J316786110 | E210: AVILA PINTURAS, C.A. | F210: 21
B211: =IFERROR(VLOOKUP($D211,'CLIENTES NUEVA ID ZONA'!$A:$F,5,0),"INACTIVO") -> INACTIVO | C211: =IFERROR(VLOOKUP($D211,'CLIENTES NUEVA ID ZONA'!$A:$F,6,0),"INACTIVO") -> INACTIVO | D211: J404498923 | E211: ASOCOMPRA ASOCIACIÓN DE COMPRADORES, A.C. | F211: 20
... B729: =IFERROR(VLOOKUP($D729,'CLIENTES NUEVA ID ZONA'!$A:$F,5,0),"INACTIVO") -> JONATHAN FERNÁNDEZ | C729: =IFERROR(VLOOKUP($D729,'CLIENTES NUEVA ID ZONA'!$A:$F,6,0),"INACTIVO") -> MILAGROS FERNANDEZ | D729: J306035010 | E729: FARMACIA SAFEL 777 S.A. | F729: 21
B730: =IFERROR(VLOOKUP($D730,'CLIENTES NUEVA ID ZONA'!$A:$F,5,0),"INACTIVO") -> WILLIAN FERMIN | C730: =IFERROR(VLOOKUP($D730,'CLIENTES NUEVA ID ZONA'!$A:$F,6,0),"INACTIVO") -> MILAGROS FERNANDEZ | D730: J306811036 | E730: FARMACIA DARANPE, C.A. | F730: 21
B731: =IFERROR(VLOOKUP($D731,'CLIENTES NUEVA ID ZONA'!$A:$F,5,0),"INACTIVO") -> CARLOS ZURITA | C731: =IFERROR(VLOOKUP($D731,'CLIENTES NUEVA ID ZONA'!$A:$F,6,0),"INACTIVO") -> MILAGROS FERNANDEZ | D731: J306943838 | E731: TRINIGOLD FARMACIA, C.A. | F731: 21
B732: =IFERROR(VLOOKUP($D732,'CLIENTES NUEVA ID ZONA'!$A:$F,5,0),"INACTIVO") -> JONATHAN FERNÁNDEZ | C732: =IFERROR(VLOOKUP($D732,'CLIENTES NUEVA ID ZONA'!$A:$F,6,0),"INACTIVO") -> MILAGROS FERNANDEZ | D732: J309060457 | E732: FARMACIA CANDEL, C.A. | F732: 01
B733: =IFERROR(VLOOKUP($D733,'CLIENTES NUEVA ID ZONA'!$A:$F,5,0),"INACTIVO") -> INACTIVO | C733: =IFERROR(VLOOKUP($D733,'CLIENTES NUEVA ID ZONA'!$A:$F,6,0),"INACTIVO") -> INACTIVO | D733: V172191378 | E733: YOHANA GABRIELA MESA JAIMES | F733: 20
B734: =IFERROR(VLOOKUP($D734,'CLIENTES NUEVA ID ZONA'!$A:$F,5,0),"INACTIVO") -> JOSEPH PADILLA 61 | C734: =IFERROR(VLOOKUP($D734,'CLIENTES NUEVA ID ZONA'!$A:$F,6,0),"INACTIVO") -> ANDREINA RANGEL | D734: J293514002 | E734: MERCA FACIL AUTOMERCADO, C.A. | F734: 21
B735: =IFERROR(VLOOKUP($D735,'CLIENTES NUEVA ID ZONA'!$A:$F,5,0),"INACTIVO") -> JOSEPH PADILLA | C735: =IFERROR(VLOOKUP($D735,'CLIENTES NUEVA ID ZONA'!$A:$F,6,0),"INACTIVO") -> ANDREINA RANGEL | D735: J411919233 | E735: DROGUERIA CENTRAL C.A | F735: 01
B736: =IFERROR(VLOOKUP($D736,'CLIENTES NUEVA ID ZONA'!$A:$F,5,0),"INACTIVO") -> JOSEPH PADILLA 61 | C736: =IFERROR(VLOOKUP($D736,'CLIENTES NUEVA ID ZONA'!$A:$F,6,0),"INACTIVO") -> ANDREINA RANGEL | D736: J302545617 | E736: SUPERMERCADO BARATTA C.A. | F736: 21
B737: =IFERROR(VLOOKUP($D737,'CLIENTES NUEVA ID ZONA'!$A:$F,5,0),"INACTIVO") -> JOSEPH PADILLA 61 | C737: =IFERROR(VLOOKUP($D737,'CLIENTES NUEVA ID ZONA'!$A:$F,6,0),"INACTIVO") -> ANDREINA RANGEL | D737: J305269300 | E737: GARZON HIPERMERCADO, C.A. | F737: 21
B738: =IFERROR(VLOOKUP($D738,'CLIENTES NUEVA ID ZONA'!$A:$F,5,0),"INACTIVO") -> JOSEPH PADILLA | C738: =IFERROR(VLOOKUP($D738,'CLIENTES NUEVA ID ZONA'!$A:$F,6,0),"INACTIVO") -> ANDREINA RANGEL | D738: J307012676 | E738: COMERCIALIZADORA ROMERO 2000,C.A. | F738: 26
B739: =IFERROR(VLOOKUP($D739,'CLIENTES NUEVA ID ZONA'!$A:$F,5,0),"INACTIVO") -> INACTIVO | C739: =IFERROR(VLOOKUP($D739,'CLIENTES NUEVA ID ZONA'!$A:$F,6,0),"INACTIVO") -> INACTIVO | D739: J311576649 | E739: FARMACIAS DEL TACHIRA (FARTA) C.A. | F739: 01
B740: =IFERROR(VLOOKUP($D740,'CLIENTES NUEVA ID ZONA'!$A:$F,5,0),"INACTIVO") -> JOSEPH PADILLA 61 | C740: =IFERROR(VLOOKUP($D740,'CLIENTES NUEVA ID ZONA'!$A:$F,6,0),"INACTIVO") -> ANDREINA RANGEL | D740: J500162944 | E740: DROGUERIA LOS ANDES, C.A. | F740: 26
B741: =IFERROR(VLOOKUP($D741,'CLIENTES NUEVA ID ZONA'!$A:$F,5,0),"INACTIVO") -> JOSEPH PADILLA | C741: =IFERROR(VLOOKUP($D741,'CLIENTES NUEVA ID ZONA'!$A:$F,6,0),"INACTIVO") -> ANDREINA RANGEL | D741: J302788811 | E741: SURTI MEDICA CHACON C.A. | F741: 21
B742: =IFERROR(VLOOKUP($D742,'CLIENTES NUEVA ID ZONA'!$A:$F,5,0),"INACTIVO") -> JOSEPH PADILLA | C742: =IFERROR(VLOOKUP($D742,'CLIENTES NUEVA ID ZONA'!$A:$F,6,0),"INACTIVO") -> ANDREINA RANGEL | D742: J404079289 | E742: DEMACA ANDINA CA | F742: 20
B743: =IFERROR(VLOOKUP($D743,'CLIENTES NUEVA ID ZONA'!$A:$F,5,0),"INACTIVO") -> JOSEPH PADILLA | C743: =IFERROR(VLOOKUP($D743,'CLIENTES NUEVA ID ZONA'!$A:$F,6,0),"INACTIVO") -> ANDREINA RANGEL | D743: J408651238 | E743: DISTRIBUIDORA GARCIA MARTINEZ C.A | F743: 20
... B781: =IFERROR(VLOOKUP($D781,'CLIENTES NUEVA ID ZONA'!$A:$F,5,0),"INACTIVO") -> JOSEPH PADILLA 61 | C781: =IFERROR(VLOOKUP($D781,'CLIENTES NUEVA ID ZONA'!$A:$F,6,0),"INACTIVO") -> ANDREINA RANGEL | D781: J500682700 | E781: DISERMAT, C.A | F781: 26
B782: =IFERROR(VLOOKUP($D782,'CLIENTES NUEVA ID ZONA'!$A:$F,5,0),"INACTIVO") -> JOSEPH PADILLA 61 | C782: =IFERROR(VLOOKUP($D782,'CLIENTES NUEVA ID ZONA'!$A:$F,6,0),"INACTIVO") -> ANDREINA RANGEL | D782: J408905949 | E782: DROGUERIA PICO BOLIVAR, C.A | F782: 26
B783: =IFERROR(VLOOKUP($D783,'CLIENTES NUEVA ID ZONA'!$A:$F,5,0),"INACTIVO") -> INACTIVO | C783: =IFERROR(VLOOKUP($D783,'CLIENTES NUEVA ID ZONA'!$A:$F,6,0),"INACTIVO") -> INACTIVO | D783: J412623095 | E783: SAN JUAN GROUP, C.A | F783: 21
B784: =IFERROR(VLOOKUP($D784,'CLIENTES NUEVA ID ZONA'!$A:$F,5,0),"INACTIVO") -> JUAN LEÓN 12 | C784: =IFERROR(VLOOKUP($D784,'CLIENTES NUEVA ID ZONA'!$A:$F,6,0),"INACTIVO") -> DUBRASKA PÉREZ | D784: J401131530 | E784: HYPER LIDER FLOR AMARILLO, C.A. | F784: 21
B785: =IFERROR(VLOOKUP($D785,'CLIENTES NUEVA ID ZONA'!$A:$F,5,0),"INACTIVO") -> JUAN LEÓN 12 | C785: =IFERROR(VLOOKUP($D785,'CLIENTES NUEVA ID ZONA'!$A:$F,6,0),"INACTIVO") -> DUBRASKA PÉREZ | D785: J401131670 | E785: HYPER LIDER SAN DIEGO, C.A. | F785: 21
B786: =IFERROR(VLOOKUP($D786,'CLIENTES NUEVA ID ZONA'!$A:$F,5,0),"INACTIVO") -> JUAN LEÓN 12 | C786: =IFERROR(VLOOKUP($D786,'CLIENTES NUEVA ID ZONA'!$A:$F,6,0),"INACTIVO") -> DUBRASKA PÉREZ | D786: J410906928 | E786: HIPER LIDER SAN FELIPE, C.A | F786: 21
B787: =IFERROR(VLOOKUP($D787,'CLIENTES NUEVA ID ZONA'!$A:$F,5,0),"INACTIVO") -> JUAN LEÓN 12 | C787: =IFERROR(VLOOKUP($D787,'CLIENTES NUEVA ID ZONA'!$A:$F,6,0),"INACTIVO") -> DUBRASKA PÉREZ | D787: J413158400 | E787: HIPER LIDER BARCELONA, C.A | F787: 21
B788: =IFERROR(VLOOKUP($D788,'CLIENTES NUEVA ID ZONA'!$A:$F,5,0),"INACTIVO") -> JUAN LEÓN 12 | C788: =IFERROR(VLOOKUP($D788,'CLIENTES NUEVA ID ZONA'!$A:$F,6,0),"INACTIVO") -> DUBRASKA PÉREZ | D788: J413174839 | E788: HIPER LIDER MATURIN, C.A | F788: 21
B789: =IFERROR(VLOOKUP($D789,'CLIENTES NUEVA ID ZONA'!$A:$F,5,0),"INACTIVO") -> JUAN LEÓN 12 | C789: =IFERROR(VLOOKUP($D789,'CLIENTES NUEVA ID ZONA'!$A:$F,6,0),"INACTIVO") -> DUBRASKA PÉREZ | D789: J402174160 | E789: HYPER LIDER YARITAGUA, C.A. | F789: 21
B790: =IFERROR(VLOOKUP($D790,'CLIENTES NUEVA ID ZONA'!$A:$F,5,0),"INACTIVO") -> JUAN LEÓN 12 | C790: =IFERROR(VLOOKUP($D790,'CLIENTES NUEVA ID ZONA'!$A:$F,6,0),"INACTIVO") -> DUBRASKA PÉREZ | D790: J405521040 | E790: HIPER LIDER CABUDARE, C.A. | F790: 21
B791: =IFERROR(VLOOKUP($D791,'CLIENTES NUEVA ID ZONA'!$A:$F,5,0),"INACTIVO") -> JUAN LEÓN 12 | C791: =IFERROR(VLOOKUP($D791,'CLIENTES NUEVA ID ZONA'!$A:$F,6,0),"INACTIVO") -> DUBRASKA PÉREZ | D791: J406004766 | E791: HIPER LIDER TAMACA,CA | F791: 21
B792: =IFERROR(VLOOKUP($D792,'CLIENTES NUEVA ID ZONA'!$A:$F,5,0),"INACTIVO") -> JUAN LEÓN 12 | C792: =IFERROR(VLOOKUP($D792,'CLIENTES NUEVA ID ZONA'!$A:$F,6,0),"INACTIVO") -> DUBRASKA PÉREZ | D792: J293611547 | E792: SUPER LIDER PALO NEGRO, C.A. | F792: 21
B793: =IFERROR(VLOOKUP($D793,'CLIENTES NUEVA ID ZONA'!$A:$F,5,0),"INACTIVO") -> JUAN LEÓN 12 | C793: =IFERROR(VLOOKUP($D793,'CLIENTES NUEVA ID ZONA'!$A:$F,6,0),"INACTIVO") -> DUBRASKA PÉREZ | D793: J294451675 | E793: CORPORACION JRC, C.A. | F793: 21
B794: =IFERROR(VLOOKUP($D794,'CLIENTES NUEVA ID ZONA'!$A:$F,5,0),"INACTIVO") -> INACTIVO | C794: =IFERROR(VLOOKUP($D794,'CLIENTES NUEVA ID ZONA'!$A:$F,6,0),"INACTIVO") -> INACTIVO | D794: J296689130 | E794: FARMACIA YERBA BUENA, C.A. | F794: 01
... B1117: =IFERROR(VLOOKUP($D1117,'CLIENTES NUEVA ID ZONA'!$A:$F,5,0),"INACTIVO") -> JOSEPH PADILLA | C1117: =IFERROR(VLOOKUP($D1117,'CLIENTES NUEVA ID ZONA'!$A:$F,6,0),"INACTIVO") -> ANDREINA RANGEL | D1117: J500930798 | E1117: DROGUERIA SURDELAGO, C.A | F1117: 26
B1118: E-COMMERCE | C1118: E-COMMERCE | D1118: J502034315 | E1118: DISTRIBUIDORA QUINCALLA EXPRESS, C.A. | F1118: 50
B1119: =IFERROR(VLOOKUP($D1119,'CLIENTES NUEVA ID ZONA'!$A:$F,5,0),"INACTIVO") -> DUBRASKA PÉREZ 53 | C1119: =IFERROR(VLOOKUP($D1119,'CLIENTES NUEVA ID ZONA'!$A:$F,6,0),"INACTIVO") -> DUBRASKA PÉREZ | D1119: J065008709 | E1119: DISTRIBUIDORA ROSARIO, C. A | F1119: 20

Sheet Sucursales
B2: Código de dirección | C2: Número de cliente | D2: Nombre de cliente | E2: Nombre corto | F2: RUTA | G2: VENDEDOR | H2: GERENTE | I2: SUCURSAL
B3: 10018 | C3: J000797218 | D3: INVERSIONES LUVEBRAS, C.A. | E3: 91 LUVEBRAS | F3: 57 | G3: CARLOS ZURITA | H3: MILAGROS FERNANDEZ | I3: GUATIRE (VALLE ARRIB)
B4: 10019 | C4: J000797218 | D4: INVERSIONES LUVEBRAS, C.A. | E4: 91 LUVEBRAS | F4: 57 | G4: CARLOS ZURITA | H4: MILAGROS FERNANDEZ | I4: GUATIRE (ESMERALDA )
B5: 10020 | C5: J000797218 | D5: INVERSIONES LUVEBRAS, C.A. | E5: 91 LUVEBRAS | F5: 57 | G5: CARLOS ZURITA | H5: MILAGROS FERNANDEZ | I5: LA CASTELLANA
B6: 10021 | C6: J000797218 | D6: INVERSIONES LUVEBRAS, C.A. | E6: 91 LUVEBRAS | F6: 58 | G6: ELVIS RONDON | H6: MILAGROS FERNANDEZ | I6: EL MARQUÉS
B7: 10022 | C7: J000797218 | D7: INVERSIONES LUVEBRAS, C.A. | E7: 91 LUVEBRAS | F7: 58 | G7: ELVIS RONDON | H7: MILAGROS FERNANDEZ | I7: LA FLORIDA
B8: 10023 | C8: J000797218 | D8: INVERSIONES LUVEBRAS, C.A. | E8: 91 LUVEBRAS | F8: 58 | G8: ELVIS RONDON | H8: MILAGROS FERNANDEZ | I8: SANTA MÓNICA
B9: 10024 | C9: J000797218 | D9: INVERSIONES LUVEBRAS, C.A. | E9: 91 LUVEBRAS | F9: 58 | G9: ELVIS RONDON | H9: MILAGROS FERNANDEZ | I9: SANTA INES
B10: 50002 | C10: J000811601 | D10: AUTOMERCADO LUZ C.A. | E10: AUTOMERCADO LUZ | F10: 58 | G10: VACANTE | H10: MILAGROS FERNANDEZ | I10: CHACAO
B11: 50019 | C11: J000811601 | D11: AUTOMERCADO LUZ C.A. | E11: AUTOMERCADO LUZ | F11: 58 | G11: VACANTE | H11: MILAGROS FERNANDEZ | I11: LA FLORIDA (ANDRÉS BELLO)
B12: 11043 | C12: J305065616 | D12: PLANSUAREZ, C.A. | E12: 55 PLANSUAREZ | F12: 57 | G12: CARLOS ZURITA | H12: MILAGROS FERNANDEZ | I12: CAURIMARE
B13: 11044 | C13: J305065616 | D13: PLANSUAREZ, C.A. | E13: 55 PLANSUAREZ | F13: 57 | G13: CARLOS ZURITA | H13: MILAGROS FERNANDEZ | I13: LA URBINA
B14: 11045 | C14: J305065616 | D14: PLANSUAREZ, C.A. | E14: 55 PLANSUAREZ | F14: 57 | G14: CARLOS ZURITA | H14: MILAGROS FERNANDEZ | I14: LA TRINIDAD
... B55: 10110 | C55: J413273071 | D55: HIPER LIDER CERRO VERDE, C.A | E55: 90 SUPER LIDER | F55: 12 | G55: JUAN LEON | H55: DUBRASKA PÉREZ | I55: CUA
B56: 10092 | C56: J500199759 | D56: FORUM SUPER MAYORISTA, C.A | E56: FORUM | F56: 10 | I56: LOS PROCERES -IPFA
B57: 10098 | C57: J500199759 | D57: FORUM SUPER MAYORISTA, C.A | E57: FORUM | F57: 10 | I57: GUARENAS
B58: 10099 | C58: J500199759 | D58: FORUM SUPER MAYORISTA, C.A | E58: FORUM | F58: 10 | I58: VALENCIA
B59: 10100 | C59: J500199759 | D59: FORUM SUPER MAYORISTA, C.A | E59: FORUM | F59: 10 | I59: PORTUGUESA
B60: 10103 | C60: J500199759 | D60: FORUM SUPER MAYORISTA, C.A | E60: FORUM | F60: 10 | I60: MATURIN
B61: 10104 | C61: J500199759 | D61: FORUM SUPER MAYORISTA, C.A | E61: FORUM | F61: 10 | I61: CENDIS - CUA
B62: 10105 | C62: J500199759 | D62: FORUM SUPER MAYORISTA, C.A | E62: FORUM | F62: 10 | I62: PARAISO
B63: 10106 | C63: J500199759 | D63: FORUM SUPER MAYORISTA, C.A | E63: FORUM | F63: 10 | I63: CARRIZAL
B64: 50078 | C64: J500199759 | D64: FORUM SUPER MAYORISTA, C.A | E64: FORUM | F64: 10 | I64: CAGUA
B65: 10108 | C65: J500199759 | D65: FORUM SUPER MAYORISTA, C.A | E65: FORUM | F65: 10 | I65: GUATIRE
B66: 10107 | C66: J500199759 | D66: FORUM SUPER MAYORISTA, C.A | E66: FORUM | F66: 10 | I66: LA URBINA - CARACAS
B67: 10111 | C67: J500199759 | D67: FORUM SUPER MAYORISTA, C.A | E67: FORUM | F67: 10 | I67: MARACAY
B68: 10118 | C68: J500199759 | D68: FORUM SUPER MAYORISTA, C.A | E68: FORUM | F68: 10 | I68: BARUTA - LA PIRAMIDE
B69: 23042 | C69: J411399655 | D69: GRAN ABASTO GIRASOL C.A | E69: ABASTO GIRASOL | F69: 23 | G69: MARTHA VILORIA | H69: DUBRASKA PÉREZ | I69: ACARIGUA-PORTUGUESA
B70: 23043 | C70: J411399655 | D70: GRAN ABASTO GIRASOL C.A | E70: ABASTO GIRASOL | F70: 23 | G70: MARTHA VILORIA | H70: DUBRASKA PÉREZ | I70: ARAURE-PORTUGUESA
B71: 23044 | C71: J411399655 | D71: GRAN ABASTO GIRASOL C.A | E71: ABASTO GIRASOL | F71: 23 | G71: MARTHA VILORIA | H71: DUBRASKA PÉREZ | I71: GUANARE-PORTUGUESA
B72: 23045 | C72: J411399655 | D72: GRAN ABASTO GIRASOL C.A | E72: ABASTO GIRASOL | F72: 23 | G72: MARTHA VILORIA | H72: DUBRASKA PÉREZ | I72: BARINAS
B73: 23062 | C73: J411399655 | D73: GRAN ABASTO GIRASOL C.A | E73: ABASTO GIRASOL | F73: 23 | G73: MARTHA VILORIA | H73: DUBRASKA PÉREZ | I73: BARQUISIMETO
B74: 11082 | C74: J500374275 | D74: IMPORTADORA EL TIO AMMI I, C.A | E74: EL TIO AMMI | F74: 11 | G74: DUBRASKA PÉREZ 11 | H74: DUBRASKA PÉREZ | I74: KAPITANIA - EL RECREO
B75: 11083 | C75: J500374275 | D75: IMPORTADORA EL TIO AMMI I, C.A | E75: EL TIO AMMI | F75: 11 | G75: DUBRASKA PÉREZ 11 | H75: DUBRASKA PÉREZ | I75: CAGUA
B76: 11084 | C76: J500374275 | D76: IMPORTADORA EL TIO AMMI I, C.A | E76: EL TIO AMMI | F76: 11 | G76: DUBRASKA PÉREZ 11 | H76: DUBRASKA PÉREZ | I76: VALENCIA
B77: 11085 | C77: J500374275 | D77: IMPORTADORA EL TIO AMMI I, C.A | E77: EL TIO AMMI | F77: 11 | G77: DUBRASKA PÉREZ 11 | H77: DUBRASKA PÉREZ | I77: GUACARA
B78: 11090 | C78: J500374461 | D78: IMPORTADORA EL TIO AMMI II, C.A | E78: EL TIO AMMI | F78: 11 | G78: DUBRASKA PÉREZ 11 | H78: DUBRASKA PÉREZ | I78: CRUZ VERDE
B79: 11091 | C79: J500374461 | D79: IMPORTADORA EL TIO AMMI II, C.A | E79: EL TIO AMMI | F79: 11 | G79: DUBRASKA PÉREZ 11 | H79: DUBRASKA PÉREZ | I79: CATIA
B80: 11092 | C80: J500374461 | D80: IMPORTADORA EL TIO AMMI II, C.A | E80: EL TIO AMMI | F80: 11 | G80: DUBRASKA PÉREZ 11 | H80: DUBRASKA PÉREZ | I80: CABIMAS
... B88: 11089 | C88: J500374518 | D88: IMPORTADORA EL TIO AMMI IV, C.A | E88: EL TIO AMMI | F88: 11 | G88: DUBRASKA PÉREZ 11 | H88: DUBRASKA PÉREZ | I88: MATURIN
B89: 20119 | C89: J500328800 | D89: REDVITAL COMERCIALIZADORA, C.A. | E89: DROG PHARMAX | F89: =VLOOKUP($C89,Tabla3[[#All],[Número de cliente]:[Ciudad]],4,0) -> 20 | G89: =VLOOKUP($C89,Tabla3[[#All],[Número de cliente]:[Ciudad]],5,0) -> JUAN LEÓN 20 | H89: =VLOOKUP($C89,Tabla3[[#All],[Número de cliente]:[Ciudad]],6,0) -> DUBRASKA PÉREZ | I89: SAN DIEGO
B90: 20120 | C90: J500328800 | D90: REDVITAL COMERCIALIZADORA, C.A. | E90: DROG PHARMAX | F90: =VLOOKUP($C90,Tabla3[[#All],[Número de cliente]:[Ciudad]],4,0) -> 20 | G90: =VLOOKUP($C90,Tabla3[[#All],[Número de cliente]:[Ciudad]],5,0) -> JUAN LEÓN 20 | H90: =VLOOKUP($C90,Tabla3[[#All],[Número de cliente]:[Ciudad]],6,0) -> DUBRASKA PÉREZ | I90: MARACAIBO (LA LIMPIA)
B91: 20121 | C91: J500328800 | D91: REDVITAL COMERCIALIZADORA, C.A. | E91: DROG PHARMAX | F91: =VLOOKUP($C91,Tabla3[[#All],[Número de cliente]:[Ciudad]],4,0) -> 20 | G91: =VLOOKUP($C91,Tabla3[[#All],[Número de cliente]:[Ciudad]],5,0) -> JUAN LEÓN 20 | H91: =VLOOKUP($C91,Tabla3[[#All],[Número de cliente]:[Ciudad]],6,0) -> DUBRASKA PÉREZ | I91: BARQUISIMETO
B92: 20122 | C92: J500328800 | D92: REDVITAL COMERCIALIZADORA, C.A. | E92: DROG PHARMAX | F92: =VLOOKUP($C92,Tabla3[[#All],[Número de cliente]:[Ciudad]],4,0) -> 20 | G92: =VLOOKUP($C92,Tabla3[[#All],[Número de cliente]:[Ciudad]],5,0) -> JUAN LEÓN 20 | H92: =VLOOKUP($C92,Tabla3[[#All],[Número de cliente]:[Ciudad]],6,0) -> DUBRASKA PÉREZ | I92: TURMERO
B93: 20123 | C93: J500328800 | D93: REDVITAL COMERCIALIZADORA, C.A. | E93: DROG PHARMAX | F93: =VLOOKUP($C93,Tabla3[[#All],[Número de cliente]:[Ciudad]],4,0) -> 20 | G93: =VLOOKUP($C93,Tabla3[[#All],[Número de cliente]:[Ciudad]],5,0) -> JUAN LEÓN 20 | H93: =VLOOKUP($C93,Tabla3[[#All],[Número de cliente]:[Ciudad]],6,0) -> DUBRASKA PÉREZ | I93: GUARENAS
B94: 20124 | C94: J500328800 | D94: REDVITAL COMERCIALIZADORA, C.A. | E94: DROG PHARMAX | F94: =VLOOKUP($C94,Tabla3[[#All],[Número de cliente]:[Ciudad]],4,0) -> 20 | G94: =VLOOKUP($C94,Tabla3[[#All],[Número de cliente]:[Ciudad]],5,0) -> JUAN LEÓN 20 | H94: =VLOOKUP($C94,Tabla3[[#All],[Número de cliente]:[Ciudad]],6,0) -> DUBRASKA PÉREZ | I94: PUERTO CABELLO
B95: 20125 | C95: J500328800 | D95: REDVITAL COMERCIALIZADORA, C.A. | E95: DROG PHARMAX | F95: =VLOOKUP($C95,Tabla3[[#All],[Número de cliente]:[Ciudad]],4,0) -> 20 | G95: =VLOOKUP($C95,Tabla3[[#All],[Número de cliente]:[Ciudad]],5,0) -> JUAN LEÓN 20 | H95: =VLOOKUP($C95,Tabla3[[#All],[Número de cliente]:[Ciudad]],6,0) -> DUBRASKA PÉREZ | I95: MARACAY
B96: 20126 | C96: J500328800 | D96: REDVITAL COMERCIALIZADORA, C.A. | E96: DROG PHARMAX | F96: =VLOOKUP($C96,Tabla3[[#All],[Número de cliente]:[Ciudad]],4,0) -> 20 | G96: =VLOOKUP($C96,Tabla3[[#All],[Número de cliente]:[Ciudad]],5,0) -> JUAN LEÓN 20 | H96: =VLOOKUP($C96,Tabla3[[#All],[Número de cliente]:[Ciudad]],6,0) -> DUBRASKA PÉREZ | I96: SAN FELIPE
B97: 20127 | C97: J500328800 | D97: REDVITAL COMERCIALIZADORA, C.A. | E97: DROG PHARMAX | F97: =VLOOKUP($C97,Tabla3[[#All],[Número de cliente]:[Ciudad]],4,0) -> 20 | G97: =VLOOKUP($C97,Tabla3[[#All],[Número de cliente]:[Ciudad]],5,0) -> JUAN LEÓN 20 | H97: =VLOOKUP($C97,Tabla3[[#All],[Número de cliente]:[Ciudad]],6,0) -> DUBRASKA PÉREZ | I97: LISANDRO ALVARADO
B98: 20128 | C98: J500328800 | D98: REDVITAL COMERCIALIZADORA, C.A. | E98: DROG PHARMAX | F98: =VLOOKUP($C98,Tabla3[[#All],[Número de cliente]:[Ciudad]],4,0) -> 20 | G98: =VLOOKUP($C98,Tabla3[[#All],[Número de cliente]:[Ciudad]],5,0) -> JUAN LEÓN 20 | H98: =VLOOKUP($C98,Tabla3[[#All],[Número de cliente]:[Ciudad]],6,0) -> DUBRASKA PÉREZ | I98: RIO LAMA
B99: 20129 | C99: J500328800 | D99: REDVITAL COMERCIALIZADORA, C.A. | E99: DROG PHARMAX | F99: =VLOOKUP($C99,Tabla3[[#All],[Número de cliente]:[Ciudad]],4,0) -> 20 | G99: =VLOOKUP($C99,Tabla3[[#All],[Número de cliente]:[Ciudad]],5,0) -> JUAN LEÓN 20 | H99: =VLOOKUP($C99,Tabla3[[#All],[Número de cliente]:[Ciudad]],6,0) -> DUBRASKA PÉREZ | I99: CC CRISTAL
B100: 20130 | C100: J500328800 | D100: REDVITAL COMERCIALIZADORA, C.A. | E100: DROG PHARMAX | F100: =VLOOKUP($C100,Tabla3[[#All],[Número de cliente]:[Ciudad]],4,0) -> 20 | G100: =VLOOKUP($C100,Tabla3[[#All],[Número de cliente]:[Ciudad]],5,0) -> JUAN LEÓN 20 | H100: =VLOOKUP($C100,Tabla3[[#All],[Número de cliente]:[Ciudad]],6,0) -> DUBRASKA PÉREZ | I100: GUACARA
... B106: 20136 | C106: J500328800 | D106: REDVITAL COMERCIALIZADORA, C.A. | E106: DROG PHARMAX | F106: =VLOOKUP($C106,Tabla3[[#All],[Número de cliente]:[Ciudad]],4,0) -> 20 | G106: =VLOOKUP($C106,Tabla3[[#All],[Número de cliente]:[Ciudad]],5,0) -> JUAN LEÓN 20 | H106: =VLOOKUP($C106,Tabla3[[#All],[Número de cliente]:[Ciudad]],6,0) -> DUBRASKA PÉREZ | I106: LA VIÑA (PATTISERIE)
B107: 20082 | C107: J500328800 | D107: REDVITAL COMERCIALIZADORA, C.A. | E107: DROG PHARMAX | F107: =VLOOKUP($C107,Tabla3[[#All],[Número de cliente]:[Ciudad]],4,0) -> 20 | G107: =VLOOKUP($C107,Tabla3[[#All],[Número de cliente]:[Ciudad]],5,0) -> JUAN LEÓN 20 | H107: =VLOOKUP($C107,Tabla3[[#All],[Número de cliente]:[Ciudad]],6,0) -> DUBRASKA PÉREZ | I107: LA VIÑA | J107: Lab Ponce
B108: 20099 | C108: J500328800 | D108: REDVITAL COMERCIALIZADORA, C.A. | E108: DROG PHARMAX | F108: =VLOOKUP($C108,Tabla3[[#All],[Número de cliente]:[Ciudad]],4,0) -> 20 | G108: =VLOOKUP($C108,Tabla3[[#All],[Número de cliente]:[Ciudad]],5,0) -> JUAN LEÓN 20 | H108: =VLOOKUP($C108,Tabla3[[#All],[Número de cliente]:[Ciudad]],6,0) -> DUBRASKA PÉREZ | I108: LA VIÑA
B109: 20114 | C109: J500328800 | D109: REDVITAL COMERCIALIZADORA, C.A. | E109: DROG PHARMAX | F109: =VLOOKUP($C109,Tabla3[[#All],[Número de cliente]:[Ciudad]],4,0) -> 20 | G109: =VLOOKUP($C109,Tabla3[[#All],[Número de cliente]:[Ciudad]],5,0) -> JUAN LEÓN 20 | H109: =VLOOKUP($C109,Tabla3[[#All],[Número de cliente]:[Ciudad]],6,0) -> DUBRASKA PÉREZ | I109: LA YAGUARA
B110: 20115 | C110: J500328800 | D110: REDVITAL COMERCIALIZADORA, C.A. | E110: DROG PHARMAX | F110: =VLOOKUP($C110,Tabla3[[#All],[Número de cliente]:[Ciudad]],4,0) -> 20 | G110: =VLOOKUP($C110,Tabla3[[#All],[Número de cliente]:[Ciudad]],5,0) -> JUAN LEÓN 20 | H110: =VLOOKUP($C110,Tabla3[[#All],[Número de cliente]:[Ciudad]],6,0) -> DUBRASKA PÉREZ | I110: LA URBINA
B111: 20137 | C111: J500328800 | D111: REDVITAL COMERCIALIZADORA, C.A. | E111: DROG PHARMAX | F111: =VLOOKUP($C111,Tabla3[[#All],[Número de cliente]:[Ciudad]],4,0) -> 20 | G111: =VLOOKUP($C111,Tabla3[[#All],[Número de cliente]:[Ciudad]],5,0) -> JUAN LEÓN 20 | H111: =VLOOKUP($C111,Tabla3[[#All],[Número de cliente]:[Ciudad]],6,0) -> DUBRASKA PÉREZ | I111: FIN DE SIGLO
B112: 20139 | C112: J500328800 | D112: REDVITAL COMERCIALIZADORA, C.A. | E112: DROG PHARMAX | F112: =VLOOKUP($C112,Tabla3[[#All],[Número de cliente]:[Ciudad]],4,0) -> 20 | G112: =VLOOKUP($C112,Tabla3[[#All],[Número de cliente]:[Ciudad]],5,0) -> JUAN LEÓN 20 | H112: =VLOOKUP($C112,Tabla3[[#All],[Número de cliente]:[Ciudad]],6,0) -> DUBRASKA PÉREZ | I112: NAGUANAGUA
B113: 20140 | C113: J500328800 | D113: REDVITAL COMERCIALIZADORA, C.A. | E113: DROG PHARMAX | F113: =VLOOKUP($C113,Tabla3[[#All],[Número de cliente]:[Ciudad]],4,0) -> 20 | G113: =VLOOKUP($C113,Tabla3[[#All],[Número de cliente]:[Ciudad]],5,0) -> JUAN LEÓN 20 | H113: =VLOOKUP($C113,Tabla3[[#All],[Número de cliente]:[Ciudad]],6,0) -> DUBRASKA PÉREZ | I113: LA GUAIRA

Sheet SKU
A1: Número de artículo | B1: Descripción artículo | C1: MARCA | D1: ORIGEN | E1: FAMILIA | F1: U de M | G1: SUB - MARCA | H1: COMPAÑÍA | I1: ESTATUS | J1: PROVEEDOR | K1: EAN13 | L1: NOMBRE CORTO | M1: Contenido | N1: Peso | O1: Empaque
A2: 1010110021 | B2: DENCORUB CREMA 20X48 (E) | C2: DENCORUB | D2: PROPIA | E2: FARMA | F2: 48 | G2: DENCORUB | H2: LP | I2: INACTIVO | J2: LABORATORIOS PONCE | L2: DENCORUB CREMA 20GR | M2: 20 | N2: gr | O2: 48 | P2: =+A2 -> 1010110021
A3: 1010110041 | B3: DENCORUB CREMA 40X48 (E) | C3: DENCORUB | D3: PROPIA | E3: FARMA | F3: 48 | G3: DENCORUB | H3: LP | I3: INACTIVO | J3: LABORATORIOS PONCE | L3: DENCORUB CREMA 40GR | M3: 40 | N3: gr | O3: 48 | P3: =+A3 -> 1010110041
A4: 1010110081 | B4: DENCORUB CREMA 80X48 (E) | C4: DENCORUB | D4: PROPIA | E4: FARMA | F4: 48 | G4: DENCORUB | H4: LP | I4: INACTIVO | J4: LABORATORIOS PONCE | L4: DENCORUB CREMA 80GR | M4: 80 | N4: gr | O4: 48 | P4: =+A4 -> 1010110081
A5: 1010210041 | B5: DENCORUB GEL 40X48 (E) | C5: DENCORUB | D5: PROPIA | E5: FARMA | F5: 48 | G5: DENCORUB | H5: LP | I5: INACTIVO | J5: LABORATORIOS PONCE | L5: DENCORUB GEL 40GR | M5: 40 | N5: gr | O5: 48 | P5: =+A5 -> 1010210041
A6: 1010210081 | B6: DENCORUB GEL 80X48 (E) | C6: DENCORUB | D6: PROPIA | E6: FARMA | F6: 48 | G6: DENCORUB | H6: LP | I6: INACTIVO | J6: LABORATORIOS PONCE | L6: DENCORUB GEL 80GR | M6: 80 | N6: gr | O6: 48 | P6: =+A6 -> 1010210081
A7: 1010310075 | B7: DENCORUB AIR 75X24 (E) | C7: DENCORUB | D7: PROPIA | E7: FARMA | F7: 24 | G7: DENCORUB | H7: LP | I7: INACTIVO | J7: LABORATORIOS PONCE | L7: DENCORUB AIR 75 | M7: 75 | N7: gr | O7: 24 | P7: =+A7 -> 1010310075
A8: 1030110020 | B8: DENCOFEN 1,16% C-GEL20X24(E) | C8: DENCOFEN | D8: PROPIA | E8: FARMA | F8: 24 | G8: DENCOFEN | H8: LP | I8: ACTIVO | J8: LABORATORIOS PONCE | K8: 7591309003296 | L8: DENCOFEN GEL 20GR | M8: 20 | N8: gr | O8: 24 | P8: =+A8 -> 1030110020
A9: 1030111020 | B9: DENCOFEN 1,16%C-GEL 20X48 (E) | C9: DENCOFEN | D9: PROPIA | E9: FARMA | F9: 48 | G9: DENCOFEN | H9: LP | I9: INACTIVO | J9: LABORATORIOS PONCE | L9: DENCOFEN GEL 20GR | M9: 20 | N9: gr | O9: 48 | P9: =+A9 -> 1030111020
A10: 1030111040 | B10: DENCOFEN 1,16%C-GEL 40X48 (E) | C10: DENCOFEN | D10: PROPIA | E10: FARMA | F10: 48 | G10: DENCOFEN | H10: LP | I10: INACTIVO | J10: LABORATORIOS PONCE | L10: DENCOFEN GEL 40GR | M10: 40 | N10: gr | O10: 48 | P10: =+A10 -> 1030111040
A11: 1030111080 | B11: DENCOFEN 1,16%C-GEL 80X48 (E) | C11: DENCOFEN | D11: PROPIA | E11: FARMA | F11: 48 | G11: DENCOFEN | H11: LP | I11: INACTIVO | J11: LABORATORIOS PONCE | L11: DENCOFEN GEL 80GR | M11: 80 | N11: gr | O11: 48 | P11: =+A11 -> 1030111080
A12: 1040210040 | B12: BENGAY CREMA 40X48 (E) | C12: BENGAY | D12: PROPIA | E12: FARMA | F12: 48 | G12: BENGAY | H12: LP | I12: INACTIVO | J12: LABORATORIOS PONCE | M12: 40 | N12: gr | O12: 48 | P12: =+A12 -> 1040210040
A13: 1040310040 | B13: BENGAY GEL 40X48 (E) | C13: BENGAY | D13: PROPIA | E13: FARMA | F13: 48 | G13: BENGAY | H13: LP | I13: INACTIVO | J13: LABORATORIOS PONCE | M13: 40 | N13: gr | O13: 48 | P13: =+A13 -> 1040310040
A14: 1040410040 | B14: BENGAY UNGTO.40X48 (E) | C14: BENGAY | D14: PROPIA | E14: FARMA | F14: 48 | G14: BENGAY | H14: LP | I14: INACTIVO | J14: LABORATORIOS PONCE | M14: 40 | N14: gr | O14: 48 | P14: =+A14 -> 1040410040
A15: 2200110033 | B15: CURE BAND VENDITAS STD 30X12 | C15: CURE BAND | D15: REPRESENTADA | E15: COSMÉTICO | F15: 12 | G15: CURE BAND | H15: P&B | I15: INACTIVO | J15: PONCE & BENZO | M15: 30 | O15: 12 | P15: =+A15 -> 2200110033
A16: 2200110103 | B16: CURE BAND VENDITAS STD 100X100 | C16: CURE BAND | D16: REPRESENTADA | E16: COSMÉTICO | F16: 100 | G16: CURE BAND | H16: P&B | I16: INACTIVO | J16: PONCE & BENZO | M16: 100 | O16: 100 | P16: =+A16 -> 2200110103
A17: 2200110125 | B17: CURE BAND VENDITA STD 100X24 | C17: CURE BAND | D17: REPRESENTADA | E17: COSMÉTICO | F17: 24 | G17: CURE BAND | H17: P&B | I17: INACTIVO | J17: PONCE & BENZO | M17: 100 | O17: 24 | P17: =+A17 -> 2200110125
A18: 2240130252 | B18: PLAK- ATTACK CON FLUOR KIDS | C18: PLACK- ATTACK | D18: PROPIA | E18: COSMÉTICO | F18: 1 | G18: PLACK- ATTACK | H18: P&B | I18: INACTIVO | J18: PONCE & BENZO | P18: =+A18 -> 2240130252
A19: 2240240250 | B19: PLAK-ATTACK PROT ENCIA 250X12 | C19: PLACK- ATTACK | D19: PROPIA | E19: COSMÉTICO | F19: 12 | G19: PLACK- ATTACK | H19: P&B | I19: INACTIVO | J19: PONCE & BENZO | M19: 250 | O19: 12 | P19: =+A19 -> 2240240250
A20: 2260120120 | B20: DIOX.GEL ANTIBACTERIAL 110X12 | C20: DIOXOGEN | D20: PROPIA | E20: COSMÉTICO | F20: 12 | G20: DIOXOGEN MED ANTIBACTERIAL | H20: P&B | I20: INACTIVO | J20: PONCE & BENZO | M20: 110 | N20: gr | O20: 12 | P20: =+A20 -> 2260120120
A21: 2260120220 | B21: DIOX.GEL ANTIBACTERIAL 220X12 | C21: DIOXOGEN | D21: PROPIA | E21: COSMÉTICO | F21: 12 | G21: DIOXOGEN MED ANTIBACTERIAL | H21: P&B | I21: INACTIVO | J21: PONCE & BENZO | M21: 220 | N21: gr | O21: 12 | P21: =+A21 -> 2260120220
A22: 2260130110 | B22: DIOX. GEL ANTIBACTERIAL Q10.110X12 | C22: DIOXOGEN | D22: PROPIA | E22: COSMÉTICO | F22: 12 | G22: DIOXOGEN MED ANTIBACTERIAL | H22: P&B | I22: INACTIVO | J22: PONCE & BENZO | M22: 110 | N22: gr | O22: 12 | P22: =+A22 -> 2260130110
A23: 2260220241 | B23: DIOX JAB.LIQUIDO MED 240X24 | C23: DIOXOGEN | D23: PROPIA | E23: COSMÉTICO | F23: 24 | G23: DIOXOGEN JABÓN LÍQUIDO | H23: P&B | I23: INACTIVO | J23: PONCE & BENZO | L23: DIOXOGEN JAB.LIQUIDO MED 240GR | M23: 240 | N23: ml | O23: 24 | P23: =+A23 -> 2260220241
A24: 2260221250 | B24: DIOX.JAB LIQ.EXT.TE VERD230X12 | C24: DIOXOGEN | D24: PROPIA | E24: COSMÉTICO | F24: 12 | G24: DIOXOGEN JABÓN LÍQUIDO | H24: P&B | I24: INACTIVO | J24: PONCE & BENZO | M24: 230 | N24: ml | O24: 12 | P24: =+A24 -> 2260221250
A25: 2260222250 | B25: DIOX.JAB LIQ.EXT.ALGODON230X12 | C25: DIOXOGEN | D25: PROPIA | E25: COSMÉTICO | F25: 12 | G25: DIOXOGEN JABÓN LÍQUIDO | H25: P&B | I25: INACTIVO | J25: PONCE & BENZO | M25: 230 | N25: ml | O25: 12 | P25: =+A25 -> 2260222250
A26: 2260223250 | B26: DIOX.JAB LIQ.EXT.UVA ROJ230X12 | C26: DIOXOGEN | D26: PROPIA | E26: COSMÉTICO | F26: 12 | G26: DIOXOGEN JABÓN LÍQUIDO | H26: P&B | I26: INACTIVO | J26: PONCE & BENZO | M26: 230 | N26: ml | O26: 12 | P26: =+A26 -> 2260223250
A27: 2260224250 | B27: DIOXOGEN JABON LIQUIDO EXTRAC. ALOE VERA 230 X 12 | C27: DIOXOGEN | D27: PROPIA | E27: COSMÉTICO | F27: 12 | G27: DIOXOGEN JABÓN LÍQUIDO | H27: P&B | I27: INACTIVO | J27: PONCE & BENZO | M27: 230 | N27: ml | O27: 12 | P27: =+A27 -> 2260224250
A28: 2260229230 | B28: DIOX.JAB LIQ.EXT.ALOE V 230X24 | C28: DIOXOGEN | D28: PROPIA | E28: COSMÉTICO | F28: 24 | G28: DIOXOGEN JABÓN LÍQUIDO | H28: P&B | I28: INACTIVO | J28: PONCE & BENZO | M28: 230 | N28: ml | O28: 24 | P28: =+A28 -> 2260229230
A29: 2260225250 | B29: DIOX.JAB LIQ.EXTRA.PROTE230X12 | C29: DIOXOGEN | D29: PROPIA | E29: COSMÉTICO | F29: 12 | G29: DIOXOGEN JABÓN LÍQUIDO | H29: P&B | I29: INACTIVO | J29: PONCE & BENZO | M29: 230 | N29: ml | O29: 12 | P29: =+A29 -> 2260225250
A30: 2260227230 | B30: DIOX.JAB LIQ.EXT.ALGODON230X24 | C30: DIOXOGEN | D30: PROPIA | E30: COSMÉTICO | F30: 24 | G30: DIOXOGEN JABÓN LÍQUIDO | H30: P&B | I30: INACTIVO | J30: PONCE & BENZO | M30: 230 | N30: ml | O30: 24 | P30: =+A30 -> 2260227230
A31: 2260230230 | B31: DIOX.JAB LIQ.EXTRA.PROTE230X24 | C31: DIOXOGEN | D31: PROPIA | E31: COSMÉTICO | F31: 24 | G31: DIOXOGEN JABÓN LÍQUIDO | H31: P&B | I31: INACTIVO | J31: PONCE & BENZO | M31: 230 | N31: ml | O31: 24 | P31: =+A31 -> 2260230230
A32: 2260310041 | B32: DIOX.ROLL ORIGINAL 40X63 | C32: DIOXOGEN | D32: PROPIA | E32: COSMÉTICO | F32: 63 | G32: DIOXOGEN DESODORANTE | H32: P&B | I32: INACTIVO | J32: PONCE & BENZO | M32: 40 | N32: gr | O32: 63 | P32: =+A32 -> 2260310041
A33: 2260310136 | B33: DIOX.ROLL ORIG 90X36 | C33: DIOXOGEN | D33: PROPIA | E33: COSMÉTICO | F33: 36 | G33: DIOXOGEN DESODORANTE | H33: P&B | I33: ACTIVO | J33: PONCE & BENZO | K33: 7591309000042 | L33: DIOXOGEN ROLL ON ORIGINAL 90GR | M33: 90 | N33: gr | O33: 36 | P33: =+A33 -> 2260310136
A34: 2260320040 | B34: DIOX.ROLL TALCO 40X12 | C34: DIOXOGEN | D34: PROPIA | E34: COSMÉTICO | F34: 12 | G34: DIOXOGEN DESODORANTE | H34: P&B | I34: INACTIVO | J34: PONCE & BENZO | M34: 40 | N34: gr | O34: 12 | P34: =+A34 -> 2260320040
A35: 2260320136 | B35: DIOX.ROLL TALCO 90X36 | C35: DIOXOGEN | D35: PROPIA | E35: COSMÉTICO | F35: 36 | G35: DIOXOGEN DESODORANTE | H35: P&B | I35: ACTIVO | J35: PONCE & BENZO | K35: 7591309000066 | L35: DIOXOGEN ROLL ON TALCO 90GR | M35: 90 | N35: gr | O35: 36 | P35: =+A35 -> 2260320136
A36: 2260330043 | B36: DIOX.ROLL ALOE V 40X63 | C36: DIOXOGEN | D36: PROPIA | E36: COSMÉTICO | F36: 63 | G36: DIOXOGEN DESODORANTE | H36: P&B | I36: INACTIVO | J36: PONCE & BENZO | M36: 40 | N36: gr | O36: 63 | P36: =+A36 -> 2260330043
A37: 2260330136 | B37: DIOX.ROLL ALOE 90X36 | C37: DIOXOGEN | D37: PROPIA | E37: COSMÉTICO | F37: 36 | G37: DIOXOGEN DESODORANTE | H37: P&B | I37: ACTIVO | J37: PONCE & BENZO | K37: 7591309000080 | L37: DIOXOGEN ROLL ON ALOE 90GR | M37: 90 | N37: gr | O37: 36 | P37: =+A37 -> 2260330136
A38: 2260340136 | B38: DIOX.ROLL BICARB 90X36 | C38: DIOXOGEN | D38: PROPIA | E38: COSMÉTICO | F38: 36 | G38: DIOXOGEN DESODORANTE | H38: P&B | I38: ACTIVO | J38: PONCE & BENZO | K38: 7591309000219 | L38: DIOXOGEN ROLL ON BICARBONATO 90GR | M38: 90 | N38: gr | O38: 36 | P38: =+A38 -> 2260340136
A39: 2260315012 | B39: DIOXOGEN ROLL ON ORIGINAL 50X12 | C39: DIOXOGEN | D39: PROPIA | E39: COSMÉTICO | F39: 12 | G39: DIOXOGEN DESODORANTE | H39: P&B | I39: ACTIVO | J39: PONCE & BENZO | K39: 7591309002480 | L39: DIOXOGEN ROLL ON ORIGINAL 50GR | M39: 50 | N39: gr | O39: 12 | P39: =+A39 -> 2260315012
A40: 2260325012 | B40: DIOXOGEN ROLL ON TALCO 50X12 | C40: DIOXOGEN | D40: PROPIA | E40: COSMÉTICO | F40: 12 | G40: DIOXOGEN DESODORANTE | H40: P&B | I40: ACTIVO | J40: PONCE & BENZO | K40: 7591309002473 | L40: DIOXOGEN ROLL ON TALCO 50GR | M40: 50 | N40: gr | O40: 12 | P40: =+A40 -> 2260325012
A41: 2260335012 | B41: DIOXOGEN ROLL ON ALOE 50X12 | C41: DIOXOGEN | D41: PROPIA | E41: COSMÉTICO | F41: 12 | G41: DIOXOGEN DESODORANTE | H41: P&B | I41: ACTIVO | J41: PONCE & BENZO | K41: 7591309002510 | L41: DIOXOGEN ROLL ON ALOE 50GR | M41: 50 | N41: gr | O41: 12 | P41: =+A41 -> 2260335012
A42: 2260345012 | B42: DIOXOGEN ROLL ON BICARBONATO 50X12 | C42: DIOXOGEN | D42: PROPIA | E42: COSMÉTICO | F42: 12 | G42: DIOXOGEN DESODORANTE | H42: P&B | I42: ACTIVO | J42: PONCE & BENZO | K42: 7591309002466 | L42: DIOXOGEN ROLL ON BICARBONATO 50GR | M42: 50 | N42: gr | O42: 12 | P42: =+A42 -> 2260345012
A43: 2260410240 | B43: DIOX.GELLIMPIADOR 240X24 | C43: DIOXOGEN | D43: PROPIA | E43: COSMÉTICO | F43: 24 | G43: DIOXOGEN MED | H43: P&B | I43: INACTIVO | J43: PONCE & BENZO | M43: 240 | N43: gr | O43: 24 | P43: =+A43 -> 2260410240
A44: 2260510115 | B44: DIOXOGEN SOLUCION 115X24 | C44: DIOXOGEN | D44: PROPIA | E44: COSMÉTICO | F44: 24 | G44: DIOXOGEN MED | H44: P&B | I44: ACTIVO | J44: PONCE & BENZO | K44: 7591309900762 | L44: DIOXOGEN SOLUCIÓN 115ml | M44: 115 | N44: ml | O44: 24 | P44: =+A44 -> 2260510115
A45: 2260510116 | B45: DIOXOGEN SOLUCION 115X12 | C45: DIOXOGEN | D45: PROPIA | E45: COSMÉTICO | F45: 12 | G45: DIOXOGEN MED | H45: P&B | I45: INACTIVO | J45: PONCE & BENZO | M45: 115 | N45: ml | O45: 12 | P45: =+A45 -> 2260510116
A46: 2260510230 | B46: DIOXOGEN SOLUCION 230X24 | C46: DIOXOGEN | D46: PROPIA | E46: COSMÉTICO | F46: 24 | G46: DIOXOGEN MED | H46: P&B | I46: INACTIVO | J46: PONCE & BENZO | K46: 7591309900779 | L46: DIOXOGEN SOLUCIÓN 230ml | M46: 230 | N46: ml | O46: 24 | P46: =+A46 -> 2260510230
A47: 2260510460 | B47: DIOXOGEN SOLUCION 460X12 | C47: DIOXOGEN | D47: PROPIA | E47: COSMÉTICO | F47: 12 | G47: DIOXOGEN MED | H47: P&B | I47: ACTIVO | J47: PONCE & BENZO | K47: 7591309900793 | L47: DIOXOGEN SOLUCIÓN 460ml | M47: 460 | N47: ml | O47: 12 | P47: =+A47 -> 2260510460
A48: 2260510461 | B48: DIOXOGEN SOLUCION 460X6 | C48: DIOXOGEN | D48: PROPIA | E48: COSMÉTICO | F48: 6 | G48: DIOXOGEN MED | H48: P&B | I48: INACTIVO | J48: PONCE & BENZO | M48: 460 | N48: ml | O48: 6 | P48: =+A48 -> 2260510461
A49: 2260811175 | B49: DIOX DES AERO ORIG(NAC)175X12 | C49: DIOXOGEN | D49: PROPIA | E49: COSMÉTICO | F49: 12 | G49: DIOXOGEN DESODORANTE | H49: P&B | I49: INACTIVO | J49: PONCE & BENZO | K49: 7591309003258 | L49: DIOXOGEN AERO ORIGINAL 175 | M49: 175 | O49: 12 | P49: =+A49 -> 2260811175
A50: 2260822175 | B50: DIOX DES AERO TAL(NAC) 175X12 | C50: DIOXOGEN | D50: PROPIA | E50: COSMÉTICO | F50: 12 | G50: DIOXOGEN DESODORANTE | H50: P&B | I50: INACTIVO | J50: PONCE & BENZO | K50: 7591309003265 | L50: DIOXOGEN AERO TALCO 175 | M50: 175 | O50: 12 | P50: =+A50 -> 2260822175
A51: 2260844175 | B51: DIOX DES AERO BICAR(NAC)175X12 | C51: DIOXOGEN | D51: PROPIA | E51: COSMÉTICO | F51: 12 | G51: DIOXOGEN DESODORANTE | H51: P&B | I51: INACTIVO | J51: PONCE & BENZO | K51: 7591309003272 | L51: DIOXOGEN AERO BICARBONATO 175 | M51: 175 | O51: 12 | P51: =+A51 -> 2260844175
A52: 2260910200 | B52: DIOX.ESPUMA AFEIT.TTP 200X20 | C52: DIOXOGEN | D52: PROPIA | E52: COSMÉTICO | F52: 20 | G52: DIOXOGEN ESPUMA AFEITAR | H52: P&B | I52: INACTIVO | J52: PONCE & BENZO | M52: 200 | O52: 20 | P52: =+A52 -> 2260910200
A53: 2260911200 | B53: DIOX.ESPUMA AFEIT. TTP200X23 | C53: DIOXOGEN | D53: PROPIA | E53: COSMÉTICO | F53: 23 | G53: DIOXOGEN ESPUMA AFEITAR | H53: P&B | I53: INACTIVO | J53: PONCE & BENZO | M53: 200 | O53: 23 | P53: =+A53 -> 2260911200
A54: 2261132280 | B54: DIOX INTEN C GEL LIMP ANT HIP 280X12 | C54: DIOXOGEN | D54: PROPIA | E54: COSMÉTICO | F54: 12 | G54: DIOXOGEN JABÓN LÍQUIDO | H54: P&B | I54: ACTIVO | J54: PONCE & BENZO | K54: 7591309901318 | L54: DIOXOGEN INTEN CARE 280GR | M54: 280 | N54: gr | O54: 12 | P54: =+A54 -> 2261132280
A55: 2310110051 | B55: OVERSKIN ANTI CREMA TUBO 50X12 | C55: OVERSKIN | D55: PROPIA | E55: COSMÉTICO | F55: 12 | G55: OVERSKIN | H55: P&B | I55: ACTIVO | J55: PONCE & BENZO | K55: 7591309000622 | L55: OVERSKIN 40% 50GR | M55: 50 | N55: gr | O55: 12 | P55: =+A55 -> 2310110051
A56: 2310111050 | B56: OVERSKIN TUBO PANALIT10% 50X12 | C56: OVERSKIN | D56: PROPIA | E56: COSMÉTICO | F56: 12 | G56: OVERSKIN | H56: P&B | I56: INACTIVO | J56: PONCE & BENZO | M56: 50 | N56: gr | O56: 12 | P56: =+A56 -> 2310111050
A57: 2310135012 | B57: OVERSKIN TUBO PANALIT13% 50X12 | C57: OVERSKIN | D57: PROPIA | E57: COSMÉTICO | F57: 12 | G57: OVERSKIN | H57: P&B | I57: ACTIVO | J57: PONCE & BENZO | K57: 7591309002183 | L57: OVERSKIN 13% 50GR | M57: 50 | N57: gr | O57: 12 | P57: =+A57 -> 2310135012
A58: 2310301250 | B58: OVERSKIN CREMA HUM 250X12 | C58: OVERSKIN | D58: PROPIA | E58: COSMÉTICO | F58: 12 | G58: OVERSKIN | H58: P&B | I58: INACTIVO | J58: PONCE & BENZO | M58: 250 | N58: gr | O58: 12 | P58: =+A58 -> 2310301250
A59: 9050100001 | B59: KIT OVERSKIN X 6 | C59: OVERSKIN | D59: PROPIA | E59: COSMÉTICO | F59: 6 | G59: OVERSKIN | H59: P&B | I59: INACTIVO | J59: PONCE & BENZO | O59: 6 | P59: =+A59 -> 9050100001
A60: 2370110018 | B60: SHOCK.CEP.PL.RD.YSG-2111F.1X12 | C60: SHOCK | D60: REPRESENTADA | E60: COSMÉTICO | F60: 12 | G60: SHOCK | H60: P&B | I60: INACTIVO | J60: PONCE & BENZO | M60: 1 | O60: 12 | P60: =+A60 -> 2370110018
A61: 2380110013 | B61: FREE CEP.PARA CEJAS EY-01 1X12 | C61: FREE | D61: REPRESENTADA | E61: COSMÉTICO | F61: 12 | G61: FREE | H61: P&B | I61: INACTIVO | J61: PONCE & BENZO | M61: 1 | O61: 12 | P61: =+A61 -> 2380110013
A62: 2380310012 | B62: FREE ESPEJO OVNI M836SS 1X12 | C62: FREE | D62: REPRESENTADA | E62: COSMÉTICO | F62: 12 | G62: FREE | H62: P&B | I62: INACTIVO | J62: PONCE & BENZO | M62: 1 | O62: 12 | P62: =+A62 -> 2380310012
A63: 2380310013 | B63: FREE ESPEJ HERRAD M849SS 1X12 | C63: FREE | D63: REPRESENTADA | E63: COSMÉTICO | F63: 12 | G63: FREE | H63: P&B | I63: INACTIVO | J63: PONCE & BENZO | M63: 1 | O63: 12 | P63: =+A63 -> 2380310013
A64: 2380310014 | B64: FREE ESPEJ PLATEA M850SS 1X12 | C64: FREE | D64: REPRESENTADA | E64: COSMÉTICO | F64: 12 | G64: FREE | H64: P&B | I64: INACTIVO | J64: PONCE & BENZO | M64: 1 | O64: 12 | P64: =+A64 -> 2380310014
A65: 2380510012 | B65: FREE ENCR DE PESTA±A NC02 1X12 | C65: FREE | D65: REPRESENTADA | E65: COSMÉTICO | F65: 12 | G65: FREE | H65: P&B | I65: INACTIVO | J65: PONCE & BENZO | M65: 1 | O65: 12 | P65: =+A65 -> 2380510012
A66: 2380610014 | B66: FREE ESPEJ FACIAL LS07 6X12 | C66: FREE | D66: REPRESENTADA | E66: COSMÉTICO | F66: 12 | G66: FREE | H66: P&B | I66: INACTIVO | J66: PONCE & BENZO | M66: 6 | O66: 12 | P66: =+A66 -> 2380610014
A67: 2532410003 | B67: SHARK LUBRICADO 24X3 | C67: SHARK | D67: REPRESENTADA | E67: COSMÉTICO | F67: 3 | G67: SHARK | H67: P&B | I67: INACTIVO | J67: PONCE & BENZO | M67: 24 | O67: 3 | P67: =+A67 -> 2532410003
A68: 2532430003 | B68: SHARK SUPERFINO 24X3 | C68: SHARK | D68: REPRESENTADA | E68: COSMÉTICO | F68: 3 | G68: SHARK | H68: P&B | I68: INACTIVO | J68: PONCE & BENZO | M68: 24 | O68: 3 | P68: =+A68 -> 2532430003
A69: 2532490003 | B69: SHARK DUAL PLEASURE 24X3 | C69: SHARK | D69: REPRESENTADA | E69: COSMÉTICO | F69: 3 | G69: SHARK | H69: P&B | I69: INACTIVO | J69: PONCE & BENZO | M69: 24 | O69: 3 | P69: =+A69 -> 2532490003
A70: 2540011250 | B70: STARKIDS CREMA 250X12 | C70: STARKIDS | D70: PROPIA | E70: COSMÉTICO | F70: 12 | G70: STARKIDS | H70: P&B | I70: INACTIVO | J70: PONCE & BENZO | M70: 250 | N70: gr | O70: 12 | P70: =+A70 -> 2540011250
A71: 2540412150 | B71: STARKIDSTRIPGELANT(3X50)X12 | C71: STARKIDS | D71: PROPIA | E71: COSMÉTICO | F71: 12 | G71: STARKIDS | H71: P&B | I71: INACTIVO | J71: PONCE & BENZO | M71: 3 | O71: 12 | P71: =+A71 -> 2540412150
A72: 2550220230 | B72: SUPERKIDS JABLIQ 230X12 | C72: SUPERKIDS | D72: PROPIA | E72: COSMÉTICO | F72: 12 | G72: SUPERKIDS | H72: P&B | I72: INACTIVO | J72: PONCE & BENZO | M72: 230 | N72: ml | O72: 12 | P72: =+A72 -> 2550220230
A73: 2550422150 | B73: SUPERKIDSTRIPGELANT(3X50)X12 | C73: SUPERKIDS | D73: PROPIA | E73: COSMÉTICO | F73: 12 | G73: SUPERKIDS | H73: P&B | I73: INACTIVO | J73: PONCE & BENZO | M73: 3 | O73: 12 | P73: =+A73 -> 2550422150
A74: 2700110042 | B74: DENCORUB ICE(40*12)TERMOENCOG. | C74: DENCORUB | D74: PROPIA | E74: COSMÉTICO | F74: 12 | G74: DENCORUB ICE | H74: P&B | I74: INACTIVO | J74: PONCE & BENZO | L74: DENCORUB ICE 40GR | M74: 40 | N74: gr | O74: 12 | P74: =+A74 -> 2700110042
A75: 2700110043 | B75: DENCORUB ICE(40X24) | C75: DENCORUB | D75: PROPIA | E75: COSMÉTICO | F75: 24 | G75: DENCORUB ICE | H75: P&B | I75: ACTIVO | J75: PONCE & BENZO | K75: 7591309001049 | L75: DENCORUB ICE 40GR | M75: 40 | N75: gr | O75: 24 | P75: =+A75 -> 2700110043
A76: 2700110082 | B76: DENCORUB ICE(80*12)TERMOENCOG. | C76: DENCORUB | D76: PROPIA | E76: COSMÉTICO | F76: 12 | G76: DENCORUB ICE | H76: P&B | I76: INACTIVO | J76: PONCE & BENZO | L76: DENCORUB ICE 80GR | M76: 80 | N76: gr | O76: 12 | P76: =+A76 -> 2700110082
A77: 2700110084 | B77: DENCORUB ICE (80X24) | C77: DENCORUB | D77: PROPIA | E77: COSMÉTICO | F77: 24 | G77: DENCORUB ICE | H77: P&B | I77: INACTIVO | J77: PONCE & BENZO | L77: DENCORUB ICE 80GR | M77: 80 | N77: gr | O77: 24 | P77: =+A77 -> 2700110084
A78: 2700221090 | B78: DENCORUB ICE ARNICA 90X48 | C78: DENCORUB | D78: PROPIA | E78: COSMÉTICO | F78: 48 | G78: DENCORUB ICE | H78: P&B | I78: INACTIVO | J78: PONCE & BENZO | L78: DENCORUB ICE ARNICA 90GR | M78: 90 | N78: gr | O78: 48 | P78: =+A78 -> 2700221090
A79: 2970110015 | B79: VITENOL CREMA 15X24 | C79: VITENOL | D79: PROPIA | E79: COSMÉTICO | F79: 24 | G79: VITENOL | H79: P&B | I79: ACTIVO | J79: PONCE & BENZO | K79: 7591309000714 | L79: VITENOL 15GR | M79: 15 | N79: gr | O79: 24 | P79: =+A79 -> 2970110015
A80: 2980110048 | B80: ADEL UGUENTO 50X48 | C80: ADEL | D80: PROPIA | E80: COSMÉTICO | F80: 48 | G80: ADEL | H80: P&B | I80: INACTIVO | J80: PONCE & BENZO | L80: ADEL UNGÜENTO 50GR | M80: 50 | N80: gr | O80: 48 | P80: =+A80 -> 2980110048
A81: 2980111250 | B81: ADEL UNGÜENTO 50X 12 | C81: ADEL | D81: PROPIA | E81: COSMÉTICO | F81: 12 | G81: ADEL | H81: P&B | I81: ACTIVO | J81: PONCE & BENZO | K81: 7591309902834 | L81: ADEL UNGÜENTO 50GR | M81: 50 | N81: gr | O81: 12 | P81: =+A81 -> 2980111250
A82: 3020210240 | B82: WAMPOLE EMULS TUT FRUTI 240X36 | C82: WAMPOLE | D82: PROPIA | E82: ALIMENTO | F82: 36 | G82: WAMPOLE | H82: P&B | I82: INACTIVO | J82: PONCE & BENZO | M82: 240 | N82: ml | O82: 36 | P82: =+A82 -> 3020210240
A83: 3020210242 | B83: WAMPOLE EMULS TUT FRUTI 240X24 | C83: WAMPOLE | D83: PROPIA | E83: ALIMENTO | F83: 24 | G83: WAMPOLE | H83: P&B | I83: INACTIVO | J83: PONCE & BENZO | M83: 240 | N83: ml | O83: 24 | P83: =+A83 -> 3020210242
A84: 3020210243 | B84: WAMPOLE EMULS.TUT.FRUTI 240X12 | C84: WAMPOLE | D84: PROPIA | E84: ALIMENTO | F84: 12 | G84: WAMPOLE | H84: P&B | I84: INACTIVO | J84: PONCE & BENZO | M84: 240 | N84: ml | O84: 12 | P84: =+A84 -> 3020210243
A85: 3020210360 | B85: WAMPOLE EMULS TUT FRUTI 360X24 | C85: WAMPOLE | D85: PROPIA | E85: ALIMENTO | F85: 24 | G85: WAMPOLE | H85: P&B | I85: INACTIVO | J85: PONCE & BENZO | M85: 360 | N85: ml | O85: 24 | P85: =+A85 -> 3020210360
A86: 3020510240 | B86: WAMPOLE EMULS NARANJA 240X36 | C86: WAMPOLE | D86: PROPIA | E86: ALIMENTO | F86: 36 | G86: WAMPOLE | H86: P&B | I86: INACTIVO | J86: PONCE & BENZO | M86: 240 | N86: ml | O86: 36 | P86: =+A86 -> 3020510240
A87: 3020510360 | B87: WAMPOLE EMULS NARANJA 360X24 | C87: WAMPOLE | D87: PROPIA | E87: ALIMENTO | F87: 24 | G87: WAMPOLE | H87: P&B | I87: INACTIVO | J87: PONCE & BENZO | M87: 360 | N87: ml | O87: 24 | P87: =+A87 -> 3020510360
A88: 3020610240 | B88: WAMPOLE EMULS FRESA 240X36 | C88: WAMPOLE | D88: PROPIA | E88: ALIMENTO | F88: 36 | G88: WAMPOLE | H88: P&B | I88: INACTIVO | J88: PONCE & BENZO | M88: 240 | N88: ml | O88: 36 | P88: =+A88 -> 3020610240
A89: 3020610242 | B89: WAMPOLE EMULSION FRESA 240X24 | C89: WAMPOLE | D89: PROPIA | E89: ALIMENTO | F89: 24 | G89: WAMPOLE | H89: P&B | I89: INACTIVO | J89: PONCE & BENZO | M89: 240 | N89: ml | O89: 24 | P89: =+A89 -> 3020610242
A90: 3020610360 | B90: WAMPOLE EMULS FRESA 360X24 | C90: WAMPOLE | D90: PROPIA | E90: ALIMENTO | F90: 24 | G90: WAMPOLE | H90: P&B | I90: INACTIVO | J90: PONCE & BENZO | M90: 360 | N90: ml | O90: 24 | P90: =+A90 -> 3020610360
A91: 3030510400 | B91: WAMPOLE MERG.NAR.TARRO 400X12 | C91: WAMPOLE | D91: PROPIA | E91: ALIMENTO | F91: 12 | G91: WAMPOLE | H91: P&B | I91: INACTIVO | J91: PONCE & BENZO | M91: 400 | N91: ml | O91: 12 | P91: =+A91 -> 3030510400
A92: 3030710400 | B92: WAMPOLE MERG TUTTI-FRUT 400X12 | C92: WAMPOLE | D92: PROPIA | E92: ALIMENTO | F92: 12 | G92: WAMPOLE | H92: P&B | I92: INACTIVO | J92: PONCE & BENZO | M92: 400 | N92: ml | O92: 12 | P92: =+A92 -> 3030710400
A93: 3040110400 | B93: NTC NUTRI DESDE NAC 400X24 (E) | C93: NUTRICIA | D93: REPRESENTADA | E93: ALIMENTO | F93: 24 | G93: NUTRICIA | H93: P&B | I93: INACTIVO | J93: PONCE & BENZO | M93: 400 | O93: 24 | P93: =+A93 -> 3040110400
A94: 3040120400 | B94: NTC NUTRI MAY 6M 400X24 (E) | C94: NUTRICIA | D94: REPRESENTADA | E94: ALIMENTO | F94: 24 | G94: NUTRICIA | H94: P&B | I94: INACTIVO | J94: PONCE & BENZO | M94: 400 | O94: 24 | P94: =+A94 -> 3040120400
A95: 3040130400 | B95: NTC.NUTRILON A.R. 400X24 (E) | C95: NUTRICIA | D95: REPRESENTADA | E95: ALIMENTO | F95: 24 | G95: NUTRICIA | H95: P&B | I95: INACTIVO | J95: PONCE & BENZO | M95: 400 | O95: 24 | P95: =+A95 -> 3040130400
A96: 3040170400 | B96: NTC.NUTRI.NENATAL 400X24 (E) | C96: NUTRICIA | D96: REPRESENTADA | E96: ALIMENTO | F96: 24 | G96: NUTRICIA | H96: P&B | I96: INACTIVO | J96: PONCE & BENZO | M96: 400 | O96: 24 | P96: =+A96 -> 3040170400
A97: 3040190400 | B97: NTC.NUTRILON H.A. 400X24 (E) | C97: NUTRICIA | D97: REPRESENTADA | E97: ALIMENTO | F97: 24 | G97: NUTRICIA | H97: P&B | I97: INACTIVO | J97: PONCE & BENZO | M97: 400 | O97: 24 | P97: =+A97 -> 3040190400
A98: 3390110053 | B98: EQUAL POLVO(SOBRES) 50X6 | C98: EQUAL | D98: REPRESENTADA | E98: ALIMENTO | F98: 6 | G98: EQUAL | H98: P&B | I98: INACTIVO | J98: PONCE & BENZO | M98: 50 | O98: 6 | P98: =+A98 -> 3390110053
A99: 3390110203 | B99: EQUAL POLVO(SOBRES) 200X6 | C99: EQUAL | D99: REPRESENTADA | E99: ALIMENTO | F99: 6 | G99: EQUAL | H99: P&B | I99: INACTIVO | J99: PONCE & BENZO | M99: 200 | O99: 6 | P99: =+A99 -> 3390110203
A100: 3390110500 | B100: EQUAL POLVO(SOBRES)500X1 | C100: EQUAL | D100: REPRESENTADA | E100: ALIMENTO | F100: 1 | G100: EQUAL | H100: P&B | I100: INACTIVO | J100: PONCE & BENZO | M100: 500 | O100: 1 | P100: =+A100 -> 3390110500
...

Sheet ESTRUCTURA P&B - LP
A1: ID DE VENDEDOR | B1: CATEGORÍA | C1: SUBCATEGORÍA | D1: ID DE TERRITORIO | E1: ASESOR COMERCIAL | F1: GERENTE DE DISTRITO | G1: COMPAÑÍA | H1: CLIENTES CODIF | I1: VISITAS REALES | J1: UBICACIÓN FÍSICA | K1: CUBRE GEOGRÁFICAMENTE | L1: ATIENDE | M1: TELÉFONO | N1: POTENCIAL ZONA | O1: AB POT ZONA | P1: PICTURE
A2: 10 | B2: CAPITAL | C2: GTE VTA | D2: 1 | E2: MILAGROS FERNANDEZ 10 | F2: MILAGROS FERNANDEZ | G2: P&B | H2: 12 | I2: 12 | J2: Caracas | K2: Cadenas Gran Caracas - Miranda | L2: Cta Clave - Distribuidores | M2: 04143375872 | N2: ASESOR BASE | O2: AB | R2: =+Tabla1[[#This Row],[CATEGORÍA]] -> CAPITAL
A3: 50 | B3: CAPITAL | C3: GTE VTA | D3: 1 | E3: BETSY CASTRO | F3: MILAGROS FERNANDEZ | G3: P&B | H3: 56 | I3: 54 | J3: Caracas | K3: Caracas | L3: Cta Clave - Distribuidores | M3: 04242388416 | N3: ASESOR SUPERIOR | O3: AS | R3: =+Tabla1[[#This Row],[CATEGORÍA]] -> CAPITAL
A4: 57 | B4: CAPITAL | C4: GTE VTA | D4: 1 | E4: CARLOS ZURITA | F4: MILAGROS FERNANDEZ | G4: P&B | J4: Caracas | K4: CARACAS (PLAZAS) | L4: Cta Clave - Distribuidores | M4: 4241376711 | N4: ASESOR JUNIOR | O4: AB | R4: =+Tabla1[[#This Row],[CATEGORÍA]] -> CAPITAL
A5: 58 | B5: CAPITAL | C5: GTE VTA | D5: 1 | E5: CARLOS ZURITA | F5: MILAGROS FERNANDEZ | G5: P&B | J5: Caracas | K5: CARACAS (PLAZAS) | L5: Cta Clave - Distribuidores | M5: 4241376711 | N5: ASESOR JUNIOR | O5: AB | R5: =+Tabla1[[#This Row],[CATEGORÍA]] -> CAPITAL
A6: 11 | B6: CAPITAL | C6: GTE VTA | D6: 4 | E6: DUBRASKA PÉREZ 11 | F6: DUBRASKA PÉREZ | G6: P&B | H6: 41 | I6: 12 | J6: Caracas | K6: Cadenas Gran Caracas - Miranda | L6: Cta Clave - Distribuidores | M6: 04143706651 | N6: ASESOR BASE | O6: AB | R6: =+Tabla1[[#This Row],[CATEGORÍA]] -> CAPITAL
A7: 30 | B7: CAPITAL | C7: GTE VTA | D7: 1 | E7: MILAGROS FERNANDEZ 30 | F7: MILAGROS FERNANDEZ | G7: P&B | H7: 1 | I7: 1 | J7: Caracas | K7: Caracas (Farmatodo) | L7: Farmatodo | M7: 04143375872 | N7: CORPORATIVO | O7: C | R7: =+Tabla1[[#This Row],[CATEGORÍA]] -> CAPITAL
A8: 54 | B8: CAPITAL | C8: GTE VTA | D8: 1 | E8: EDUWARD MARTÍNEZ | F8: MILAGROS FERNANDEZ | G8: P&B | J8: Caracas | K8: CARACAS | M8: 4241801853 | N8: ASESOR BASE | O8: AB | R8: =+Tabla1[[#This Row],[CATEGORÍA]] -> CAPITAL
A9: 55 | B9: CAPITAL | C9: GTE VTA | D9: 1 | E9: WILLIAN FERMIN | F9: MILAGROS FERNANDEZ | G9: P&B | J9: Caracas | K9: CARACAS | M9: 4142382144 | N9: ASESOR BASE | O9: AB | R9: =+Tabla1[[#This Row],[CATEGORÍA]] -> CAPITAL
A10: 56 | B10: CAPITAL | C10: GTE VTA | D10: 1 | E10: JONATHAN FERNÁNDEZ | F10: MILAGROS FERNANDEZ | G10: P&B | J10: Caracas | K10: CARACAS | M10: 4241615018 | N10: ASESOR BASE | O10: AB | R10: =+Tabla1[[#This Row],[CATEGORÍA]] -> CAPITAL
A11: 59 | B11: CAPITAL | C11: GTE VTA | D11: 1 | E11: ELVIS RONDON | F11: MILAGROS FERNANDEZ | G11: P&B | J11: Caracas | K11: CARACAS | N11: ASESOR BASE | O11: AB
A12: 12 | B12: CENTRO-OCCIDENTE | C12: GTE VTA | D12: 4 | E12: JUAN LEÓN 12 | F12: DUBRASKA PÉREZ | G12: P&B | H12: 38 | I12: 27 | J12: Maracay | K12: Maracay | L12: Cta Clave - Distribuidores | M12: 4144631103 | N12: ASESOR PROMEDIO | O12: AP | R12: =+Tabla1[[#This Row],[CATEGORÍA]] -> CENTRO-OCCIDENTE
A13: 20 | B13: CENTRO-OCCIDENTE | C13: GTE VTA | D13: 4 | E13: JUAN LEÓN 20 | F13: DUBRASKA PÉREZ | G13: P&B | H13: 22 | I13: 20 | J13: Valencia | K13: Valencia - Carabobo | L13: Cta Clave - Distribuidores | M13: 4144631103 | N13: ASESOR PROMEDIO | O13: AP | R13: =+Tabla1[[#This Row],[CATEGORÍA]] -> CENTRO-OCCIDENTE
A14: 22 | B14: CENTRO-OCCIDENTE | C14: GTE VTA | D14: 4 | E14: DUBRASKA PÉREZ 22 | F14: DUBRASKA PÉREZ | G14: P&B | H14: 22 | I14: 21 | J14: Barquisimeto | K14: Lara | L14: Cta Clave - Distribuidores | M14: 04143706651 | N14: ASESOR BASE | O14: AB | R14: =+Tabla1[[#This Row],[CATEGORÍA]] -> CENTRO-OCCIDENTE
A15: 23 | B15: CENTRO-OCCIDENTE | C15: GTE VTA | D15: 4 | E15: MARTHA VILORIA | F15: DUBRASKA PÉREZ | G15: P&B | H15: 20 | I15: 16 | J15: Barquisimeto | K15: Lara | L15: Cta Clave - Distribuidores | M15: 04128512430 | N15: ASESOR SUPERIOR | O15: AS | R15: =+Tabla1[[#This Row],[CATEGORÍA]] -> CENTRO-OCCIDENTE
A16: 21 | B16: OCCIDENTE | C16: GTE VTA | D16: 5 | E16: ANDREINA RANGEL 21 | F16: ANDREINA RANGEL | G16: P&B | H16: 31 | I16: 16 | J16: Maracaibo | K16: Maracaibo | L16: Cta Clave - Distribuidores | M16: 04246522779 | N16: ASESOR SUPERIOR | O16: AS | R16: =+Tabla1[[#This Row],[CATEGORÍA]] -> OCCIDENTE
A17: 60 | B17: OCCIDENTE | C17: GTE VTA | D17: 5 | E17: JOSEPH PADILLA | F17: ANDREINA RANGEL | G17: P&B | H17: 12 | I17: 11 | J17: San Cristóbal | K17: San Cristóbal | L17: Cta Clave - Distribuidores | M17: 04247755055 | N17: ASESOR PROMEDIO | O17: AP | R17: =+Tabla1[[#This Row],[CATEGORÍA]] -> OCCIDENTE
A18: 61 | B18: OCCIDENTE | C18: GTE VTA | D18: 5 | E18: JOSEPH PADILLA 61 | F18: ANDREINA RANGEL | G18: P&B | H18: 17 | I18: 16 | J18: Mérida | K18: Andes (Mérida - Vigía) | L18: Cta Clave - Distribuidores | M18: 04247755055 | N18: ASESOR SUPERIOR | O18: AS | R18: =+Tabla1[[#This Row],[CATEGORÍA]] -> OCCIDENTE
A19: 62 | B19: OCCIDENTE | C19: GTE VTA | D19: 5 | E19: ANDREINA RANGEL 62 | F19: ANDREINA RANGEL | G19: P&B | H19: 31 | I19: 28 | J19: Maracaibo | K19: Maracaibo - Falcón - Costa Oriental - Trujillo | L19: Cta Clave - Distribuidores | M19: 04246522779 | N19: ASESOR SUPERIOR | O19: AS | R19: =+Tabla1[[#This Row],[CATEGORÍA]] -> OCCIDENTE
A20: 51 | B20: ORIENTE NORTE | C20: GTE VTA | D20: 6 | E20: DIANA DELGADO 51 | F20: DIANA DELGADO | G20: P&B | H20: 17 | I20: 17 | J20: Anzoátegui | K20: Barcelona - Pto La Cruz - Lecherías - El Tigre | L20: Cta Clave - Distribuidores | M20: 04148975309 | N20: ASESOR BASE | O20: AB | R20: =+Tabla1[[#This Row],[CATEGORÍA]] -> ORIENTE NORTE
A21: 52 | B21: ORIENTE SUR | C21: GTE VTA | D21: 6 | E21: DIANA DELGADO 52 | F21: DIANA DELGADO | G21: P&B | H21: 23 | I21: 18 | J21: Puerto Ordaz | K21: Puerto Ordaz - Maturín - Bolívar | L21: Cta Clave - Distribuidores | M21: 04148975309 | N21: ASESOR PROMEDIO | O21: AP | R21: =+Tabla1[[#This Row],[CATEGORÍA]] -> ORIENTE SUR
A22: 53 | B22: ZONA INSULAR | C22: GTE VTA | D22: 2 | E22: DUBRASKA PÉREZ 53 | F22: DUBRASKA PÉREZ | G22: P&B | H22: 2 | I22: 2 | J22: Margarita | K22: Margarita | L22: Cta Clave - Distribuidores | M22: 04143706651 | N22: ASESOR BASE | O22: AB | R22: =+Tabla1[[#This Row],[CATEGORÍA]] -> ZONA INSULAR
A23: 95 | B23: OFICINA | D23: 7 | E23: EVENTUALES | F23: ROSLI APONTE | G23: P&B | R23: =+Tabla1[[#This Row],[CATEGORÍA]] -> OFICINA
A24: 96 | B24: OFICINA | D24: 7 | E24: INSTITUCIONALES | F24: ROSLI APONTE | G24: P&B | J24: Caracas | K24: Caracas | L24: Institucionales | R24: =+Tabla1[[#This Row],[CATEGORÍA]] -> OFICINA
A25: 0 | B25: INACTIVO | E25: INACTIVO | F25: INACTIVO | G25: P&B | R25: =+Tabla1[[#This Row],[CATEGORÍA]] -> INACTIVO
A26: 80 | B26: OFICINA | D26: 7 | E26: D.T.T. | F26: ROSLI APONTE | G26: P&B | R26: =+Tabla1[[#This Row],[CATEGORÍA]] -> OFICINA
A27: 90 | B27: OFICINA | D27: 7 | E27: INTER-COMPAÑÍA | F27: ROSLI APONTE | G27: P&B | R27: =+Tabla1[[#This Row],[CATEGORÍA]] -> OFICINA
A28: 91 | B28: OFICINA | D28: 7 | E28: EMPLEADOS | F28: ROSLI APONTE | G28: P&B | R28: =+Tabla1[[#This Row],[CATEGORÍA]] -> OFICINA
A29: 97 | B29: OFICINA | D29: 7 | E29: PÉRDIDA EN TRÁNSITO | F29: ROSLI APONTE | G29: P&B | R29: =+Tabla1[[#This Row],[CATEGORÍA]] -> OFICINA
A30: 99 | B30: =+Tabla1[[#This Row],[ASESOR COMERCIAL]] -> E-COMMERCE | D30: 10 | E30: E-COMMERCE | F30: =+E30 -> E-COMMERCE
A31: 98 | B31: =+Tabla1[[#This Row],[ASESOR COMERCIAL]] -> INACTIVO | E31: INACTIVO | F31: =+E31 -> INACTIVO
D32: 1 | E32: CENTRO- CAPITAL | F32: LETTY DUGARTE
D33: 2 | E33: ZONA INSULAR | F33: DUBRASKA PÉREZ
D34: 3 | E34: NACIONAL - CUENTAS CLAVE | F34: DUBRASKA PÉREZ
D35: 4 | E35: CENTRO-OCCIDENTE | F35: DUBRASKA PÉREZ
D36: 5 | E36: OCCIDENTE | F36: MILAGROS FERNANDEZ
D37: 6 | E37: ORIENTE | F37: ROSLI APONTE
D38: 7 | E38: OFICINA | F38: ROSLI APONTE

Sheet Clase de Cliente
B2: Clase de cliente | C2: Clase de cliente2 | D2: Descripción
B3: 01 | C3: CAD.FARMAC | D3: CADENAS - FARMACIAS
B4: 02 | C4: CAD.PERFUM | D4: CADENAS - PERFUMERIAS
B5: 03 | C5: CAD.SUPERM | D5: CADENAS - SUPERMERCADOS
B6: 04 | C6: FARMAC.IND | D6: FARMACIAS INDEPENDIENTES
B7: 05 | C7: PERFUM.IND | D7: PERFUMERIAS INDEPENDIENTES
B8: 06 | C8: SUPERM.IND | D8: SUPERMERCADOS INDEPENDIENTES
B9: 07 | C9: DISTRIB. | D9: DISTRIBUIDOR
B10: 08 | C10: DROGUERIAS | D10: DROGUERIAS
B11: 09 | C11: INST | D11: INSTITUCIONAL
B12: 10 | C12: Z-AT.CLIEN | D12: ATENCION AL CLIENTE
B13: 11 | C13: Z-EMPLEADO | D13: EMPLEADOS
... B21: 19 | C21: CLUSTER | D21: CLUSTER

Sheet Direcciones de clientes PB
A1: Compañía | B1: Id. de vendedor | C1: Nombre de cliente | D1: Número de cliente | E1: Nivel de precio | F1: Código de dirección | G1: Descuento de cliente | H1: Id. de condiciones de pago | I1: Inactivo | J1: Fecha de creación | K1: Id. de sitio | L1: Clase de cliente | M1: Id. de plan de impuestos | N1: correo electrónico | O1: APTO
A2: P&B | B2: 61 | C2: SUCESION MEDICO DENTAL LLANOS SUCESORES DE ALFREDO ENRIQUE CALDE | D2: J503382007 | E2: 26 | F2: 61047 | G2: 0,00 | H2: 15 DIAS | I2: No | J2: 45384 | K2: VENTAS-YAG | L2: DROGUERIAS | M2: V IVA | O2: =IFERROR(VLOOKUP($D2,'CLIENTES NUEVA ID ZONA'!$A$1:$R$669,17,0),"NO") -> NO
A3: P&B | B3: 99 | C3: DISTRIBUIDORA JF 2050, C.A. | D3: J501162816 | E3: 50 | F3: 99028 | G3: 0,00 | H3: PREPAGADO | I3: No | J3: 45373 | K3: ECOMMERCE | L3: Z-AT.CLIEN | M3: V IVA | O3: =IFERROR(VLOOKUP($D3,'CLIENTES NUEVA ID ZONA'!$A$1:$R$669,17,0),"NO") -> OFICINA
A4: P&B | B4: 21 | C4: DROGUERIA INSUMEDIC, C.A | D4: J503869852 | E4: 26 | F4: 21068 | G4: 0,00 | H4: PREPAGADO | I4: No | J4: 45365 | K4: VENTAS-YAG | L4: DROGUERIAS | M4: V IVA | O4: =IFERROR(VLOOKUP($D4,'CLIENTES NUEVA ID ZONA'!$A$1:$R$669,17,0),"NO") -> NO
A5: P&B | B5: 10 | C5: CAPITALINA DE ALIMENTOS 212, C.A | D5: J501815860 | E5: 26 | F5: 95031 | G5: 0,00 | H5: PREPAGADO | I5: Sí | J5: 45364 | K5: ATD - CCS | L5: DISTRIB. | M5: V IVA | O5: =IFERROR(VLOOKUP($D5,'CLIENTES NUEVA ID ZONA'!$A$1:$R$669,17,0),"NO") -> NO
A6: P&B | B6: 95 | C6: GESTAAMBIENTAL 2023, C.A | D6: J504007200 | E6: UNICO | F6: 95019 | G6: 0,00 | H6: CONTADO COD | I6: No | J6: 45364 | K6: MP - CCS | L6: RECICLAJE | M6: V IVA | N6: comprasriovida@gmail.com | O6: =IFERROR(VLOOKUP($D6,'CLIENTES NUEVA ID ZONA'!$A$1:$R$669,17,0),"NO") -> NO
A7: P&B | B7: 99 | C7: JOHANA DEL CARMEN MIRANDA MOTA | D7: V166206479 | E7: 50 | F7: 99027 | G7: 0,00 | H7: PREPAGADO | I7: No | J7: 45356 | K7: ECOMMERCE | L7: Z-AT.CLIEN | M7: V IVA | O7: =IFERROR(VLOOKUP($D7,'CLIENTES NUEVA ID ZONA'!$A$1:$R$669,17,0),"NO") -> OFICINA
A8: P&B | B8: 21 | C8: MULTITIENDAS FARMAPLUS, C.A | D8: J501541795 | E8: 21 | F8: 21067 | G8: 0,00 | H8: CONTADO COD | I8: No | J8: 45351 | K8: VENTAS-YAG | L8: CAD.FARMAC | M8: V IVA | O8: =IFERROR(VLOOKUP($D8,'CLIENTES NUEVA ID ZONA'!$A$1:$R$669,17,0),"NO") -> SI
A9: P&B | B9: 10 | C9: VIVA SUPERCENTRO, C.A. | D9: J500449321 | E9: 21 | F9: 10124 | G9: 0,00 | H9: PREPAGADO | I9: No | J9: 45350 | K9: ATD - CCS | L9: CAD.SUPERM | M9: V IVA | O9: =IFERROR(VLOOKUP($D9,'CLIENTES NUEVA ID ZONA'!$A$1:$R$669,17,0),"NO") -> NO
A10: P&B | B10: 56 | C10: FARMAVALOR, C.A | D10: J500205805 | E10: 21 | F10: 11078 | G10: 0,00 | H10: 30 DIAS | I10: No | J10: 45349 | K10: ATD - CCS | L10: CAD.FARMAC | M10: V IVA | O10: =IFERROR(VLOOKUP($D10,'CLIENTES NUEVA ID ZONA'!$A$1:$R$669,17,0),"NO") -> NO
A11: P&B | B11: 56 | C11: FARMAVALOR, C.A | D11: J500205805 | E11: 21 | F11: 11079 | G11: 0,00 | H11: 30 DIAS | I11: No | J11: 45349 | K11: ATD - CCS | L11: CAD.FARMAC | M11: V IVA | O11: =IFERROR(VLOOKUP($D11,'CLIENTES NUEVA ID ZONA'!$A$1:$R$669,17,0),"NO") -> NO
A12: P&B | B12: 56 | C12: FARMAVALOR, C.A | D12: J500205805 | E12: 21 | F12: 11080 | G12: 0,00 | H12: 30 DIAS | I12: No | J12: 45349 | K12: ATD - CCS | L12: CAD.FARMAC | M12: V IVA | O12: =IFERROR(VLOOKUP($D12,'CLIENTES NUEVA ID ZONA'!$A$1:$R$669,17,0),"NO") -> NO
A13: P&B | B13: 99 | C13: FARMACIA JESUS DE LA MISERICORDIA., C.A. | D13: J502208070 | E13: 50 | F13: 99026 | G13: 0,00 | H13: PREPAGADO | I13: No | J13: 45349 | K13: ECOMMERCE | L13: Z-AT.CLIEN | M13: V IVA | O13: =IFERROR(VLOOKUP($D13,'CLIENTES NUEVA ID ZONA'!$A$1:$R$669,17,0),"NO") -> OFICINA
A14: P&B | B14: 53 | C14: INSIDE MARKET, C.A | D14: J401583806 | E14: 21 | F14: 53037 | G14: 0,00 | H14: 60 DIAS | I14: No | J14: 45344 | K14: ATD - CCS | L14: DISTRIB. | M14: V IVA | O14: =IFERROR(VLOOKUP($D14,'CLIENTES NUEVA ID ZONA'!$A$1:$R$669,17,0),"NO") -> SI
A15: P&B | B15: 99 | C15: ELIANA CRISTINA AMAYA DE AMAYA | D15: V183303127 | E15: 50 | F15: 99025 | G15: 0,00 | H15: PREPAGADO | I15: No | J15: 45343 | K15: ECOMMERCE | L15: Z-AT.CLIEN | M15: V IVA | O15: =IFERROR(VLOOKUP($D15,'CLIENTES NUEVA ID ZONA'!$A$1:$R$669,17,0),"NO") -> OFICINA
A16: P&B | B16: 99 | C16: DIGNA JANETH RAMOS GARCIA | D16: V156160616 | E16: 50 | F16: 99024 | G16: 0,00 | H16: PREPAGADO | I16: No | J16: 45341 | K16: ECOMMERCE | L16: Z-AT.CLIEN | M16: V IVA | O16: =IFERROR(VLOOKUP($D16,'CLIENTES NUEVA ID ZONA'!$A$1:$R$669,17,0),"NO") -> OFICINA
A17: P&B | B17: 10 | C17: SOL BRILLANTE DE AMAZONAS C.A | D17: J504689700 | E17: 21 | F17: 10211 | G17: 0,00 | H17: 30 DIAS | I17: No | J17: 45337 | K17: ATD - CCS | L17: CAD.SUPERM | M17: V IVA | O17: =IFERROR(VLOOKUP($D17,'CLIENTES NUEVA ID ZONA'!$A$1:$R$669,17,0),"NO") -> NO
A18: P&B | B18: 10 | C18: SOL BRILLANTE DE AMAZONAS C.A | D18: J504689700 | E18: 21 | F18: 10212 | G18: 0,00 | H18: 30 DIAS | I18: No | J18: 45337 | K18: ATD - CCS | L18: CAD.SUPERM | M18: V IVA | O18: =IFERROR(VLOOKUP($D18,'CLIENTES NUEVA ID ZONA'!$A$1:$R$669,17,0),"NO") -> NO
... A21: P&B | B21: 10 | C21: SOL BRILLANTE DE AMAZONAS C.A | D21: J504689700 | E21: 21 | F21: 10215 | G21: 0,00 | H21: 30 DIAS | I21: No | J21: 45337 | K21: VENTAS-YAG | L21: CAD.SUPERM | M21: V IVA | O21: =IFERROR(VLOOKUP($D21,'CLIENTES NUEVA ID ZONA'!$A$1:$R$669,17,0),"NO") -> NO
A22: P&B | B22: 51 | C22: ZAKIPHARMA, C.A. | D22: J500976160 | E22: 26 | F22: 51091 | G22: 0,00 | H22: 10 DIAS | I22: No | J22: 45336 | K22: ATD - CCS | L22: DROGUERIAS | M22: V IVA | N22: precios@cataniaautomercado.com | O22: =IFERROR(VLOOKUP($D22,'CLIENTES NUEVA ID ZONA'!$A$1:$R$669,17,0),"NO") -> NO
A23: P&B | B23: 56 | C23: ISAGEN MEDICAL, C.A. | D23: J299485250 | E23: 21 | F23: 56000 | G23: 0,00 | H23: PREPAGADO | I23: No | J23: 45331 | K23: ATD - CCS | L23: PERFUM.IND | M23: V IVA | N23: precios@cataniaautomercado.com | O23: =IFERROR(VLOOKUP($D23,'CLIENTES NUEVA ID ZONA'!$A$1:$R$669,17,0),"NO") -> NO
A24: P&B | B24: 99 | C24: ADRIANA PEREIRO NEGRO | D24: V117414546 | E24: 50 | F24: 99023 | G24: 0,00 | H24: PREPAGADO | I24: No | J24: 45331 | K24: ECOMMERCE | L24: Z-AT.CLIEN | M24: V IVA | N24: precios@cataniaautomercado.com | O24: =IFERROR(VLOOKUP($D24,'CLIENTES NUEVA ID ZONA'!$A$1:$R$669,17,0),"NO") -> OFICINA
A25: P&B | B25: 99 | C25: ERIC ARRIVILLEGA | D25: V166694465 | E25: 50 | F25: 99022 | G25: 0,00 | H25: PREPAGADO | I25: No | J25: 45331 | K25: ECOMMERCE | L25: Z-AT.CLIEN | M25: V IVA | O25: =IFERROR(VLOOKUP($D25,'CLIENTES NUEVA ID ZONA'!$A$1:$R$669,17,0),"NO") -> OFICINA
A26: P&B | B26: 99 | C26: DANIELA ANDREINA EGURROLA DIAZ | D26: V207915994 | E26: 50 | F26: 99021 | G26: 0,00 | H26: PREPAGADO | I26: No | J26: 45331 | K26: ECOMMERCE | L26: Z-AT.CLIEN | M26: V IVA | O26: =IFERROR(VLOOKUP($D26,'CLIENTES NUEVA ID ZONA'!$A$1:$R$669,17,0),"NO") -> OFICINA
A27: P&B | B27: 99 | C27: MILAGRO ISABEL SALCEDO SALCEDO | D27: V263429687 | E27: 50 | F27: 99020 | G27: 0,00 | H27: PREPAGADO | I27: No | J27: 45328 | K27: ECOMMERCE | L27: Z-AT.CLIEN | M27: V IVA | O27: =IFERROR(VLOOKUP($D27,'CLIENTES NUEVA ID ZONA'!$A$1:$R$669,17,0),"NO") -> OFICINA
A28: P&B | B28: 99 | C28: MARIA ALEJANDRA ROJAS DOMINGUEZ | D28: V225587988 | E28: 50 | F28: 99019 | G28: 0,00 | H28: PREPAGADO | I28: No | J28: 45322 | K28: ECOMMERCE | L28: Z-AT.CLIEN | M28: V IVA | N28: distribuidorainsumedico@gmail.com | O28: =IFERROR(VLOOKUP($D28,'CLIENTES NUEVA ID ZONA'!$A$1:$R$669,17,0),"NO") -> OFICINA
A29: P&B | B29: 99 | C29: QUIROPEDIA BLANCO C.A | D29: J002225963 | E29: 50 | F29: 99018 | G29: 0,00 | H29: PREPAGADO | I29: No | J29: 45317 | K29: ECOMMERCE | L29: Z-AT.CLIEN | M29: V IVA | O29: =IFERROR(VLOOKUP($D29,'CLIENTES NUEVA ID ZONA'!$A$1:$R$669,17,0),"NO") -> NO
A30: P&B | B30: 99 | C30: CLINICAS SOLUMEDICA, C.A. | D30: J500839014 | E30: 50 | F30: 99017 | G30: 0,00 | H30: PREPAGADO | I30: No | J30: 45317 | K30: ECOMMERCE | L30: Z-AT.CLIEN | M30: V IVA | O30: =IFERROR(VLOOKUP($D30,'CLIENTES NUEVA ID ZONA'!$A$1:$R$669,17,0),"NO") -> OFICINA
A31: P&B | B31: 99 | C31: INVERSIONES BERTMAR 8986, C.A | D31: J501693382 | E31: 50 | F31: 99016 | G31: 0,00 | H31: PREPAGADO | I31: No | J31: 45314 | K31: ECOMMERCE | L31: Z-AT.CLIEN | M31: V IVA | O31: =IFERROR(VLOOKUP($D31,'CLIENTES NUEVA ID ZONA'!$A$1:$R$669,17,0),"NO") -> OFICINA
A32: P&B | B32: 99 | C32: EMILIO LEON | D32: V03979230 | E32: 50 | F32: 99015 | G32: 0,00 | H32: PREPAGADO | I32: No | J32: 45310 | K32: ECOMMERCE | L32: Z-AT.CLIEN | M32: V IVA | N32: recibidores.monica@plansuarez.com.ve | O32: =IFERROR(VLOOKUP($D32,'CLIENTES NUEVA ID ZONA'!$A$1:$R$669,17,0),"NO") -> OFICINA
A33: P&B | B33: 99 | C33: JULIO CESAR GARCIA ZERPA | D33: V042141190 | E33: 50 | F33: 99014 | G33: 0,00 | H33: PREPAGADO | I33: No | J33: 45308 | K33: ECOMMERCE | L33: Z-AT.CLIEN | M33: V IVA | O33: =IFERROR(VLOOKUP($D33,'CLIENTES NUEVA ID ZONA'!$A$1:$R$669,17,0),"NO") -> OFICINA
A34: P&B | B34: 99 | C34: JENIFFER RUIZ | D34: V26770964 | E34: 50 | F34: 99013 | G34: 0,00 | H34: PREPAGADO | I34: No | J34: 45275 | K34: ECOMMERCE | L34: Z-AT.CLIEN | M34: V IVA | O34: =IFERROR(VLOOKUP($D34,'CLIENTES NUEVA ID ZONA'!$A$1:$R$669,17,0),"NO") -> OFICINA
A35: P&B | B35: 53 | C35: INSIDE MARKET, C.A | D35: J401583806 | E35: 21 | F35: 53036 | G35: 0,00 | H35: 60 DIAS | I35: No | J35: 45274 | K35: ATD - CCS | L35: DISTRIB. | M35: V IVA | N35: comprasdis.cia@gmail.com | O35: =IFERROR(VLOOKUP($D35,'CLIENTES NUEVA ID ZONA'!$A$1:$R$669,17,0),"NO") -> SI
A36: P&B | B36: 50 | C36: DISTRITOTAL 1, C.A | D36: J504465429 | E36: 20 | F36: 50096 | G36: 0,00 | H36: 21 DIAS | I36: No | J36: 45271 | K36: ATD - CCS | L36: DISTRIB. | M36: V IVA | O36: =IFERROR(VLOOKUP($D36,'CLIENTES NUEVA ID ZONA'!$A$1:$R$669,17,0),"NO") -> SI
A37: P&B | B37: 53 | C37: INSIDE MARKET, C.A | D37: J401583806 | E37: 21 | F37: 53035 | G37: 0,00 | H37: 60 DIAS | I37: No | J37: 45267 | K37: VENTAS-YAG | L37: DISTRIB. | M37: V IVA | O37: =IFERROR(VLOOKUP($D37,'CLIENTES NUEVA ID ZONA'!$A$1:$R$669,17,0),"NO") -> SI
A38: P&B | B38: 99 | C38: MARIA EMILIA CIRA | D38: V16532501 | E38: 50 | F38: 99012 | G38: 0,00 | H38: PREPAGADO | I38: No | J38: 45259 | K38: ECOMMERCE | L38: Z-AT.CLIEN | M38: V IVA | O38: =IFERROR(VLOOKUP($D38,'CLIENTES NUEVA ID ZONA'!$A$1:$R$669,17,0),"NO") -> OFICINA
A39: P&B | B39: 50 | C39: STEPHEN CHRISTIAN SCHUBERT | D39: E813628760 | F39: 50095 | G39: 0,00 | I39: No | J39: 45252 | K39: ATD - CCS | L39: FARMAC.IND | M39: V IVA | O39: =IFERROR(VLOOKUP($D39,'CLIENTES NUEVA ID ZONA'!$A$1:$R$669,17,0),"NO") -> NO
A40: P&B | B40: 53 | C40: INSIDE MARKET, C.A | D40: J401583806 | E40: 21 | F40: 53034 | G40: 0,00 | H40: 60 DIAS | I40: No | J40: 45246 | K40: ATD - CCS | L40: DISTRIB. | M40: V IVA | O40: =IFERROR(VLOOKUP($D40,'CLIENTES NUEVA ID ZONA'!$A$1:$R$669,17,0),"NO") -> SI
A41: P&B | B41: 99 | C41: DROGUERIA FARMA MISTICA, C.A | D41: J309801228 | E41: 50 | F41: 99011 | G41: 0,00 | H41: CONTADO COD | I41: No | J41: 45243 | K41: ECOMMERCE | L41: Z-AT.CLIEN | M41: V IVA | N41: compras@farmaceutica24.com | O41: =IFERROR(VLOOKUP($D41,'CLIENTES NUEVA ID ZONA'!$A$1:$R$669,17,0),"NO") -> OFICINA
A42: P&B | B42: 51 | C42: DISTRIBUIDORA JM NUEVA ESPARTA, C.A | D42: J501024219 | E42: 20 | F42: 54054 | G42: 0,00 | H42: PREPAGADO | I42: No | J42: 45240 | K42: VENTAS-YAG | L42: DISTRIB. | M42: V IVA E | N42: acobo@drogueriabaron.com.ve | O42: =IFERROR(VLOOKUP($D42,'CLIENTES NUEVA ID ZONA'!$A$1:$R$669,17,0),"NO") -> NO
A43: P&B | B43: 99 | C43: YADIRA JIMÉNEZ | D43: V21465942 | E43: 50 | F43: 99010 | G43: 0,00 | H43: PREPAGADO | I43: No | J43: 45237 | K43: ECOMMERCE | L43: Z-AT.CLIEN | M43: V IVA | O43: =IFERROR(VLOOKUP($D43,'CLIENTES NUEVA ID ZONA'!$A$1:$R$669,17,0),"NO") -> NO
A44: P&B | B44: 95 | C44: KAREN URBAEZ | D44: V271593518 | E44: 21 | F44: 95030 | G44: 0,00 | H44: CONTADO COD | I44: No | J44: 45236 | K44: VENTCAMERC | L44: Z-EMPLEADO | M44: V IVA | O44: =IFERROR(VLOOKUP($D44,'CLIENTES NUEVA ID ZONA'!$A$1:$R$669,17,0),"NO") -> SI
A45: P&B | B45: 58 | C45: AUTOMERCADOS PLAZA'S, C.A. | D45: J306725024 | E45: 21 | F45: 10123 | G45: 0,00 | H45: 45 DIAS | I45: No | J45: 45230 | K45: ATD - CCS | L45: CAD.SUPERM | M45: V IVA | O45: =IFERROR(VLOOKUP($D45,'CLIENTES NUEVA ID ZONA'!$A$1:$R$669,17,0),"NO") -> SI
A46: P&B | B46: 10 | C46: IMPORTADORA DE ALIMENTOS BOLONIA, C.A | D46: J405638311 | E46: 26 | F46: 11077 | G46: 0,00 | H46: PREPAGADO | I46: No | J46: 45226 | K46: ATD - CCS | L46: DISTRIB. | M46: V IVA | N46: almacenacarigua@yonlui.com | O46: =IFERROR(VLOOKUP($D46,'CLIENTES NUEVA ID ZONA'!$A$1:$R$669,17,0),"NO") -> SI
A47: P&B | B47: 50 | C47: IMPORTACIONES LUCKY FENG, C.A. | D47: J500389248 | E47: 20 | F47: 50093 | G47: 0,00 | H47: PREPAGADO | I47: No | J47: 45226 | K47: ATD - CCS | L47: DROGUERIAS | M47: V IVA | N47: mromero@dromarko.com | O47: =IFERROR(VLOOKUP($D47,'CLIENTES NUEVA ID ZONA'!$A$1:$R$669,17,0),"NO") -> NO
A48: P&B | B48: 62 | C48: MARCAS MASIVAS S.A. | D48: J500577702 | E48: 20 | F48: 62056 | G48: 0,00 | H48: 15 DIAS | I48: No | J48: 45226 | K48: VENTAS-YAG | L48: DISTRIB. | M48: V IVA | N48: compras@drogueria365.com | O48: =IFERROR(VLOOKUP($D48,'CLIENTES NUEVA ID ZONA'!$A$1:$R$669,17,0),"NO") -> SI
A49: P&B | B49: 50 | C49: INVERSIONES AREANSEB 2018, C.A. | D49: J412192213 | E49: 21 | F49: 50092 | G49: 0,00 | H49: 15 DIAS | I49: No | J49: 45224 | K49: ATD - CCS | L49: DISTRIB. | M49: V IVA | N49: comprasguanare@yonlui.com | O49: =IFERROR(VLOOKUP($D49,'CLIENTES NUEVA ID ZONA'!$A$1:$R$669,17,0),"NO") -> NO
A50: P&B | B50: 50 | C50: BIG BANG IMPORT, C.A | D50: J501317623 | E50: 20 | F50: 50094 | G50: 0,00 | H50: 15 DIAS | I50: No | J50: 45222 | K50: ATD - CCS | L50: DISTRIB. | M50: V IVA | O50: =IFERROR(VLOOKUP($D50,'CLIENTES NUEVA ID ZONA'!$A$1:$R$669,17,0),"NO") -> NO
A51: P&B | B51: 99 | C51: DROGUERIA PHARMAHEALTHY, C.A | D51: J501066418 | E51: 50 | F51: 99009 | G51: 0,00 | H51: PREPAGADO | I51: No | J51: 45219 | K51: ECOMMERCE | L51: Z-AT.CLIEN | M51: V IVA | O51: =IFERROR(VLOOKUP($D51,'CLIENTES NUEVA ID ZONA'!$A$1:$R$669,17,0),"NO") -> OFICINA
A52: P&B | B52: 95 | C52: CORPORACION INDUSTRIAL PANA-VEN, C.A | D52: J297259422 | E52: 21 | F52: 95029 | G52: 0,00 | H52: PREPAGADO | I52: No | J52: 45218 | K52: SERV | L52: DISTRIB. | M52: V IVA | O52: =IFERROR(VLOOKUP($D52,'CLIENTES NUEVA ID ZONA'!$A$1:$R$669,17,0),"NO") -> OFICINA
A53: P&B | B53: 52 | C53: DISTRIBUIDORA F&S, C.A. | D53: J409266850 | E53: 20 | F53: 52110 | G53: 0,00 | H53: PREPAGADO | I53: No | J53: 45218 | K53: VENTAS-YAG | L53: DISTRIB. | M53: V IVA | O53: =IFERROR(VLOOKUP($D53,'CLIENTES NUEVA ID ZONA'!$A$1:$R$669,17,0),"NO") -> NO
A54: P&B | B54: 10 | C54: CORPORACION LETIMAR, C.A. | D54: J410060964 | E54: 20 | F54: 10122 | G54: 0,00 | H54: PREPAGADO | I54: No | J54: 45215 | K54: ATD - CCS | L54: DISTRIB. | M54: V IVA | O54: =IFERROR(VLOOKUP($D54,'CLIENTES NUEVA ID ZONA'!$A$1:$R$669,17,0),"NO") -> NO
A55: P&B | B55: 11 | C55: FARMACIA 4B, C.A. | D55: J296913757 | E55: 01 | F55: 11076 | G55: 0,00 | H55: 15 DIAS | I55: No | J55: 45204 | K55: VENTAS-YAG | L55: CAD.FARMAC | M55: V IVA | O55: =IFERROR(VLOOKUP($D55,'CLIENTES NUEVA ID ZONA'!$A$1:$R$669,17,0),"NO") -> NO
A56: P&B | B56: 12 | C56: DISTUCA, C.A. | D56: J313167142 | E56: 21 | F56: 12043 | G56: 0,00 | H56: PREPAGADO | I56: No | J56: 45198 | K56: VENTAS-YAG | L56: DISTRIB. | M56: V IVA | O56: =IFERROR(VLOOKUP($D56,'CLIENTES NUEVA ID ZONA'!$A$1:$R$669,17,0),"NO") -> NO
A57: P&B | B57: 20 | C57: REPRESENTACIONES MEDICA R.Y. 2015, C.A | D57: J406114588 | E57: 26 | F57: 20110 | G57: 0,00 | H57: PREPAGADO | I57: No | J57: 45198 | K57: VENTAS-YAG | L57: DROGUERIAS | M57: V IVA | O57: =IFERROR(VLOOKUP($D57,'CLIENTES NUEVA ID ZONA'!$A$1:$R$669,17,0),"NO") -> NO
A58: P&B | B58: 10 | C58: SUPERMERCADO RIO VIDA C.A | D58: J500585039 | E58: 21 | F58: 10121 | G58: 0,00 | H58: 21 DIAS | I58: No | J58: 45195 | K58: ATD - CCS | L58: CAD.SUPERM | M58: V IVA | N58: inversionesda.adm2@gmail.com | O58: =IFERROR(VLOOKUP($D58,'CLIENTES NUEVA ID ZONA'!$A$1:$R$669,17,0),"NO") -> NO
A59: P&B | B59: 98 | C59: GRUPO SURAKI, C.A | D59: J403047596 | E59: 26 | F59: 61046 | G59: 0,00 | H59: PREPAGADO | I59: No | J59: 45189 | K59: VENTAS-YAG | L59: DISTRIB. | M59: V IVA | N59: granabastogirasol@gmail.com | O59: =IFERROR(VLOOKUP($D59,'CLIENTES NUEVA ID ZONA'!$A$1:$R$669,17,0),"NO") -> NO
A60: P&B | B60: 99 | C60: YMARA JIMÉNEZ | D60: V10283333 | E60: 50 | F60: 99008 | G60: 0,00 | H60: PREPAGADO | I60: No | J60: 45182 | K60: ECOMMERCE | L60: Z-AT.CLIEN | M60: V IVA | N60: granabastogirasol@gmail.com | O60: =IFERROR(VLOOKUP($D60,'CLIENTES NUEVA ID ZONA'!$A$1:$R$669,17,0),"NO") -> NO
A61: P&B | B61: 58 | C61: AUTOMERCADOS PLAZA'S, C.A. | D61: J306725024 | E61: 21 | F61: 10120 | G61: 0,00 | H61: 45 DIAS | I61: No | J61: 45180 | K61: ATD - CCS | L61: CAD.SUPERM | M61: V IVA | N61: granabastogirasol@gmail.com | O61: =IFERROR(VLOOKUP($D61,'CLIENTES NUEVA ID ZONA'!$A$1:$R$669,17,0),"NO") -> SI
A62: P&B | B62: 99 | C62: DROGUERIA ROIPHARMA, C.A. | D62: J412753355 | E62: 50 | F62: 99007 | G62: 0,00 | H62: PREPAGADO | I62: No | J62: 45175 | K62: ECOMMERCE | L62: DROGUERIAS | M62: V IVA | N62: granabastogirasol@gmail.com | O62: =IFERROR(VLOOKUP($D62,'CLIENTES NUEVA ID ZONA'!$A$1:$R$669,17,0),"NO") -> OFICINA
A63: P&B | B63: 99 | C63: SABUEZOS PETSHOP VENEZUELA S.P.V 2020, C.A. | D63: J500823495 | E63: 50 | F63: 99006 | G63: 0,00 | H63: PREPAGADO | I63: No | J63: 45174 | K63: ECOMMERCE | L63: Z-AT.CLIEN | M63: V IVA | N63: mromero@dromarko.com | O63: =IFERROR(VLOOKUP($D63,'CLIENTES NUEVA ID ZONA'!$A$1:$R$669,17,0),"NO") -> NO
A64: P&B | B64: 98 | C64: CORPORACION DE COMERCIO Y SUMINISTRO SOCIALISTA, S.A. | D64: G200093013 | E64: 01 | F64: 98002 | G64: 0,00 | H64: CONTADO COD | I64: Sí | J64: 45170 | K64: ATD - CCS | L64: DISTRIB. | M64: V IVA | N64: yj888ca@gmail.com | O64: =IFERROR(VLOOKUP($D64,'CLIENTES NUEVA ID ZONA'!$A$1:$R$669,17,0),"NO") -> NO
A65: P&B | B65: 98 | C65: ALMACENADORA DEL CENTRO, C.A. | D65: G200100192 | E65: 01 | F65: 98003 | G65: 0,00 | H65: CONTADO COD | I65: Sí | J65: 45170 | K65: VENTAS-YAG | L65: DISTRIB. | M65: V IVA | O65: =IFERROR(VLOOKUP($D65,'CLIENTES NUEVA ID ZONA'!$A$1:$R$669,17,0),"NO") -> NO
A66: P&B | B66: 98 | C66: ALIMENTOS LA GIRALDA, C.A. | D66: J001626867 | E66: 01 | F66: 98004 | G66: 0,00 | H66: CONTADO COD | I66: Sí | J66: 45170 | K66: VENTAS-YAG | L66: DISTRIB. | M66: V IVA | O66: =IFERROR(VLOOKUP($D66,'CLIENTES NUEVA ID ZONA'!$A$1:$R$669,17,0),"NO") -> NO
A67: P&B | B67: 98 | C67: MAKRO COMERCIALIZADORA, S.A. | D67: J003192350 | E67: 01 | F67: 98005 | G67: 0,00 | H67: CONTADO COD | I67: Sí | J67: 45170 | K67: YAG-CSS | L67: MAYORISTAS | M67: V IVA | O67: =IFERROR(VLOOKUP($D67,'CLIENTES NUEVA ID ZONA'!$A$1:$R$669,17,0),"NO") -> NO
A68: P&B | B68: 98 | C68: INVERSIONES MERCATRADONA, C.A. | D68: J003253308 | E68: 01 | F68: 98006 | G68: 0,00 | H68: CONTADO COD | I68: Sí | J68: 45170 | K68: VENTAS-YAG | L68: SUPERM.IND | M68: V IVA | O68: =IFERROR(VLOOKUP($D68,'CLIENTES NUEVA ID ZONA'!$A$1:$R$669,17,0),"NO") -> NO
A69: P&B | B69: 98 | C69: MAYOR Y DISTRIBUCIONES "DON PEPE" C.A. | D69: J090330615 | E69: 01 | F69: 98007 | G69: 0,00 | H69: CONTADO COD | I69: Sí | J69: 45170 | K69: VENTAS-YAG | L69: DISTRIB. | M69: V IVA | O69: =IFERROR(VLOOKUP($D69,'CLIENTES NUEVA ID ZONA'!$A$1:$R$669,17,0),"NO") -> NO
A70: P&B | B70: 98 | C70: COMERCIALIZADORA DURACENTRO, C.A | D70: J294014518 | E70: 01 | F70: 98008 | G70: 0,00 | H70: CONTADO COD | I70: Sí | J70: 45170 | K70: VENTAS-YAG | L70: DISTRIB. | M70: V IVA | N70: colvidca@gmail.com | O70: =IFERROR(VLOOKUP($D70,'CLIENTES NUEVA ID ZONA'!$A$1:$R$669,17,0),"NO") -> NO
A71: P&B | B71: 98 | C71: PICKING, C.A. | D71: J294253610 | E71: 01 | F71: 98009 | G71: 0,00 | H71: CONTADO COD | I71: Sí | J71: 45170 | K71: VENTAS-YAG | L71: Z-INTERCOM | M71: V IVA | O71: =IFERROR(VLOOKUP($D71,'CLIENTES NUEVA ID ZONA'!$A$1:$R$669,17,0),"NO") -> NO
A72: P&B | B72: 98 | C72: WILLIAM ALBERTO CALDERON GUEDEZ | D72: V107193118 | E72: 26 | F72: 61045 | G72: 0,00 | H72: PREPAGADO | I72: No | J72: 45168 | K72: VENTAS-YAG | L72: DROGUERIAS | M72: V IVA | O72: =IFERROR(VLOOKUP($D72,'CLIENTES NUEVA ID ZONA'!$A$1:$R$669,17,0),"NO") -> NO
A73: P&B | B73: 61 | C73: COMERCIALIZADORA LA BREGADORA C.A. | D73: J294691226 | E73: 26 | F73: 61044 | G73: 0,00 | H73: 15 DIAS | I73: No | J73: 45167 | K73: VENTAS-YAG | L73: DISTRIB. | M73: V IVA | O73: =IFERROR(VLOOKUP($D73,'CLIENTES NUEVA ID ZONA'!$A$1:$R$669,17,0),"NO") -> SI
A74: P&B | B74: 20 | C74: CATANIA HIPERMERCADO, C.A. | D74: J312768320 | E74: 21 | F74: 20107 | G74: 0,00 | H74: 30 DIAS | I74: No | J74: 45162 | K74: VENTAS-YAG | L74: CAD.SUPERM | M74: V IVA | O74: =IFERROR(VLOOKUP($D74,'CLIENTES NUEVA ID ZONA'!$A$1:$R$669,17,0),"NO") -> SI
A75: P&B | B75: 20 | C75: CATANIA HIPERMERCADO, C.A. | D75: J312768320 | E75: 21 | F75: 20108 | G75: 0,00 | H75: 30 DIAS | I75: No | J75: 45162 | K75: VENTAS-YAG | L75: CAD.SUPERM | M75: V IVA | O75: =IFERROR(VLOOKUP($D75,'CLIENTES NUEVA ID ZONA'!$A$1:$R$669,17,0),"NO") -> SI
A76: P&B | B76: 20 | C76: CATANIA HIPERMERCADO, C.A. | D76: J312768320 | E76: 21 | F76: 20109 | G76: 0,00 | H76: 30 DIAS | I76: No | J76: 45162 | K76: VENTAS-YAG | L76: CAD.SUPERM | M76: V IVA | O76: =IFERROR(VLOOKUP($D76,'CLIENTES NUEVA ID ZONA'!$A$1:$R$669,17,0),"NO") -> SI
A77: P&B | B77: 53 | C77: INSIDE MARKET, C.A | D77: J401583806 | E77: 21 | F77: 53033 | G77: 0,00 | H77: 60 DIAS | I77: No | J77: 45149 | K77: VENTAS-YAG | L77: DISTRIB. | M77: V IVA E | O77: =IFERROR(VLOOKUP($D77,'CLIENTES NUEVA ID ZONA'!$A$1:$R$669,17,0),"NO") -> SI
A78: P&B | B78: 99 | C78: DIANA DELGADO | D78: V10223983 | E78: 50 | F78: 99004 | G78: 0,00 | H78: PREPAGADO | I78: No | J78: 45138 | K78: ECOMMERCE | L78: Z-AT.CLIEN | M78: V IVA | O78: =IFERROR(VLOOKUP($D78,'CLIENTES NUEVA ID ZONA'!$A$1:$R$669,17,0),"NO") -> NO
A79: P&B | B79: 99 | C79: ANDREINA RANGEL | D79: V14863450 | E79: 50 | F79: 99005 | G79: 0,00 | H79: PREPAGADO | I79: No | J79: 45138 | K79: ECOMMERCE | L79: Z-AT.CLIEN | M79: V IVA | O79: =IFERROR(VLOOKUP($D79,'CLIENTES NUEVA ID ZONA'!$A$1:$R$669,17,0),"NO") -> NO
A80: P&B | B80: 60 | C80: DIEGO ANDRE COLMENARES ROLON | D80: V171092171 | E80: 26 | F80: 62055 | G80: 0,00 | H80: 15 DIAS | I80: No | J80: 45135 | K80: VENTAS-YAG | L80: DISTRIB. | M80: V IVA | O80: =IFERROR(VLOOKUP($D80,'CLIENTES NUEVA ID ZONA'!$A$1:$R$669,17,0),"NO") -> NO
A81: P&B | B81: 53 | C81: INSIDE MARKET, C.A | D81: J401583806 | E81: 21 | F81: 53030 | G81: 0,00 | H81: 60 DIAS | I81: No | J81: 45132 | K81: ATD - CCS | L81: DISTRIB. | M81: V IVA | O81: =IFERROR(VLOOKUP($D81,'CLIENTES NUEVA ID ZONA'!$A$1:$R$669,17,0),"NO") -> SI
A82: P&B | B82: 53 | C82: INSIDE MARKET, C.A | D82: J401583806 | E82: 21 | F82: 53031 | G82: 0,00 | H82: 60 DIAS | I82: No | J82: 45132 | K82: VENTAS-YAG | L82: DISTRIB. | M82: V IVA | O82: =IFERROR(VLOOKUP($D82,'CLIENTES NUEVA ID ZONA'!$A$1:$R$669,17,0),"NO") -> SI
... A90: P&B | B90: 99 | C90: SIMON RODRIGUEZ | D90: V15662389 | E90: 50 | F90: 99002 | G90: 0,00 | H90: PREPAGADO | I90: No | J90: 45113 | K90: ECOMMERCE | L90: Z-AT.CLIEN | M90: V IVA | O90: =IFERROR(VLOOKUP($D90,'CLIENTES NUEVA ID ZONA'!$A$1:$R$669,17,0),"NO") -> NO
A91: P&B | B91: 99 | C91: MARIA AZUAJE | D91: V24409520 | E91: 50 | F91: 99003 | G91: 0,00 | H91: PREPAGADO | I91: No | J91: 45113 | K91: ECOMMERCE | L91: Z-AT.CLIEN | M91: V IVA | N91: drofarzuca@gmail.com | O91: =IFERROR(VLOOKUP($D91,'CLIENTES NUEVA ID ZONA'!$A$1:$R$669,17,0),"NO") -> NO
A92: P&B | B92: 99 | C92: AGDA URQUIOLA | D92: V15470575 | E92: 50 | F92: 99000 | G92: 0,00 | H92: PREPAGADO | I92: No | J92: 45110 | K92: ECOMMERCE | L92: Z-AT.CLIEN | M92: V IVA | O92: =IFERROR(VLOOKUP($D92,'CLIENTES NUEVA ID ZONA'!$A$1:$R$669,17,0),"NO") -> NO
A93: P&B | B93: 21 | C93: DROGUERIA FARMACEUTICA 24, C.A | D93: J409767205 | E93: 26 | F93: 21066 | G93: 0,00 | H93: 21 DIAS | I93: No | J93: 45104 | K93: VENTAS-YAG | L93: DROGUERIAS | M93: V IVA | N93: ventasloari214@gmail.com | O93: =IFERROR(VLOOKUP($D93,'CLIENTES NUEVA ID ZONA'!$A$1:$R$669,17,0),"NO") -> SI
A94: P&B | B94: 50 | C94: DROGUERIA BARON PHARMA 1504, C.A | D94: J502644610 | E94: 26 | F94: 50091 | G94: 0,00 | H94: PREPAGADO | I94: No | J94: 45104 | K94: ATD - CCS | L94: DROGUERIAS | M94: V IVA | N94: ychacin@farmacia72.com.ve | O94: =IFERROR(VLOOKUP($D94,'CLIENTES NUEVA ID ZONA'!$A$1:$R$669,17,0),"NO") -> NO
A95: P&B | B95: 54 | C95: FARMACIA LCT 18, C.A | D95: J502022120 | E95: 01 | F95: 55035 | G95: 0,00 | H95: 15 DIAS | I95: No | J95: 45099 | K95: ATD - CCS | L95: CAD.FARMAC | M95: V IVA | N95: disermatc@gmail.com | O95: =IFERROR(VLOOKUP($D95,'CLIENTES NUEVA ID ZONA'!$A$1:$R$669,17,0),"NO") -> SI
A96: P&B | B96: 10 | C96: FORUM SUPER MAYORISTA, C.A | D96: J500199759 | E96: 21 | F96: 10118 | G96: 0,00 | H96: 30 DIAS | I96: No | J96: 45090 | K96: ATD - CCS | L96: MAYORISTAS | M96: V IVA | N96: nsoler@farmavalorve.com | O96: =IFERROR(VLOOKUP($D96,'CLIENTES NUEVA ID ZONA'!$A$1:$R$669,17,0),"NO") -> NO
A97: P&B | B97: 52 | C97: CORPORACION GRUPO RORAIMA II, C.A. | D97: J502375856 | E97: 20 | F97: 52109 | G97: 0,00 | H97: 15 DIAS | I97: No | J97: 45084 | K97: VENTAS-YAG | L97: DISTRIB. | M97: V IVA | O97: =IFERROR(VLOOKUP($D97,'CLIENTES NUEVA ID ZONA'!$A$1:$R$669,17,0),"NO") -> NO
A98: P&B | B98: 23 | C98: DISTRIBUIDORA YONLUI, C.A. | D98: J296889139 | E98: 20 | F98: 23047 | G98: 0,00 | H98: 15 DIAS | I98: No | J98: 45077 | K98: VENTAS-YAG | L98: DISTRIB. | M98: V IVA | O98: =IFERROR(VLOOKUP($D98,'CLIENTES NUEVA ID ZONA'!$A$1:$R$669,17,0),"NO") -> SI
A99: P&B | B99: 21 | C99: DROGUERIA DROMARKO, C.A. | D99: J408567709 | E99: 26 | F99: 21060 | G99: 0,00 | H99: 21 DIAS | I99: No | J99: 45076 | K99: ATD - CCS | L99: DROGUERIAS | M99: V IVA | O99: =IFERROR(VLOOKUP($D99,'CLIENTES NUEVA ID ZONA'!$A$1:$R$669,17,0),"NO") -> SI
A100: P&B | B100: 21 | C100: DROGUERIA 365, C.A | D100: J501933669 | E100: 26 | F100: 21062 | G100: 0,00 | H100: 15 DIAS | I100: No | J100: 45076 | K100: VENTAS-YAG | L100: DROGUERIAS | M100: V IVA | O100: =IFERROR(VLOOKUP($D100,'CLIENTES NUEVA ID ZONA'!$A$1:$R$669,17,0),"NO") -> SI
A101: P&B | B101: 23 | C101: DISTRIBUIDORA YONLUI LOS LLANOS, C.A. | D101: J500511736 | E101: 20 | F101: 23046 | G101: 0,00 | H101: 15 DIAS | I101: No | J101: 45072 | K101: VENTAS-YAG | L101: DISTRIB. | M101: V IVA | O101: =IFERROR(VLOOKUP($D101,'CLIENTES NUEVA ID ZONA'!$A$1:$R$669,17,0),"NO") -> NO
A102: P&B | B102: 98 | C102: BODEGON LA CANAIMA, C.A | D102: J502230076 | E102: 21 | F102: 10117 | G102: 0,00 | H102: 21 DIAS | I102: No | J102: 45068 | K102: ATD - CCS | L102: CAD.SUPERM | M102: V IVA | N102: roxana.gamez@baratta.com.ve | O102: =IFERROR(VLOOKUP($D102,'CLIENTES NUEVA ID ZONA'!$A$1:$R$669,17,0),"NO") -> NO
A103: P&B | B103: 62 | C103: INVERSIONES NEGOCIAR PLANET L&S, C.A | D103: J405773790 | E103: 20 | F103: 62054 | G103: 0,00 | H103: 21 DIAS | I103: No | J103: 45065 | K103: VENTAS-YAG | L103: DISTRIB. | M103: V IVA | O103: =IFERROR(VLOOKUP($D103,'CLIENTES NUEVA ID ZONA'!$A$1:$R$669,17,0),"NO") -> NO
A104: P&B | B104: 52 | C104: LLOVIZNA MARKET, C.A | D104: J502868585 | E104: 21 | F104: 52108 | G104: 0,00 | H104: PREPAGADO | I104: No | J104: 45064 | K104: VENTAS-YAG | L104: MAYORISTAS | M104: V IVA | N104: mireyapenaloza@prodalcadistribuciones.com | O104: =IFERROR(VLOOKUP($D104,'CLIENTES NUEVA ID ZONA'!$A$1:$R$669,17,0),"NO") -> NO
A105: P&B | B105: 98 | C105: PLANIFICACIÓN MRP | D105: MRP | E105: 01 | F105: PLANIFIC MRP | G105: 0,00 | H105: CONTADO COD | I105: Sí | J105: 45058 | L105: Z-AT.CLIEN | M105: V IVA | O105: =IFERROR(VLOOKUP($D105,'CLIENTES NUEVA ID ZONA'!$A$1:$R$669,17,0),"NO") -> NO
A106: P&B | B106: 12 | C106: DROGUERIA DROSALUD, C.A | D106: J500500955 | E106: 26 | F106: 12042 | G106: 0,00 | H106: PREPAGADO | I106: No | J106: 45043 | K106: VENTAS-YAG | L106: DROGUERIAS | M106: V IVA | O106: =IFERROR(VLOOKUP($D106,'CLIENTES NUEVA ID ZONA'!$A$1:$R$669,17,0),"NO") -> SI
A107: P&B | B107: 98 | C107: REPRESENTACIONES TATI-MAR, C.A. | D107: J302643562 | E107: 20 | F107: 10116 | G107: 0,00 | H107: 15 DIAS | I107: No | J107: 45036 | K107: ATD - CCS | L107: DISTRIB. | M107: V IVA | O107: =IFERROR(VLOOKUP($D107,'CLIENTES NUEVA ID ZONA'!$A$1:$R$669,17,0),"NO") -> NO
A108: P&B | B108: 50 | C108: DIST OSO PANDA, C.A. | D108: J502236694 | E108: 20 | F108: 50090 | G108: 0,00 | H108: 21 DIAS | I108: No | J108: 45028 | K108: ATD - CCS | L108: DISTRIB. | M108: V IVA | N108: unicentrochinaca@gmail.com | O108: =IFERROR(VLOOKUP($D108,'CLIENTES NUEVA ID ZONA'!$A$1:$R$669,17,0),"NO") -> NO
